Workbook

Sheet Detallado de Facturacion1
A1: CUFE | B1: Cliente | C1: Cuenta | D1: Producto | E1: NIC | F1: NIS | G1: Identificación | H1: Nombres | I1: direccion | J1: barrio | K1: Planilla | L1: Grupo empresarial | M1: Nombre Municipio | N1: Cod. Localidad | O1: Ciclo de consumo | P1: Plan de facturación | Q1: Categoría | R1: Subcategoría | S1: Método de análisis | T1: Estado | U1: Año | V1: Mes(es) | W1: Factura | X1: Cuenta de cobro | Y1: Generada el | Z1: Vence el | AA1: Total Cuenta | AB1: Monto facturado | AC1: Subsidio y/o Contribuciones | AD1: Consumo | AE1: VALOR INGRESOS INTERESES | AF1: Valor De Financiaciones | AG1: Cuota | AH1: Interes Financiacion | AI1: TOTAL IMPUESTO | AJ1: Saldo pendiente | AK1: Deuda Total | AL1: Cuentas Vencidas | AM1: Valor_Otros | AN1: Valor Nota | AO1: Valor Movimiento SA | AP1: Valor de pago | AQ1: Valor Movimiento AS | AR1: Fecha de Pago | AS1: CORREO | AT1: MEDIO DE ENVIO | AU1: responsable | AV1: FECHA | AW1: RESPONSABLE
A2: 350df86281db5b15694e51b476565ff1883fd89dc00e172004c6f770c11448e7126108f0fa80511e760eb5424a0a844b | B2: 2744 | C2: 2743 | D2: 2743 | E2: 90256510 | F2: 90256510 | G2: 800099262 | H2: ALCALDIA MUNICIPIO DE SANTIAGO | I2: =VLOOKUP(C2,'mayo-26'!B:H,7,0) -> CARRERA 3 NO. 2-31 | J2: 0 | K2: DF | L2: DF | M2: CÚCUTA MPO | N2: CUCUTA ZONA SUR | O2: 1001 - CICL FACT PARQUE GUAYABAL( 63) | P2: DIS. FINAL Y TRATAMIENTO | Q2: NO RESIDENCIAL - ASEO GP | R2: OFICIAL | S2: AFORO PERMANENTE | T2: Ocupado | U2: 2026 | V2: 6 | W2: 1081874793 | X2: 1081893265 | Y2: 09-06-2026 | Z2: 04-07-2026 | AA2: 824660.64 | AB2: 824660.64 | AC2: 0 | AD2: 17540 | AE2: 0 | AF2: 0 | AG2: 0 | AH2: 0 | AI2: 0 | AJ2: 824660.64 | AK2: 824660.64 | AL2: 0 | AM2: 240385.7 | AN2: 0 | AS2: =VLOOKUP(C2,'mayo-26'!B:AS,44,0) -> TESORERIA@SANTIAGO-NORTEDESANTANDER.GOV.CO | AT2: =VLOOKUP(C2,'mayo-26'!B:AT,45,0) -> CORREO ELECTRONICO CERTIFICADO 472
A3: caf805b515e6ebda323b20de9bf89e5d6848708156d0478096975ead5363d5490a44564c25edabc3291e63adea01ceca | B3: 2748 | C3: 2747 | D3: 2747 | E3: 90256652 | F3: 90256652 | G3: 890503483-2 | H3: ALCALDIA BUCARASICA | I3: =VLOOKUP(C3,'mayo-26'!B:H,7,0) -> CALLE 2 NO. 3-35 | J3: 0 | K3: DF | L3: DF | M3: CÚCUTA MPO | N3: CUCUTA ZONA SUR | O3: 1001 - CICL FACT PARQUE GUAYABAL( 63) | P3: DIS. FINAL Y TRATAMIENTO | Q3: NO RESIDENCIAL - ASEO GP | R3: OFICIAL | S3: AFORO PERMANENTE | T3: Ocupado | U3: 2026 | V3: 6 | W3: 1081874797 | X3: 1081893269 | Y3: 09-06-2026 | Z3: 04-07-2026 | AA3: 893774.16 | AB3: 893774.16 | AC3: 0 | AD3: 19010 | AE3: 0 | AF3: 0 | AG3: 0 | AH3: 0 | AI3: 0 | AJ3: 893774.16 | AK3: 893774.16 | AL3: 0 | AM3: 260532.05 | AN3: 0 | AS3: =VLOOKUP(C3,'mayo-26'!B:AS,44,0) -> HACIENDA@BUCARASICA-NORTEDESANTANDER.GOV.CO | AT3: =VLOOKUP(C3,'mayo-26'!B:AT,45,0) -> CORREO ELECTRONICO CERTIFICADO 472
A4: d65219d66c87f03199cc557f5fba79ae46e40e729068fa919d87434013c8e038ed20f5bf89db573c8862fd1b67e0b970 | B4: 2752 | C4: 2751 | D4: 2751 | E4: 90257710 | F4: 90257710 | G4: 890501876 | H4: MUNICIPIO DE SAN CAYETANO | I4: =VLOOKUP(C4,'mayo-26'!B:H,7,0) -> CARRERA 4 N 3 -61 | J4: 0 | K4: DF | L4: DF | M4: CÚCUTA MPO | N4: CUCUTA ZONA SUR | O4: 1001 - CICL FACT PARQUE GUAYABAL( 63) | P4: DIS. FINAL Y TRATAMIENTO | Q4: NO RESIDENCIAL - ASEO GP | R4: OFICIAL | S4: AFORO PERMANENTE | T4: Ocupado | U4: 2026 | V4: 6 | W4: 1081874799 | X4: 1081893271 | Y4: 09-06-2026 | Z4: 04-07-2026 | AA4: 5626874.9 | AB4: 5626874.9 | AC4: 0 | AD4: 119680 | AE4: 0 | AF4: 0 | AG4: 0 | AH4: 0 | AI4: 0 | AJ4: 5626874.9 | AK4: 10986409 | AL4: 1 | AM4: 1640214.4 | AN4: 0 | AS4: =VLOOKUP(C4,'mayo-26'!B:AS,44,0) -> tesoreria@sancayetano-nortedesantander.gov.co | AT4: =VLOOKUP(C4,'mayo-26'!B:AT,45,0) -> CORREO ELECTRONICO CERTIFICADO 472
A5: cd658a72087c9a44a952156917330b59bde2aef8590acec5041a0f6871c62d6c535bab7c78b3360e475a5c94ed117c37 | B5: 2760 | C5: 2759 | D5: 2759 | E5: 90290491 | F5: 90290491 | G5: 901238264-9 | H5: ADM PUB SERV PUBL DOMICILIA ACU ALC ASEO | I5: =VLOOKUP(C5,'mayo-26'!B:H,7,0) -> CRA 5 6-03 BARR PERPETUO SOCORRO | J5: HERRAN | K5: DF | L5: DF | M5: CÚCUTA MPO | N5: CUCUTA ZONA SUR | O5: 1001 - CICL FACT PARQUE GUAYABAL( 63) | P5: DIS. FINAL Y TRATAMIENTO | Q5: NO RESIDENCIAL - ASEO GP | R5: INDUSTRIAL | S5: AFORO PERMANENTE | T5: Ocupado | U5: 2026 | V5: 6 | W5: 1081874802 | X5: 1081893274 | Y5: 09-06-2026 | Z5: 04-07-2026 | AA5: 489906.72 | AB5: 489906.72 | AC5: 0 | AD5: 10420 | AE5: 0 | AF5: 0 | AG5: 0 | AH5: 0 | AI5: 0 | AJ5: 489906.34 | AK5: 489906.34 | AL5: 0 | AM5: 142806.1 | AN5: 0 | AQ5: 0.38 | AS5: =VLOOKUP(C5,'mayo-26'!B:AS,44,0) -> APCMANOBAHERRAN@GMAIL.COM | AT5: =VLOOKUP(C5,'mayo-26'!B:AT,45,0) -> CORREO ELECTRONICO CERTIFICADO 472
A6: f07e386cc5fce54c23b35dbad28c861238398ee1e12f526fb84c13c35166b320361f8694e9e08c48fe112da98121e05b | B6: 584 | C6: 583 | D6: 583 | E6: 90275668 | F6: 90275668 | G6: 807005252-1 | H6: ECOAMBIENTAL DEL NORTE SAS ESP | I6: =VLOOKUP(C6,'mayo-26'!B:H,7,0) -> CARRERA 7 NO. 3-17 VILLA DEL ROSARIO | J6: SIN DETERMINAR | K6: DF | L6: DF | M6: CÚCUTA MPO | N6: CUCUTA ZONA SUR | O6: 1001 - CICL FACT PARQUE GUAYABAL( 63) | P6: DIS. FINAL Y TRATAMIENTO | Q6: NO RESIDENCIAL - ASEO GP | R6: INDUSTRIAL | S6: AFORO PERMANENTE | T6: Ocupado | U6: 2026 | V6: 6 | W6: 1081874780 | X6: 1081893252 | Y6: 09-06-2026 | Z6: 04-07-2026 | AA6: 10112318 | AB6: 10112318 | AC6: 0 | AD6: 212630 | AE6: 115306.31 | AF6: 0 | AG6: 0 | AH6: 0 | AI6: 0 | AJ6: 10112318 | AK6: 20433676 | AL6: 1 | AM6: 2914094.1 | AN6: 0 | AS6: =VLOOKUP(C6,'mayo-26'!B:AS,44,0) -> ecoambiental807@gmail.com | AT6: =VLOOKUP(C6,'mayo-26'!B:AT,45,0) -> CORREO ELECTRONICO CERTIFICADO 472
A7: fcece3941ddce843aa2003dfeeea1eb9cd2889a0d0b253358d4cf29fd5f671f7cbe70a13a1d94889f76dcb877ec31627 | B7: 2742 | C7: 2741 | D7: 2741 | E7: 90254686 | F7: 90254686 | G7: 807000581-5 | H7: EMPRESAS PUBLICAS MUNICIPALES DE CHINACOTA EMCHINAC | I7: =VLOOKUP(C7,'mayo-26'!B:H,7,0) -> CRA 4A 13-35 BARRIO LAS COLINAS/CHINACOTA | J7: 0 | K7: DF | L7: DF | M7: CÚCUTA MPO | N7: CUCUTA ZONA SUR | O7: 1001 - CICL FACT PARQUE GUAYABAL( 63) | P7: DIS. FINAL Y TRATAMIENTO | Q7: NO RESIDENCIAL - ASEO GP | R7: INDUSTRIAL | S7: AFORO PERMANENTE | T7: Ocupado | U7: 2026 | V7: 6 | W7: 1081874776 | X7: 1081893248 | Y7: 09-06-2026 | Z7: 04-07-2026 | AA7: 12467233 | AB7: 12467233 | AC7: 0 | AD7: 265170 | AE7: 0 | AF7: 0 | AG7: 0 | AH7: 0 | AI7: 0 | AJ7: 12467233 | AK7: 12467233 | AL7: 1 | AM7: 3634154.9 | AN7: 0 | AS7: =VLOOKUP(C7,'mayo-26'!B:AS,44,0) -> EMCHINAC@EMCHINACESP-CHINACOTA.GOV.CO | AT7: =VLOOKUP(C7,'mayo-26'!B:AT,45,0) -> CORREO ELECTRONICO CERTIFICADO 472
A8: 5840f4487b33aa9217b5f28a2ef480ab059183617a9ff3e113865ffb2155b4a606c468f4eb9b06796a39d4a2f2b7f48c | B8: 2746 | C8: 2745 | D8: 2745 | E8: 90256586 | F8: 90256586 | G8: 800099251 | H8: ALCALDIA MUNICIPIO RAGONVALIA | I8: =VLOOKUP(C8,'mayo-26'!B:H,7,0) -> CALLE 6 NO. 2-32 | J8: 0 | K8: DF | L8: DF | M8: CÚCUTA MPO | N8: CUCUTA ZONA SUR | O8: 1001 - CICL FACT PARQUE GUAYABAL( 63) | P8: DIS. FINAL Y TRATAMIENTO | Q8: NO RESIDENCIAL - ASEO GP | R8: OFICIAL | S8: AFORO PERMANENTE | T8: Ocupado | U8: 2026 | V8: 6 | W8: 1081874779 | X8: 1081893251 | Y8: 09-06-2026 | Z8: 04-07-2026 | AA8: 1619231 | AB8: 1619231 | AC8: 0 | AD8: 34440 | AE8: 0 | AF8: 0 | AG8: 0 | AH8: 0 | AI8: 0 | AJ8: 1619231 | AK8: 1619231 | AL8: 0 | AM8: 472000.2 | AN8: 0 | AS8: =VLOOKUP(C8,'mayo-26'!B:AS,44,0) -> HACIENDA@RAGONVALIA-NORTEDESANTANDER.GOV.CO | AT8: =VLOOKUP(C8,'mayo-26'!B:AT,45,0) -> CORREO ELECTRONICO CERTIFICADO 472
A9: fbf1c2dd1c3bb63cfeb263fc2cffdfff24223ebb0853cb1c2f7cbb1163ee8e8160070b275578760e9f52b9dd9b950d2c | B9: 2750 | C9: 2749 | D9: 2749 | E9: 90257708 | F9: 90257708 | G9: 890501981 | H9: MUNICIPIO DE VILLA CARO | I9: =VLOOKUP(C9,'mayo-26'!B:H,7,0) -> PALACIO MPAL VILLA CARO | J9: 0 | K9: DF | L9: DF | M9: CÚCUTA MPO | N9: CUCUTA ZONA SUR | O9: 1001 - CICL FACT PARQUE GUAYABAL( 63) | P9: DIS. FINAL Y TRATAMIENTO | Q9: NO RESIDENCIAL - ASEO GP | R9: OFICIAL | S9: AFORO PERMANENTE | T9: Ocupado | U9: 2026 | V9: 6 | W9: 1081874783 | X9: 1081893255 | Y9: 09-06-2026 | Z9: 04-07-2026 | AA9: 776704.32 | AB9: 776704.32 | AC9: 0 | AD9: 16520 | AE9: 0 | AF9: 0 | AG9: 0 | AH9: 0 | AI9: 0 | AJ9: 776704.32 | AK9: 776704.32 | AL9: 0 | AM9: 226406.6 | AN9: 0 | AS9: =VLOOKUP(C9,'mayo-26'!B:AS,44,0) -> tesoreria@villacaro-nortedesantander.gov.co | AT9: =VLOOKUP(C9,'mayo-26'!B:AT,45,0) -> CORREO ELECTRONICO CERTIFICADO 472
A10: 0ab2cea0dd7008f7b0b898e92f500160638cd18857df01a188e6a854b4c087b2a06cc73bbe6552c4d83cf637474868cb | B10: 2758 | C10: 2757 | D10: 2757 | E10: 90267356 | F10: 90267356 | G10: 890501436-7 | H10: ALCALDIA MUNICIPIO DE ARBOLEDAS | I10: =VLOOKUP(C10,'mayo-26'!B:H,7,0) -> CRA 6 CALLE 2 Y 3 NO 6-25 | J10: 0 | K10: DF | L10: DF | M10: CÚCUTA MPO | N10: CUCUTA ZONA SUR | O10: 1001 - CICL FACT PARQUE GUAYABAL( 63) | P10: DIS. FINAL Y TRATAMIENTO | Q10: NO RESIDENCIAL - ASEO GP | R10: OFICIAL | S10: AFORO PERMANENTE | T10: Ocupado | U10: 2026 | V10: 6 | W10: 1081874788 | X10: 1081893260 | Y10: 09-06-2026 | Z10: 04-07-2026 | AA10: 2356441.9 | AB10: 2356441.9 | AC10: 0 | AD10: 50120 | AE10: 0 | AF10: 0 | AG10: 0 | AH10: 0 | AI10: 0 | AJ10: 2356441.9 | AK10: 2356441.9 | AL10: 0 | AM10: 686894.6 | AN10: 0 | AS10: =VLOOKUP(C10,'mayo-26'!B:AS,44,0) -> tesoreria@arboledas-nortedesantander.gov.co | AT10: =VLOOKUP(C10,'mayo-26'!B:AT,45,0) -> CORREO ELECTRONICO CERTIFICADO 472
A11: e44282796a22a3c031e66db5d49fe2c2fae784aa87e9b7f851586321afb70780dd45a9a5d2bd597ebe3a17aa637ebf16 | B11: 608069 | C11: 502777 | D11: 558548 | G11: 900508526 | H11: EMPRESA DE SOLUCIONES AMBIENTALES PARA COLOMBIA S.A.S E.S.P | I11: =VLOOKUP(C11,'mayo-26'!B:H,7,0) -> KM 7 VDA EL CUCHARO | J11: #N/A | K11: DF | L11: DF | M11: CÚCUTA MPO | N11: CUCUTA DIRECTA | O11: 1001 - CICL FACT PARQUE GUAYABAL( 63) | P11: DIS. FINAL Y TRATAMIENTO | Q11: NO RESIDENCIAL - ASEO GP | R11: COMERCIAL | S11: AFORO PERMANENTE | T11: Ocupado | U11: 2026 | V11: 6 | W11: 1081874792 | X11: 1081893264 | Y11: 09-06-2026 | Z11: 04-07-2026 | AA11: 2611997.4 | AB11: 2611997.4 | AC11: 0 | AD11: 61550 | AE11: 0 | AF11: 0 | AG11: 0 | AH11: 0 | AI11: 0 | AJ11: 2611997.4 | AK11: 2611997.4 | AL11: 0 | AM11: 561705.3 | AN11: 0 | AS11: =VLOOKUP(C11,'mayo-26'!B:AS,44,0) -> empsacol@hotmail.com | AT11: =VLOOKUP(C11,'mayo-26'!B:AT,45,0) -> CORREO ELECTRONICO CERTIFICADO 472
A12: 03e674c3056d416774e2ee5cf3966d4982ed57b24cce717c28350fa3f6b4641c6ab917ada2a71b881deba56073c44fb9 | B12: 602 | C12: 601 | D12: 601 | E12: 90280179 | F12: 90280179 | G12: 13502903 | H12: PUBLICIDAD RINCON | I12: =VLOOKUP(C12,'mayo-26'!B:H,7,0) -> #N/A | J12: #N/A | K12: DF | L12: DF | M12: CÚCUTA MPO | N12: CUCUTA DIRECTA | O12: 1001 - CICL FACT PARQUE GUAYABAL( 63) | P12: DIS. FINAL Y TRATAMIENTO | Q12: NO RESIDENCIAL - ASEO GP | R12: INDUSTRIAL | S12: AFORO PERMANENTE | T12: Ocupado | U12: 2026 | V12: 6 | W12: 1081874773 | X12: 1081893245 | Y12: 09-06-2026 | Z12: 04-07-2026 | AA12: 36495.82 | AB12: 36495.82 | AC12: 0 | AD12: 860 | AE12: 0 | AF12: 0 | AG12: 0 | AH12: 0 | AI12: 0 | AJ12: 36495.82 | AK12: 36495.82 | AL12: 0 | AM12: 7848.36 | AN12: 0 | AS12: =VLOOKUP(C12,'mayo-26'!B:AS,44,0) -> #N/A | AT12: =VLOOKUP(C12,'mayo-26'!B:AT,45,0) -> #N/A
A13: c396fc8fd75811e249bce7f4846ef20d946210752706e77ced56579fda73abe24803f727f135fbcd50c535f34731d3e3 | B13: 2743 | C13: 2742 | D13: 2742 | E13: 90255897 | F13: 90255897 | G13: 890506116-8 | H13: ALCALDIA PAMPLONITA | I13: =VLOOKUP(C13,'mayo-26'!B:H,7,0) -> #N/A | J13: PAMPLONITA | K13: DF | L13: DF | M13: CÚCUTA MPO | N13: CUCUTA ZONA SUR | O13: 1001 - CICL FACT PARQUE GUAYABAL( 63) | P13: DIS. FINAL Y TRATAMIENTO | Q13: NO RESIDENCIAL - ASEO GP | R13: OFICIAL | S13: AFORO PERMANENTE | T13: Ocupado | U13: 2026 | V13: 6 | W13: 1081874778 | X13: 1081893250 | Y13: 09-06-2026 | Z13: 04-07-2026 | AA13: 279275.04 | AB13: 279275.04 | AC13: 0 | AD13: 5940 | AE13: 0 | AF13: 0 | AG13: 0 | AH13: 0 | AI13: 0 | AJ13: 279275.04 | AK13: 279275.04 | AL13: 0 | AM13: 81407.7 | AN13: 0 | AS13: =VLOOKUP(C13,'mayo-26'!B:AS,44,0) -> serviciospublicos@pamplonita-nortedesantander.gov.co | AT13: =VLOOKUP(C13,'mayo-26'!B:AT,45,0) -> CORREO ELECTRONICO CERTIFICADO 472
A14: bbc396954ae12cd5a12e4232596af9e097d3c4dc4da740d6a7acd7d8831bf3b1352cea3f9b5f830138cbc4e4490ad08e | B14: 2747 | C14: 2746 | D14: 2746 | E14: 90256627 | F14: 90256627 | G14: 800099237 | H14: EMPODURANIA | I14: =VLOOKUP(C14,'mayo-26'!B:H,7,0) -> AVENIDA 2 NO. 8-57 | J14: 0 | K14: DF | L14: DF | M14: CÚCUTA MPO | N14: CUCUTA ZONA SUR | O14: 1001 - CICL FACT PARQUE GUAYABAL( 63) | P14: DIS. FINAL Y TRATAMIENTO | Q14: NO RESIDENCIAL - ASEO GP | R14: INDUSTRIAL | S14: AFORO PERMANENTE | T14: Ocupado | U14: 2026 | V14: 6 | W14: 1081874781 | X14: 1081893253 | Y14: 09-06-2026 | Z14: 04-07-2026 | AA14: 2183423 | AB14: 2183423 | AC14: 0 | AD14: 46440 | AE14: 0 | AF14: 0 | AG14: 0 | AH14: 0 | AI14: 0 | AJ14: 105592.04 | AK14: 105592.04 | AL14: 0 | AM14: 636460.2 | AN14: 0 | AQ14: 2077831 | AS14: =VLOOKUP(C14,'mayo-26'!B:AS,44,0) -> CONTACTENOS@DURANIA-NORTEDESANTANDER.GOV.CO | AT14: =VLOOKUP(C14,'mayo-26'!B:AT,45,0) -> CORREO ELECTRONICO CERTIFICADO 472
A15: 033afab33dd33beba8a8b4700f911794905b7b5f5829644e8df048261057d6fbcf86eb7fba6c644b072ea45c6388fafb | B15: 2751 | C15: 2750 | D15: 2750 | E15: 90257709 | F15: 90257709 | G15: 890501404 | H15: MUNICIPIO DE GRAMALOTE | I15: =VLOOKUP(C15,'mayo-26'!B:H,7,0) -> CARRERA 5 NO 7 ¿ 72 | J15: 0 | K15: DF | L15: DF | M15: CÚCUTA MPO | N15: CUCUTA ZONA SUR | O15: 1001 - CICL FACT PARQUE GUAYABAL( 63) | P15: DIS. FINAL Y TRATAMIENTO | Q15: NO RESIDENCIAL - ASEO GP | R15: OFICIAL | S15: AFORO PERMANENTE | T15: Ocupado | U15: 2026 | V15: 6 | W15: 1081874785 | X15: 1081893257 | Y15: 09-06-2026 | Z15: 04-07-2026 | AA15: 2156153.8 | AB15: 2156153.8 | AC15: 0 | AD15: 45860 | AE15: 0 | AF15: 0 | AG15: 0 | AH15: 0 | AI15: 0 | AJ15: 2156153.8 | AK15: 2156153.8 | AL15: 0 | AM15: 628511.3 | AN15: 0 | AS15: =VLOOKUP(C15,'mayo-26'!B:AS,44,0) -> TESORERIA@GRAMALOTE-NORTEDESANTANDER.GOV.CO | AT15: =VLOOKUP(C15,'mayo-26'!B:AT,45,0) -> CORREO ELECTRONICO CERTIFICADO 472
A16: 0697dffc97c87f25ba397afcd4c5ea4c6477c7e2a14c377a6ba26bb2e3925da64815ec4abf1d222ec98c718a20c6514e | B16: 2755 | C16: 2754 | D16: 2754 | E16: 90257713 | F16: 90257713 | G16: 890502611 | H16: MUNICIPIO DE LOURDES | I16: =VLOOKUP(C16,'mayo-26'!B:H,7,0) -> CARRERA 4 CON CALLE 3 ¿ 36 | J16: 0 | K16: DF | L16: DF | M16: CÚCUTA MPO | N16: CUCUTA ZONA SUR | O16: 1001 - CICL FACT PARQUE GUAYABAL( 63) | P16: DIS. FINAL Y TRATAMIENTO | Q16: NO RESIDENCIAL - ASEO GP | R16: OFICIAL | S16: AFORO PERMANENTE | T16: Ocupado | U16: 2026 | V16: 6 | W16: 1081874789 | X16: 1081893261 | Y16: 09-06-2026 | Z16: 04-07-2026 | AA16: 2158974.7 | AB16: 2158974.7 | AC16: 0 | AD16: 45920 | AE16: 0 | AF16: 0 | AG16: 0 | AH16: 0 | AI16: 0 | AJ16: 2158974.7 | AK16: 2158974.7 | AL16: 0 | AM16: 629333.6 | AN16: 0 | AS16: =VLOOKUP(C16,'mayo-26'!B:AS,44,0) -> TESORERIA@LOURDES-NORTEDESANTANDER.GOV.CO | AT16: =VLOOKUP(C16,'mayo-26'!B:AT,45,0) -> CORREO ELECTRONICO CERTIFICADO 472
A17: ba0e1392a34c56a913f413bf4ed1e71c2ca2658a83c03ed5586fca35d46e5320961a354840cc60e4715478392c0d733b | B17: 2293 | C17: 2292 | D17: 2292 | E17: 90265701 | F17: 90265701 | G17: 890501301-1 | H17: SOCIEDAD MEJORAS PUBLICAS DE CUCUTA | I17: =VLOOKUP(C17,'mayo-26'!B:H,7,0) -> CALLE 4AN # 4-89 PESCADERO | J17: PESCADERO | K17: DF | L17: DF | M17: CÚCUTA MPO | N17: CUCUTA DIRECTA | O17: 1001 - CICL FACT PARQUE GUAYABAL( 63) | P17: DIS. FINAL Y TRATAMIENTO | Q17: NO RESIDENCIAL - ASEO GP | R17: INDUSTRIAL | S17: AFORO PERMANENTE | T17: Ocupado | U17: 2026 | V17: 6 | W17: 1081874784 | X17: 1081893256 | Y17: 09-06-2026 | Z17: 04-07-2026 | AA17: 3055888.4 | AB17: 3055888.4 | AC17: 0 | AD17: 72010 | AE17: 0 | AF17: 0 | AG17: 0 | AH17: 0 | AI17: 0 | AJ17: 3055888.4 | AK17: 3055888.4 | AL17: 0 | AM17: 657163.26 | AN17: 0 | AS17: =VLOOKUP(C17,'mayo-26'!B:AS,44,0) -> contacto@smpcucuta.com | AT17: =VLOOKUP(C17,'mayo-26'!B:AT,45,0) -> CORREO ELECTRONICO CERTIFICADO 472
A18: 40e7d18a76330c0d03c5b075533c401d73e2e3b7d02e458b9b702b2ab10f0b8a9343853801ff0acdf7b86e8c20af0ae6 | B18: 2741 | C18: 2740 | D18: 2740 | E18: 90253728 | F18: 90253728 | G18: 800250853-1 | H18: ALCALDIA MUNICIPAL PUERTO SANT | I18: =VLOOKUP(C18,'mayo-26'!B:H,7,0) -> CARERA 2 NO. 2-35 | J18: 0 | K18: DF | L18: DF | M18: CÚCUTA MPO | N18: CUCUTA ZONA SUR | O18: 1001 - CICL FACT PARQUE GUAYABAL( 63) | P18: DIS. FINAL Y TRATAMIENTO | Q18: NO RESIDENCIAL - ASEO GP | R18: OFICIAL | S18: AFORO PERMANENTE | T18: Ocupado | U18: 2026 | V18: 6 | W18: 1081874786 | X18: 1081893258 | Y18: 09-06-2026 | Z18: 04-07-2026 | AA18: 4691256.5 | AB18: 4691256.5 | AC18: 0 | AD18: 99780 | AE18: 0 | AF18: 0 | AG18: 0 | AH18: 0 | AI18: 0 | AJ18: 4691256.5 | AK18: 4691256.5 | AL18: 0 | AM18: 1367484.9 | AN18: 0 | AS18: =VLOOKUP(C18,'mayo-26'!B:AS,44,0) -> TESORERIA@PUERTOSANTANDER-NORTEDESANTANDER.GOV.CO | AT18: =VLOOKUP(C18,'mayo-26'!B:AT,45,0) -> CORREO ELECTRONICO CERTIFICADO 472
A19: 511cc5f8215fbac624389cbc6be81486fd02b113fbb5ee5cc52d18ea4b450c5a667379322d02c4970f692d93114d51fa | B19: 2745 | C19: 2744 | D19: 2744 | E19: 90256525 | F19: 90256525 | G19: 800099263-8 | H19: MUNICIPIO DE SARDINATA | I19: =VLOOKUP(C19,'mayo-26'!B:H,7,0) -> CALLE 6 NO. 6 55 CENTRO SARDINATA | J19: 0 | K19: DF | L19: DF | M19: CÚCUTA MPO | N19: CUCUTA ZONA SUR | O19: 1001 - CICL FACT PARQUE GUAYABAL( 63) | P19: DIS. FINAL Y TRATAMIENTO | Q19: NO RESIDENCIAL - ASEO GP | R19: OFICIAL | S19: AFORO PERMANENTE | T19: Ocupado | U19: 2026 | V19: 6 | W19: 1081874791 | X19: 1081893263 | Y19: 09-06-2026 | Z19: 04-07-2026 | AA19: 11533965 | AB19: 11533965 | AC19: 0 | AD19: 245320 | AE19: 0 | AF19: 0 | AG19: 0 | AH19: 0 | AI19: 0 | AJ19: 11533965 | AK19: 11533965 | AL19: 0 | AM19: 3362110.6 | AN19: 0 | AS19: =VLOOKUP(C19,'mayo-26'!B:AS,44,0) | AT19: =VLOOKUP(C19,'mayo-26'!B:AT,45,0) -> CORREO ELECTRONICO CERTIFICADO 472
A20: 9e0f72d6ac1ca8dea3e73c892ea804001cd75eb41d2bf51dd9dc345e3baff3e40d17cc767e94091784f9b0d6b688a388 | B20: 2749 | C20: 2748 | D20: 2748 | E20: 90257658 | F20: 90257658 | G20: 890501549 | H20: MPIO DE SALAZAR DE LAS PALMAS | I20: =VLOOKUP(C20,'mayo-26'!B:H,7,0) -> CALLE 2 CARRERA 6 ESQUINA | J20: 0 | K20: DF | L20: DF | M20: CÚCUTA MPO | N20: CUCUTA ZONA SUR | O20: 1001 - CICL FACT PARQUE GUAYABAL( 63) | P20: DIS. FINAL Y TRATAMIENTO | Q20: NO RESIDENCIAL - ASEO GP | R20: INDUSTRIAL | S20: AFORO PERMANENTE | T20: Ocupado | U20: 2026 | V20: 6 | W20: 1081874796 | X20: 1081893268 | Y20: 09-06-2026 | Z20: 04-07-2026 | AA20: 3698278.6 | AB20: 3698278.6 | AC20: 0 | AD20: 78660 | AE20: 0 | AF20: 0 | AG20: 0 | AH20: 0 | AI20: 0 | AJ20: 3698278.6 | AK20: 3698279.2 | AL20: 1 | AM20: 1078035.3 | AN20: 0 | AS20: =VLOOKUP(C20,'mayo-26'!B:AS,44,0) -> HACIENDA@SALAZARDELASPALMAS-NORTEDESANTANDER.GOV.CO | AT20: =VLOOKUP(C20,'mayo-26'!B:AT,45,0) -> CORREO ELECTRONICO CERTIFICADO 472
A21: 235eb13c11bfae5cc864908b4cc63d0454ae6fcb88e5730d02bc3f78058c0107e8f05a4ad17d2e28b68340b98042d407 | B21: 2753 | C21: 2752 | D21: 2752 | E21: 90257711 | F21: 90257711 | G21: 807002043 | H21: EMZULIA E.S.P | I21: =VLOOKUP(C21,'mayo-26'!B:H,7,0) -> CLL 7 NO 2-03 BARRIO CENTRO MUNICIPIO EL ZULIA | J21: 0 | K21: DF | L21: DF | M21: CÚCUTA MPO | N21: CUCUTA ZONA SUR | O21: 1001 - CICL FACT PARQUE GUAYABAL( 63) | P21: DIS. FINAL Y TRATAMIENTO | Q21: NO RESIDENCIAL - ASEO GP | R21: INDUSTRIAL | S21: AFORO PERMANENTE | T21: Ocupado | U21: 2026 | V21: 6 | W21: 1081874798 | X21: 1081893270 | Y21: 09-06-2026 | Z21: 04-07-2026 | AA21: 23217911 | AB21: 23217911 | AC21: 0 | AD21: 493830 | AE21: 0 | AF21: 0 | AG21: 0 | AH21: 0 | AI21: 0 | AJ21: 23217911 | AK21: 23217912 | AL21: 1 | AM21: 6767940.2 | AN21: 0 | AS21: =VLOOKUP(C21,'mayo-26'!B:AS,44,0) -> emzulia.esp@gmail.com | AT21: =VLOOKUP(C21,'mayo-26'!B:AT,45,0) -> CORREO ELECTRONICO CERTIFICADO 472
A22: b015e76d8cd7b4283b2939c11b585a598e48edb0c3ed9d90d84a944d35fd2d244a5300a176f5e84c922414850d6c5f68 | B22: 2757 | C22: 2756 | D22: 2756 | E22: 90257826 | F22: 90257826 | G22: 890505662 | H22: MUNICIPIO DE BOCHALEMA | I22: =VLOOKUP(C22,'mayo-26'!B:H,7,0) -> CALLE 3 NO 3 - 08 | J22: 0 | K22: DF | L22: DF | M22: CÚCUTA MPO | N22: CUCUTA ZONA SUR | O22: 1001 - CICL FACT PARQUE GUAYABAL( 63) | P22: DIS. FINAL Y TRATAMIENTO | Q22: NO RESIDENCIAL - ASEO GP | R22: OFICIAL | S22: AFORO PERMANENTE | T22: Ocupado | U22: 2026 | V22: 6 | W22: 1081874803 | X22: 1081893275 | Y22: 09-06-2026 | Z22: 04-07-2026 | AA22: 4604747 | AB22: 4604747 | AC22: 0 | AD22: 97940 | AE22: 0 | AF22: 0 | AG22: 0 | AH22: 0 | AI22: 0 | AJ22: 4604747 | AK22: 4604747 | AL22: 0 | AM22: 1342267.7 | AN22: 0 | AS22: =VLOOKUP(C22,'mayo-26'!B:AS,44,0) -> UNISEPUBLICOS@BOCHALEMA-NORTEDESANTANDER.GOV.CO | AT22: =VLOOKUP(C22,'mayo-26'!B:AT,45,0) -> CORREO ELECTRONICO CERTIFICADO 472
A23: 7e3cc58fe6b22654849ce56d89fa529dd13986e13f68b2bf91497a458ead91d23947a6da9321dffcede2f195fb007c1b | B23: 433 | C23: 432 | D23: 432 | E23: 90253757 | F23: 90253757 | G23: 901347799 | H23: CURTIEMBRES CUCUTA SAS NIT.901.347.799-4 | I23: =VLOOKUP(C23,'mayo-26'!B:H,7,0) -> KM 6 #49-40 VIA SAUFASTINO EL SERRITO | J23: SIN DETERMINAR | K23: DF | L23: DF | M23: CÚCUTA MPO | N23: CUCUTA ZONA SUR | O23: 1001 - CICL FACT PARQUE GUAYABAL( 63) | P23: DIS. FINAL Y TRATAMIENTO | Q23: NO RESIDENCIAL - ASEO GP | R23: INDUSTRIAL | S23: AFORO PERMANENTE | T23: Ocupado | U23: 2026 | V23: 6 | W23: 1081874774 | X23: 1081893246 | Y23: 09-06-2026 | Z23: 04-07-2026 | AA23: 614063.39 | AB23: 614063.39 | AC23: 0 | AD23: 14470 | AE23: 0 | AF23: 0 | AG23: 0 | AH23: 0 | AI23: 0 | AJ23: 614063.39 | AK23: 614063.39 | AL23: 0 | AM23: 132053.22 | AN23: 0 | AS23: =VLOOKUP(C23,'mayo-26'!B:AS,44,0) -> CURTIEMBRESCUCUTA@GMAIL.COM | AT23: =VLOOKUP(C23,'mayo-26'!B:AT,45,0) -> CORREO ELECTRONICO CERTIFICADO 472
A24: 154e3276a2ee5be1e3c79d217014c51aa63cda4541f438f01d82a53c92d5c569623190fdf4e7d4b601852399c3ae8a75 | B24: 505 | C24: 504 | D24: 504 | E24: 90268059 | F24: 90268059 | G24: 60366490 | H24: NATALIA ANDREA ROJAS | I24: =VLOOKUP(C24,'mayo-26'!B:H,7,0) -> CLL 21 0E- 20 CAOBOS | J24: BARRIO BLANCO | K24: DF | L24: DF | M24: CÚCUTA MPO | N24: CUCUTA DIRECTA | O24: 1001 - CICL FACT PARQUE GUAYABAL( 63) | P24: DIS. FINAL Y TRATAMIENTO | Q24: NO RESIDENCIAL - ASEO GP | R24: INDUSTRIAL | S24: AFORO PERMANENTE | T24: Ocupado | U24: 2026 | V24: 6 | W24: 1081874775 | X24: 1081893247 | Y24: 09-06-2026 | Z24: 04-07-2026 | AA24: 891328.21 | AB24: 891328.21 | AC24: 0 | AD24: 20240 | AE24: 32403.33 | AF24: 0 | AG24: 0 | AH24: 0 | AI24: 0 | AJ24: 891328.21 | AK24: 2500616.3 | AL24: 3 | AM24: 184710.24 | AN24: 0 | AS24: =VLOOKUP(C24,'mayo-26'!B:AS,44,0) -> NAROHE10@HOTMAIL.COM | AT24: =VLOOKUP(C24,'mayo-26'!B:AT,45,0) -> CORREO ELECTRONICO CERTIFICADO 472
A25: 96c389aa258a0a1e4cd305479a4718bec257a95d6e29eed1e69122ea8db40bfb3841511a7e4b84e15a2e854ac9594eef | B25: 605804 | C25: 502000 | D25: 557773 | G25: 901951147 | H25: ASEOCATATUMBO S.A.S. ESP | I25: =VLOOKUP(C25,'mayo-26'!B:H,7,0) -> #N/A | J25: #N/A | K25: DF | L25: DF | M25: CÚCUTA MPO | N25: CUCUTA DIRECTA | O25: 1001 - CICL FACT PARQUE GUAYABAL( 63) | P25: ASEO INTEGRAL | Q25: NO RESIDENCIAL - ASEO GP | R25: COMERCIAL | S25: AFORO PERMANENTE | T25: Ocupado | U25: 2026 | V25: 6 | W25: 1081884177 | X25: 1081902670 | Y25: 09-06-2026 | Z25: 04-07-2026 | AA25: 4405399 | AB25: 4405399 | AC25: 0 | AD25: 0 | AE25: 0 | AF25: 0 | AG25: 0 | AH25: 0 | AI25: 0 | AJ25: 4405387.9 | AK25: 4405387.9 | AL25: 0 | AM25: 1284158 | AN25: 0 | AQ25: 11.13 | AS25: =VLOOKUP(C25,'mayo-26'!B:AS,44,0) -> #N/A | AT25: =VLOOKUP(C25,'mayo-26'!B:AT,45,0) -> #N/A
A26: c65c098c83979c0954e821249927b3f03859ea922b24b959ecd3a85e56bd4096fd7c8ca057f8ad912014d3fc855a5bd8 | B26: 285191 | C26: 217711 | D26: 217711 | E26: 40520 | F26: 40520 | G26: 900276962 | H26: D1 S A S | I26: =VLOOKUP(C26,'mayo-26'!B:H,7,0) -> KDX 73-2 1116 | J26: ATALAYA | K26: =VLOOKUP(C26,'mayo-26'!B:J,9,0) -> NO | L26: =VLOOKUP(C26,'mayo-26'!B:K,10,0) -> D1 | M26: CÚCUTA MPO | N26: CUCUTA DIRECTA | O26: 1002 - CICL FACT DIRECTA CUCUTA NORTE | P26: ASEO INTEGRAL | Q26: NO RESIDENCIAL - ASEO PP | R26: COMERCIAL RANGO 3 | S26: NO AFORADO | T26: Ocupado | U26: 2026 | V26: 6 | W26: 1081875085 | X26: 1081893557 | Y26: 46182 | Z26: 46207 | AA26: 113128.5 | AB26: 113128.5 | AC26: 37709.5 | AD26: 0 | AE26: 0 | AF26: 0 | AG26: 0 | AH26: 0 | AI26: 0 | AJ26: 113128.5 | AK26: 113128.5 | AL26: 0 | AM26: 376.2 | AN26: 0 | AS26: =VLOOKUP(C26,'mayo-26'!B:AS,44,0) -> ALBA.CELIS@D1.COM.CO;CARMEN.DAVILA@D1.COM.CO | AT26: =VLOOKUP(C26,'mayo-26'!B:AT,45,0) -> CORREO ELECTRONICO CERTIFICADO 472
A27: f49ba4dc8e59c729460cb7b7e099ba9f1abbbc0549519975e81657efd0635c24bff686c0875762014a2ffaa0e6df49f7 | B27: 297 | C27: 223223 | D27: 223223 | E27: 46258 | F27: 46258 | G27: 807004352-3 | H27: EMPRESA SOCIAL DEL ESTADO E.S.E IMSALUD | I27: =VLOOKUP(C27,'mayo-26'!B:H,7,0) -> AVE 4 17-89 - 0239431 | J27: ANTONIA SANTOS | K27: =VLOOKUP(C27,'mayo-26'!B:J,9,0) -> NO | L27: =VLOOKUP(C27,'mayo-26'!B:K,10,0) -> IMSALUD | M27: CÚCUTA MPO | N27: CUCUTA ZONA NORTE | O27: 1002 - CICL FACT DIRECTA CUCUTA NORTE | P27: ASEO INTEGRAL | Q27: NO RESIDENCIAL - ASEO PP | R27: OFICIAL RANGO 2 | S27: NO AFORADO | T27: Ocupado | U27: 2026 | V27: 6 | W27: 1081875089 | X27: 1081893561 | Y27: 46182 | Z27: 46207 | AA27: 62832 | AB27: 62832 | AC27: 0 | AD27: 0 | AE27: 0 | AF27: 0 | AG27: 0 | AH27: 0 | AI27: 0 | AJ27: 62832 | AK27: 62832 | AL27: 0 | AM27: 250.8 | AN27: 0 | AS27: =VLOOKUP(C27,'mayo-26'!B:AS,44,0) -> SUBFINANCIERA@IMSALUD.GOV.CO | AT27: =VLOOKUP(C27,'mayo-26'!B:AT,45,0) -> CORREO ELECTRONICO CERTIFICADO 472
A28: d2c80bf90fd2913c04fe311d779982fc801f62df2fba50f7698345193b304f7454850768fd0a8ddfe0747c380b1f7547 | B28: 699 | C28: 225199 | D28: 225199 | E28: 48272 | F28: 48272 | G28: 900480569 | H28: JERONIMO MARTINS COLOMBIA SAS | I28: =VLOOKUP(C28,'mayo-26'!B:H,7,0) -> CLL 12 4-52 CENTRO | J28: NIÑA CECI | K28: =VLOOKUP(C28,'mayo-26'!B:J,9,0) -> NO | L28: =VLOOKUP(C28,'mayo-26'!B:K,10,0) -> ARA CUCUTA | M28: CÚCUTA MPO | N28: CUCUTA ZONA NORTE | O28: 1002 - CICL FACT DIRECTA CUCUTA NORTE | P28: ASEO INTEGRAL | Q28: NO RESIDENCIAL - ASEO GP | R28: COMERCIAL | S28: AFORO ORDINARIO-EXTRAORDINARIO | T28: Ocupado | U28: 2026 | V28: 6 | W28: 1081875094 | X28: 1081893566 | Y28: 46182 | Z28: 46207 | AA28: 679277.47 | AB28: 679277.47 | AC28: 226425.83 | AD28: 2188 | AE28: 0 | AF28: 0 | AG28: 0 | AH28: 0 | AI28: 0 | AJ28: 679277.47 | AK28: 1359480.2 | AL28: 1 | AM28: 376.2 | AN28: 0 | AS28: =VLOOKUP(C28,'mayo-26'!B:AS,44,0) -> COORDINADOR.OPERACIONES.R11@JERONIMO-MARTINS.COM | AT28: =VLOOKUP(C28,'mayo-26'!B:AT,45,0) -> CORREO ELECTRONICO CERTIFICADO 472
A29: f794264a9dca82c39a72c392925416389fee7f8d79c375c8b7261ea454e9a351a18d865e387c8958e072886219fae897 | B29: 141 | C29: 237851 | D29: 237851 | E29: 307920 | F29: 307920 | G29: 890500514 | H29: CENTRALES ELECTRICAS DEL NORTE DE SANTANDER S.A. EMPRESA DE SERVICIOS PUBLICOS | I29: =VLOOKUP(C29,'mayo-26'!B:H,7,0) -> AV 2 CALLE 39 LIBERTAD | J29: SEVILLA | K29: =VLOOKUP(C29,'mayo-26'!B:J,9,0) -> NO | L29: =VLOOKUP(C29,'mayo-26'!B:K,10,0) -> CENS | M29: CÚCUTA MPO | N29: CUCUTA ZONA NORTE | O29: 1002 - CICL FACT DIRECTA CUCUTA NORTE | P29: ASEO INTEGRAL | Q29: NO RESIDENCIAL - ASEO GP | R29: COMERCIAL | S29: AFORO PERMANENTE | T29: Ocupado | U29: 2026 | V29: 6 | W29: 1081875098 | X29: 1081893570 | Y29: 46182 | Z29: 46207 | AA29: 728415.9 | AB29: 728415.9 | AC29: 242805.31 | AD29: 2360.63 | AE29: 0 | AF29: 0 | AG29: 0 | AH29: 0 | AI29: 0 | AJ29: 728415.9 | AK29: 728415.9 | AL29: 0 | AM29: 376.2 | AN29: 0 | AS29: =VLOOKUP(C29,'mayo-26'!B:AS,44,0) -> FACTURAELECTRONICACENS@GRUPO-EPM.COM | AT29: =VLOOKUP(C29,'mayo-26'!B:AT,45,0) -> CORREO ELECTRONICO CERTIFICADO 472
A30: abe476565549d3b780b314abf5f43e7a813492f4d2115327e5fab8ceae29acfd08cb332c3db99ad29933a01752545e77 | B30: 455370 | C30: 267583 | D30: 267583 | E30: 661467 | F30: 661467 | G30: 890501434- 2 | H30: MUNICIPIO DE SAN JOSE DE CUCUTA - SEDE TONCHALA | I30: =VLOOKUP(C30,'mayo-26'!B:H,7,0) -> CALLE 10 NO 0E-16 EDF CENTRO EMPRESARIAL BLOQUE B HOTEL TONCHALA | J30: LA PRIMAVERA | K30: =VLOOKUP(C30,'mayo-26'!B:J,9,0) -> NO | L30: =VLOOKUP(C30,'mayo-26'!B:K,10,0) -> COLEGIOS ZONA NORTE | M30: CÚCUTA MPO | N30: CUCUTA ZONA NORTE | O30: 1002 - CICL FACT DIRECTA CUCUTA NORTE | P30: ASEO INTEGRAL | Q30: NO RESIDENCIAL - ASEO PP | R30: OFICIAL RANGO 3 | S30: NO AFORADO | T30: Ocupado | U30: 2026 | V30: 6 | W30: 1081875102 | X30: 1081893574 | Y30: 46182 | Z30: 46207 | AA30: 75419 | AB30: 75419 | AC30: 0 | AD30: 0 | AE30: 0 | AF30: 0 | AG30: 0 | AH30: 0 | AI30: 0 | AJ30: 75419 | AK30: 82922 | AL30: 1 | AM30: 250.8 | AN30: 0 | AS30: =VLOOKUP(C30,'mayo-26'!B:AS,44,0) -> AREAFINANCIERA@SEMCUCUTA.GOV.CO | AT30: =VLOOKUP(C30,'mayo-26'!B:AT,45,0) -> CARTERA
A31: cf8048c7c550050a32f66cb59fad4752d8557c36abafef23c528d334d048679adada563ded0b77b5f6448cab7d196055 | B31: 269532 | C31: 269531 | D31: 269531 | E31: 676425 | F31: 676425 | G31: 900117563-3 | H31: COMPAÑIA MINERA CERRO TASAJERO SA- | I31: =VLOOKUP(C31,'mayo-26'!B:H,7,0) -> CERRO TASAJERO- VIA SAN FAUSTINO | J31: VDA PASO DE LOS RIOS | K31: =VLOOKUP(C31,'mayo-26'!B:J,9,0) -> NO | L31: =VLOOKUP(C31,'mayo-26'!B:K,10,0) -> NO | M31: CÚCUTA MPO | N31: CUCUTA DIRECTA | O31: 1002 - CICL FACT DIRECTA CUCUTA NORTE | P31: ASEO INTEGRAL | Q31: NO RESIDENCIAL - ASEO PP | R31: COMERCIAL RANGO 3 | S31: NO AFORADO | T31: Ocupado | U31: 2026 | V31: 6 | W31: 1081875106 | X31: 1081893578 | Y31: 46182 | Z31: 46207 | AA31: 113128.5 | AB31: 113128.5 | AC31: 37709.5 | AD31: 0 | AE31: 0 | AF31: 0 | AG31: 0 | AH31: 0 | AI31: 0 | AJ31: 113128.5 | AK31: 113128.5 | AL31: 0 | AM31: 376.2 | AN31: 0 | AS31: =VLOOKUP(C31,'mayo-26'!B:AS,44,0) -> FACTURACIONEMNFC@HOTMAIL.COM | AT31: =VLOOKUP(C31,'mayo-26'!B:AT,45,0) -> CORREO ELECTRONICO CERTIFICADO 472
A32: c012604be3ccb4319ac41d67bce25ab8d36a5996952472285331425bd3bbf6850510b6d3c07d7cd0820739e6a6c0f1d1 | B32: 699 | C32: 274211 | D32: 274211 | E32: 1731 | F32: 1731 | G32: 900480569 | H32: JERONIMO MARTINS COLOMBIA SAS | I32: =VLOOKUP(C32,'mayo-26'!B:H,7,0) -> CLL 12 4-52 CENTRO | J32: BELEN | K32: =VLOOKUP(C32,'mayo-26'!B:J,9,0) -> NO | L32: =VLOOKUP(C32,'mayo-26'!B:K,10,0) -> ARA CUCUTA | M32: CÚCUTA MPO | N32: CUCUTA ZONA NORTE | O32: 1002 - CICL FACT DIRECTA CUCUTA NORTE | P32: ASEO INTEGRAL | Q32: NO RESIDENCIAL - ASEO GP | R32: COMERCIAL | S32: AFORO ORDINARIO-EXTRAORDINARIO | T32: Ocupado | U32: 2026 | V32: 6 | W32: 1081875109 | X32: 1081893581 | Y32: 46182 | Z32: 46207 | AA32: 484707.7 | AB32: 484707.7 | AC32: 158774.97 | AD32: 1475 | AE32: 8382.82 | AF32: 0 | AG32: 0 | AH32: 0 | AI32: 0 | AJ32: 484707.7 | AK32: 961907.56 | AL32: 1 | AM32: 376.2 | AN32: 0 | AS32: =VLOOKUP(C32,'mayo-26'!B:AS,44,0) -> COORDINADOR.OPERACIONES.R11@JERONIMO-MARTINS.COM | AT32: =VLOOKUP(C32,'mayo-26'!B:AT,45,0) -> CORREO ELECTRONICO CERTIFICADO 472
A33: 2b00456968c64348e6a57be6ec661ecbd1f1a392ea7702d524389261c0059d80904f9087d668aeabfbf515175532e76a | B33: 699 | C33: 276691 | D33: 276691 | E33: 18151 | F33: 18151 | G33: 900480569 | H33: JERONIMO MARTINS COLOMBIA SAS | I33: =VLOOKUP(C33,'mayo-26'!B:H,7,0) -> CLL 12 4-52 CENTRO | J33: SAN MIGUEL | K33: =VLOOKUP(C33,'mayo-26'!B:J,9,0) -> NO | L33: =VLOOKUP(C33,'mayo-26'!B:K,10,0) -> ARA CUCUTA | M33: CÚCUTA MPO | N33: CUCUTA ZONA NORTE | O33: 1002 - CICL FACT DIRECTA CUCUTA NORTE | P33: ASEO INTEGRAL | Q33: NO RESIDENCIAL - ASEO GP | R33: COMERCIAL | S33: AFORO ORDINARIO-EXTRAORDINARIO | T33: Ocupado | U33: 2026 | V33: 6 | W33: 1081875115 | X33: 1081893587 | Y33: 46182 | Z33: 46207 | AA33: 359246.29 | AB33: 359246.29 | AC33: 119209.17 | AD33: 1058 | AE33: 1618.8 | AF33: 0 | AG33: 0 | AH33: 0 | AI33: 0 | AJ33: 359246.29 | AK33: 717719.36 | AL33: 1 | AM33: 376.2 | AN33: 0 | AS33: =VLOOKUP(C33,'mayo-26'!B:AS,44,0) -> COORDINADOR.OPERACIONES.R11@JERONIMO-MARTINS.COM | AT33: =VLOOKUP(C33,'mayo-26'!B:AT,45,0) -> CORREO ELECTRONICO CERTIFICADO 472
A34: e0b72d379a22f8a196ac2e59fa43a6c5c4b848a7460ae8b4c67ea0e582e711bc9d72be7101f7a7a875c14e84d75169ed | B34: 280920 | C34: 279767 | D34: 279767 | E34: 24737 | F34: 24737 | G34: 900576569 | H34: SUPERMERCADO BETEL PLUSS | I34: =VLOOKUP(C34,'mayo-26'!B:H,7,0) -> AVE 12 5AN-84 1142 | J34: CALLEJON | K34: =VLOOKUP(C34,'mayo-26'!B:J,9,0) -> NO | L34: =VLOOKUP(C34,'mayo-26'!B:K,10,0) -> BETEL | M34: CÚCUTA MPO | N34: CUCUTA DIRECTA | O34: 1002 - CICL FACT DIRECTA CUCUTA NORTE | P34: ASEO INTEGRAL | Q34: NO RESIDENCIAL - ASEO PP | R34: COMERCIAL RANGO 3 | S34: NO AFORADO | T34: Desocupado | U34: 2026 | V34: 6 | W34: 1081875120 | X34: 1081893592 | Y34: 46182 | Z34: 46207 | AA34: 91936.97 | AB34: 91936.97 | AC34: 18616 | AD34: 0 | AE34: 36088.97 | AF34: 0 | AG34: 0 | AH34: 0 | AI34: 0 | AJ34: 91936.97 | AK34: 2133376.2 | AL34: 15 | AM34: 376.2 | AN34: 0 | AS34: =VLOOKUP(C34,'mayo-26'!B:AS,44,0) -> COORDTESORERIASUPERBETEL@GMAIL.COM | AT34: =VLOOKUP(C34,'mayo-26'!B:AT,45,0) -> CORREO ELECTRONICO CERTIFICADO 472
A35: ceda3cbef11f230c48e332f91b52b748e70eb68dcd7ad81ece42de7168b9da3e9efad0ffa9049a0497393114aeece2cd | B35: 280920 | C35: 280919 | D35: 280919 | E35: 29336 | F35: 29336 | G35: 900576569 | H35: SUPERMERCADO BETEL PLUSS | I35: =VLOOKUP(C35,'mayo-26'!B:H,7,0) -> AVE 12 5AN-84 1142 | J35: CHAPINERO | K35: =VLOOKUP(C35,'mayo-26'!B:J,9,0) -> NO | L35: =VLOOKUP(C35,'mayo-26'!B:K,10,0) -> BETEL | M35: CÚCUTA MPO | N35: CUCUTA DIRECTA | O35: 1002 - CICL FACT DIRECTA CUCUTA NORTE | P35: ASEO INTEGRAL | Q35: NO RESIDENCIAL - ASEO GP | R35: COMERCIAL | S35: AFORO ORDINARIO-EXTRAORDINARIO | T35: Ocupado | U35: 2026 | V35: 6 | W35: 1081875126 | X35: 1081893598 | Y35: 46182 | Z35: 46207 | AA35: 1647727.4 | AB35: 1647727.4 | AC35: 543284.27 | AD35: 5527.5 | AE35: 17874.57 | AF35: 0 | AG35: 0 | AH35: 0 | AI35: 0 | AJ35: 1647727.4 | AK35: 4957988.2 | AL35: 3 | AM35: 376.2 | AN35: 0 | AS35: =VLOOKUP(C35,'mayo-26'!B:AS,44,0) -> COORDTESORERIASUPERBETEL@GMAIL.COM | AT35: =VLOOKUP(C35,'mayo-26'!B:AT,45,0) -> CORREO ELECTRONICO CERTIFICADO 472
A36: 98372cea1076bb4def88d8f3920166b95ce4d9ca0b22090e006af46585b8fcd6420f0441d6486ec8ad919e2236728de3 | B36: 297 | C36: 292435 | D36: 292435 | E36: 101989 | F36: 101989 | G36: 807004352-3 | H36: EMPRESA SOCIAL DEL ESTADO E.S.E IMSALUD | I36: =VLOOKUP(C36,'mayo-26'!B:H,7,0) -> AVE 4 17-89 - 0239431 | J36: CUNDINAMARCA | K36: =VLOOKUP(C36,'mayo-26'!B:J,9,0) -> NO | L36: =VLOOKUP(C36,'mayo-26'!B:K,10,0) -> IMSALUD | M36: CÚCUTA MPO | N36: CUCUTA ZONA NORTE | O36: 1002 - CICL FACT DIRECTA CUCUTA NORTE | P36: ASEO INTEGRAL | Q36: NO RESIDENCIAL - ASEO PP | R36: OFICIAL RANGO 3 | S36: NO AFORADO | T36: Ocupado | U36: 2026 | V36: 6 | W36: 1081875130 | X36: 1081893602 | Y36: 46182 | Z36: 46207 | AA36: 75419 | AB36: 75419 | AC36: 0 | AD36: 0 | AE36: 0 | AF36: 0 | AG36: 0 | AH36: 0 | AI36: 0 | AJ36: 75419 | AK36: 75419 | AL36: 0 | AM36: 250.8 | AN36: 0 | AS36: =VLOOKUP(C36,'mayo-26'!B:AS,44,0) -> SUBFINANCIERA@IMSALUD.GOV.CO | AT36: =VLOOKUP(C36,'mayo-26'!B:AT,45,0) -> CORREO ELECTRONICO CERTIFICADO 472
A37: 005b0abbbfa859095f2091976748af27fd53c7f18de1e949308e6e3c9689bfdd91cd4f365d5428df575605a0575b2cc7 | B37: 297 | C37: 292975 | D37: 292975 | E37: 155089 | F37: 155089 | G37: 807004352-3 | H37: EMPRESA SOCIAL DEL ESTADO E.S.E IMSALUD | I37: =VLOOKUP(C37,'mayo-26'!B:H,7,0) -> AVE 4 17-89 - 0239431 | J37: CHAPINERO | K37: =VLOOKUP(C37,'mayo-26'!B:J,9,0) -> NO | L37: =VLOOKUP(C37,'mayo-26'!B:K,10,0) -> IMSALUD | M37: CÚCUTA MPO | N37: CUCUTA ZONA NORTE | O37: 1002 - CICL FACT DIRECTA CUCUTA NORTE | P37: ASEO INTEGRAL | Q37: NO RESIDENCIAL - ASEO PP | R37: OFICIAL RANGO 2 | S37: NO AFORADO | T37: Ocupado | U37: 2026 | V37: 6 | W37: 1081875134 | X37: 1081893606 | Y37: 46182 | Z37: 46207 | AA37: 62832 | AB37: 62832 | AC37: 0 | AD37: 0 | AE37: 0 | AF37: 0 | AG37: 0 | AH37: 0 | AI37: 0 | AJ37: 62832 | AK37: 62832 | AL37: 0 | AM37: 250.8 | AN37: 0 | AS37: =VLOOKUP(C37,'mayo-26'!B:AS,44,0) -> SUBFINANCIERA@IMSALUD.GOV.CO | AT37: =VLOOKUP(C37,'mayo-26'!B:AT,45,0) -> CORREO ELECTRONICO CERTIFICADO 472
A38: 913562c1cf026633e5014bfb02234cc07196647f821cda9ce4037c8a6dcf836e6f18752fdd124c4602e366f256f04e60 | B38: 297 | C38: 295095 | D38: 295095 | E38: 186399 | F38: 186399 | G38: 807004352-3 | H38: EMPRESA SOCIAL DEL ESTADO E.S.E IMSALUD | I38: =VLOOKUP(C38,'mayo-26'!B:H,7,0) -> AVE 4 17-89 - 0239431 | J38: SEVILLA | K38: =VLOOKUP(C38,'mayo-26'!B:J,9,0) -> NO | L38: =VLOOKUP(C38,'mayo-26'!B:K,10,0) -> IMSALUD | M38: CÚCUTA MPO | N38: CUCUTA ZONA NORTE | O38: 1002 - CICL FACT DIRECTA CUCUTA NORTE | P38: ASEO INTEGRAL | Q38: NO RESIDENCIAL - ASEO GP | R38: OFICIAL | S38: AFORO ORDINARIO-EXTRAORDINARIO | T38: Ocupado | U38: 2026 | V38: 6 | W38: 1081875136 | X38: 1081893608 | Y38: 46182 | Z38: 46207 | AA38: 104065.4 | AB38: 104065.4 | AC38: 0 | AD38: 350 | AE38: 0 | AF38: 0 | AG38: 0 | AH38: 0 | AI38: 0 | AJ38: 104065.4 | AK38: 104065.4 | AL38: 0 | AM38: 250.8 | AN38: 0 | AS38: =VLOOKUP(C38,'mayo-26'!B:AS,44,0) -> SUBFINANCIERA@IMSALUD.GOV.CO | AT38: =VLOOKUP(C38,'mayo-26'!B:AT,45,0) -> CORREO ELECTRONICO CERTIFICADO 472
A39: 6aeb5def2380d1e27808a9c5db826fbac00dbf50a244dd32a35ae4754197f4d7b23486485797a237ab1a88f7c1f3d80a | B39: 299352 | C39: 299351 | D39: 299351 | E39: 206188 | F39: 206188 | G39: 60353386 | H39: EMBUTIDOS CARNEVALI/CARNES FRIAS DEL ORIENTE | I39: =VLOOKUP(C39,'mayo-26'!B:H,7,0) -> AVE 6 17N-71 1219 | J39: ZONA INDUSTRIAL | K39: =VLOOKUP(C39,'mayo-26'!B:J,9,0) -> NO | L39: =VLOOKUP(C39,'mayo-26'!B:K,10,0) -> NO | M39: CÚCUTA MPO | N39: CUCUTA DIRECTA | O39: 1002 - CICL FACT DIRECTA CUCUTA NORTE | P39: ASEO INTEGRAL | Q39: NO RESIDENCIAL - ASEO GP | R39: INDUSTRIAL | S39: AFORO PERMANENTE | T39: Ocupado | U39: 2026 | V39: 6 | W39: 1081875139 | X39: 1081893611 | Y39: 46182 | Z39: 46207 | AA39: 1100472.2 | AB39: 1100472.2 | AC39: 253955.11 | AD39: 4262.5 | AE39: 0 | AF39: 0 | AG39: 0 | AH39: 0 | AI39: 0 | AJ39: 1100472.2 | AK39: 2026413.8 | AL39: 1 | AM39: 326.04 | AN39: 0 | AS39: =VLOOKUP(C39,'mayo-26'!B:AS,44,0) -> ADM.CARNEVALI@GMAIL.COM | AT39: =VLOOKUP(C39,'mayo-26'!B:AT,45,0) -> CORREO ELECTRONICO CERTIFICADO 472
A40: 0f39ab1a1354cc528180c73d946ab1874adf6d9d94c3f0250a385517c91ad4e4f45e509d8d6d9d61c6548339ed99834c | B40: 297 | C40: 307735 | D40: 307735 | E40: 307162 | F40: 307162 | G40: 807004352-3 | H40: EMPRESA SOCIAL DEL ESTADO E.S.E IMSALUD | I40: =VLOOKUP(C40,'mayo-26'!B:H,7,0) -> AVE 4 17-89 - 0239431 | J40: BELEN | K40: =VLOOKUP(C40,'mayo-26'!B:J,9,0) -> NO | L40: =VLOOKUP(C40,'mayo-26'!B:K,10,0) -> IMSALUD | M40: CÚCUTA MPO | N40: CUCUTA ZONA NORTE | O40: 1002 - CICL FACT DIRECTA CUCUTA NORTE | P40: ASEO INTEGRAL | Q40: NO RESIDENCIAL - ASEO GP | R40: OFICIAL | S40: AFORO ORDINARIO-EXTRAORDINARIO | T40: Ocupado | U40: 2026 | V40: 6 | W40: 1081875143 | X40: 1081893615 | Y40: 46182 | Z40: 46207 | AA40: 105963.04 | AB40: 105963.04 | AC40: 0 | AD40: 360 | AE40: 0 | AF40: 0 | AG40: 0 | AH40: 0 | AI40: 0 | AJ40: 105963.04 | AK40: 105963.04 | AL40: 0 | AM40: 250.8 | AN40: 0 | AS40: =VLOOKUP(C40,'mayo-26'!B:AS,44,0) -> SUBFINANCIERA@IMSALUD.GOV.CO | AT40: =VLOOKUP(C40,'mayo-26'!B:AT,45,0) -> CORREO ELECTRONICO CERTIFICADO 472
A41: 8c315f0c2ae87eaa8cfb4313655bffbde18b325104891916c5f2b004cf4d922461575259a8e34554bf8835bed5c05752 | B41: 297 | C41: 314723 | D41: 314723 | E41: 451064 | F41: 451064 | G41: 807004352-3 | H41: EMPRESA SOCIAL DEL ESTADO E.S.E IMSALUD | I41: =VLOOKUP(C41,'mayo-26'!B:H,7,0) -> AVE 4 17-89 - 0239431 | J41: EL CERRITO | K41: =VLOOKUP(C41,'mayo-26'!B:J,9,0) -> NO | L41: =VLOOKUP(C41,'mayo-26'!B:K,10,0) -> IMSALUD | M41: CÚCUTA MPO | N41: CUCUTA ZONA NORTE | O41: 1002 - CICL FACT DIRECTA CUCUTA NORTE | P41: ASEO INTEGRAL | Q41: NO RESIDENCIAL - ASEO PP | R41: OFICIAL RANGO 2 | S41: NO AFORADO | T41: Ocupado | U41: 2026 | V41: 6 | W41: 1081875145 | X41: 1081893617 | Y41: 46182 | Z41: 46207 | AA41: 62832 | AB41: 62832 | AC41: 0 | AD41: 0 | AE41: 0 | AF41: 0 | AG41: 0 | AH41: 0 | AI41: 0 | AJ41: 62832 | AK41: 62832 | AL41: 0 | AM41: 250.8 | AN41: 0 | AS41: =VLOOKUP(C41,'mayo-26'!B:AS,44,0) -> SUBFINANCIERA@IMSALUD.GOV.CO | AT41: =VLOOKUP(C41,'mayo-26'!B:AT,45,0) -> CORREO ELECTRONICO CERTIFICADO 472
A42: 79c0c9ec4726c5fdd630b0c6931f56920a92a5e2d80e8d459bf2085ae169ab211f0345bb56a803cbb362e37cf8238f6f | B42: 3156 | C42: 3155 | D42: 3155 | E42: 80123481 | F42: 80123481 | G42: 800084244 | H42: HIELOS EL OSO POLAR NIT 800084244-2 | I42: =VLOOKUP(C42,'mayo-26'!B:H,7,0) -> AV 4 7N-165 ZONA INDUSTRIAL | J42: ZONA INDUSTRIAL | K42: =VLOOKUP(C42,'mayo-26'!B:J,9,0) -> NO | L42: =VLOOKUP(C42,'mayo-26'!B:K,10,0) -> NO | M42: CÚCUTA MPO | N42: CUCUTA DIRECTA | O42: 1002 - CICL FACT DIRECTA CUCUTA NORTE | P42: ASEO INTEGRAL | Q42: NO RESIDENCIAL - ASEO GP | R42: INDUSTRIAL | S42: AFORO ORDINARIO-EXTRAORDINARIO | T42: Ocupado | U42: 2026 | V42: 6 | W42: 1081874926 | X42: 1081893398 | Y42: 46182 | Z42: 46207 | AA42: 114369.23 | AB42: 114369.23 | AC42: 26238.31 | AD42: 262.5 | AE42: 669.86 | AF42: 0 | AG42: 0 | AH42: 0 | AI42: 0 | AJ42: 114369.23 | AK42: 114369.23 | AL42: 0 | AM42: 326.04 | AN42: 0 | AS42: =VLOOKUP(C42,'mayo-26'!B:AS,44,0) -> ADMINISTRACION@HIELOSLICORESOSOPOLAR.COM | AT42: =VLOOKUP(C42,'mayo-26'!B:AT,45,0) -> CORREO ELECTRONICO CERTIFICADO 472
A43: daef77df7d395844a68892e5192eb4d6345ec073f6586aa8380257e7d759f5ae8be2d8a82197221ada16cbd0fffe82bf | B43: 147 | C43: 3159 | D43: 3159 | E43: 80123485 | F43: 80123485 | G43: 800141397-5 | H43: POLICIA NACIONAL-DIRECCION LOGISTICA Y FINANCIERA | I43: =VLOOKUP(C43,'mayo-26'!B:H,7,0) -> AVE 3 CLL 24 GARITA # 1 | J43: BARRIO NO LISTADO | K43: =VLOOKUP(C43,'mayo-26'!B:J,9,0) -> NO | L43: =VLOOKUP(C43,'mayo-26'!B:K,10,0) -> POLICIA | M43: CÚCUTA MPO | N43: CUCUTA DIRECTA | O43: 1002 - CICL FACT DIRECTA CUCUTA NORTE | P43: ASEO INTEGRAL | Q43: NO RESIDENCIAL - ASEO GP | R43: OFICIAL | S43: AFORO ORDINARIO-EXTRAORDINARIO | T43: Ocupado | U43: 2026 | V43: 6 | W43: 1081874933 | X43: 1081893405 | Y43: 46182 | Z43: 46207 | AA43: 287756.96 | AB43: 287756.96 | AC43: 0 | AD43: 1318 | AE43: 0 | AF43: 0 | AG43: 0 | AH43: 0 | AI43: 0 | AJ43: 287756.96 | AK43: 576090.32 | AL43: 2 | AM43: 250.8 | AN43: 0 | AS43: =VLOOKUP(C43,'mayo-26'!B:AS,44,0) -> MECUC.GUBIR@POLICIA.GOV.CO | AT43: =VLOOKUP(C43,'mayo-26'!B:AT,45,0) -> CORREO ELECTRONICO CERTIFICADO 472
A44: b564eadc680801293863a263998322b7bbedfa974cd730b80d85a473c02de53dec4363b8f9f36443c93a982e0a7cb344 | B44: 455370 | C44: 3163 | D44: 3163 | E44: 80123489 | F44: 80123489 | G44: 890501434- 2 | H44: MUNICIPIO DE SAN JOSE DE CUCUTA - SEDE TONCHALA | I44: =VLOOKUP(C44,'mayo-26'!B:H,7,0) -> CALLE 10 NO 0E-16 EDF CENTRO EMPRESARIAL BLOQUE B HOTEL TONCHALA | J44: VIRGILIO BARCO | K44: =VLOOKUP(C44,'mayo-26'!B:J,9,0) -> NO | L44: =VLOOKUP(C44,'mayo-26'!B:K,10,0) -> COLEGIOS ZONA NORTE | M44: CÚCUTA MPO | N44: CUCUTA ZONA NORTE | O44: 1002 - CICL FACT DIRECTA CUCUTA NORTE | P44: ASEO INTEGRAL | Q44: NO RESIDENCIAL - ASEO GP | R44: OFICIAL | S44: AFORO ORDINARIO-EXTRAORDINARIO | T44: Ocupado | U44: 2026 | V44: 6 | W44: 1081874937 | X44: 1081893409 | Y44: 46182 | Z44: 46207 | AA44: 512058 | AB44: 512058 | AC44: 0 | AD44: 2500 | AE44: 0 | AF44: 0 | AG44: 0 | AH44: 0 | AI44: 0 | AJ44: 512058 | AK44: 1525959.7 | AL44: 3 | AM44: 250.8 | AN44: 0 | AS44: =VLOOKUP(C44,'mayo-26'!B:AS,44,0) -> AREAFINANCIERA@SEMCUCUTA.GOV.CO | AT44: =VLOOKUP(C44,'mayo-26'!B:AT,45,0) -> CARTERA
A45: 212b87edbdedf77e47dc228c261128b2c6062355f5d2c298f71e1229bef42a4b323e5385f716da17d8c6307c7a667d93 | B45: 455370 | C45: 3167 | D45: 3167 | E45: 80123493 | F45: 80123493 | G45: 890501434- 2 | H45: MUNICIPIO DE SAN JOSE DE CUCUTA - SEDE TONCHALA | I45: =VLOOKUP(C45,'mayo-26'!B:H,7,0) -> CALLE 10 NO 0E-16 EDF CENTRO EMPRESARIAL BLOQUE B HOTEL TONCHALA | J45: BARRIO NUEVO | K45: =VLOOKUP(C45,'mayo-26'!B:J,9,0) -> NO | L45: =VLOOKUP(C45,'mayo-26'!B:K,10,0) -> COLEGIOS ZONA NORTE | M45: CÚCUTA MPO | N45: CUCUTA ZONA NORTE | O45: 1002 - CICL FACT DIRECTA CUCUTA NORTE | P45: ASEO INTEGRAL | Q45: NO RESIDENCIAL - ASEO GP | R45: OFICIAL | S45: AFORO ORDINARIO-EXTRAORDINARIO | T45: Ocupado | U45: 2026 | V45: 6 | W45: 1081874940 | X45: 1081893412 | Y45: 46182 | Z45: 46207 | AA45: 189459.2 | AB45: 189459.2 | AC45: 0 | AD45: 800 | AE45: 0 | AF45: 0 | AG45: 0 | AH45: 0 | AI45: 0 | AJ45: 189459.2 | AK45: 565752.1 | AL45: 3 | AM45: 250.8 | AN45: 0 | AS45: =VLOOKUP(C45,'mayo-26'!B:AS,44,0) -> AREAFINANCIERA@SEMCUCUTA.GOV.CO | AT45: =VLOOKUP(C45,'mayo-26'!B:AT,45,0) -> CARTERA
A46: ad4e5e864de9f3b2a6166e283589f9d229de98c9845c69e60bf304b8ce293ccb2e5651774571d22e854d376e1806df85 | B46: 455370 | C46: 3171 | D46: 3171 | E46: 80123497 | F46: 80123497 | G46: 890501434- 2 | H46: MUNICIPIO DE SAN JOSE DE CUCUTA - SEDE TONCHALA | I46: =VLOOKUP(C46,'mayo-26'!B:H,7,0) -> CALLE 10 NO 0E-16 EDF CENTRO EMPRESARIAL BLOQUE B HOTEL TONCHALA | J46: RUDENSIDO SOTO | K46: =VLOOKUP(C46,'mayo-26'!B:J,9,0) -> NO | L46: =VLOOKUP(C46,'mayo-26'!B:K,10,0) -> COLEGIOS ZONA NORTE | M46: CÚCUTA MPO | N46: CUCUTA ZONA NORTE | O46: 1002 - CICL FACT DIRECTA CUCUTA NORTE | P46: ASEO INTEGRAL | Q46: NO RESIDENCIAL - ASEO GP | R46: OFICIAL | S46: AFORO ORDINARIO-EXTRAORDINARIO | T46: Ocupado | U46: 2026 | V46: 6 | W46: 1081874944 | X46: 1081893416 | Y46: 46182 | Z46: 46207 | AA46: 346014.51 | AB46: 346014.51 | AC46: 0 | AD46: 1625 | AE46: 0 | AF46: 0 | AG46: 0 | AH46: 0 | AI46: 0 | AJ46: 346014.51 | AK46: 1031735.2 | AL46: 3 | AM46: 250.8 | AN46: 0 | AS46: =VLOOKUP(C46,'mayo-26'!B:AS,44,0) -> AREAFINANCIERA@SEMCUCUTA.GOV.CO | AT46: =VLOOKUP(C46,'mayo-26'!B:AT,45,0) -> CARTERA
A47: a9800ac4488891bf84fe523e7372e74d4a97320d87922dce3a0013401b95509ece246c10ca2531ca5de0647656c882ec | B47: 455370 | C47: 3175 | D47: 3175 | E47: 80123501 | F47: 80123501 | G47: 890501434- 2 | H47: MUNICIPIO DE SAN JOSE DE CUCUTA - SEDE TONCHALA | I47: =VLOOKUP(C47,'mayo-26'!B:H,7,0) -> CALLE 10 NO 0E-16 EDF CENTRO EMPRESARIAL BLOQUE B HOTEL TONCHALA | J47: LOS ALPES | K47: =VLOOKUP(C47,'mayo-26'!B:J,9,0) -> NO | L47: =VLOOKUP(C47,'mayo-26'!B:K,10,0) -> COLEGIOS ZONA NORTE | M47: CÚCUTA MPO | N47: CUCUTA ZONA NORTE | O47: 1002 - CICL FACT DIRECTA CUCUTA NORTE | P47: ASEO INTEGRAL | Q47: NO RESIDENCIAL - ASEO GP | R47: OFICIAL | S47: AFORO ORDINARIO-EXTRAORDINARIO | T47: Ocupado | U47: 2026 | V47: 6 | W47: 1081874946 | X47: 1081893418 | Y47: 46182 | Z47: 46207 | AA47: 338423.95 | AB47: 338423.95 | AC47: 0 | AD47: 1585 | AE47: 0 | AF47: 0 | AG47: 0 | AH47: 0 | AI47: 0 | AJ47: 338423.95 | AK47: 1009142.1 | AL47: 3 | AM47: 250.8 | AN47: 0 | AS47: =VLOOKUP(C47,'mayo-26'!B:AS,44,0) -> AREAFINANCIERA@SEMCUCUTA.GOV.CO | AT47: =VLOOKUP(C47,'mayo-26'!B:AT,45,0) -> CARTERA
A48: 61fb7ce2236b5a3ee49a3126c4841cf68879879edf3f8129d4de6d0eecd6019f3951d34ff244464495f497370721ee5c | B48: 3180 | C48: 3179 | D48: 3179 | E48: 80123505 | F48: 80123505 | G48: 890502572 | H48: ARROCERA GELVEZ SAS NIT 890502572-2 | I48: =VLOOKUP(C48,'mayo-26'!B:H,7,0) -> AV 7 18N-67/77/87 VIA AEROPUER | J48: ZONA INDUSTRIAL | K48: =VLOOKUP(C48,'mayo-26'!B:J,9,0) -> NO | L48: =VLOOKUP(C48,'mayo-26'!B:K,10,0) -> NO | M48: CÚCUTA MPO | N48: CUCUTA DIRECTA | O48: 1002 - CICL FACT DIRECTA CUCUTA NORTE | P48: ASEO INTEGRAL | Q48: NO RESIDENCIAL - ASEO GP | R48: INDUSTRIAL | S48: AFORO PERMANENTE | T48: Ocupado | U48: 2026 | V48: 6 | W48: 1081874949 | X48: 1081893421 | Y48: 46182 | Z48: 46207 | AA48: 360392.57 | AB48: 360392.57 | AC48: 83167.51 | AD48: 1262.5 | AE48: 0 | AF48: 0 | AG48: 0 | AH48: 0 | AI48: 0 | AJ48: 360392.57 | AK48: 360392.57 | AL48: 0 | AM48: 326.04 | AN48: 0 | AS48: =VLOOKUP(C48,'mayo-26'!B:AS,44,0) -> FACTURAELECTRONICA@ARROZGELVEZ.COM | AT48: =VLOOKUP(C48,'mayo-26'!B:AT,45,0) -> CORREO ELECTRONICO CERTIFICADO 472
A49: 2b4453a4761b90b7eff23e7bbf1b8b143ffabfc252b9b3c5c549abd814a0dc7b6d7cfbad680c2a5d2fe697ede4547cfe | B49: 232 | C49: 3183 | D49: 3183 | E49: 80123509 | F49: 80123509 | G49: 830122566 | H49: TELECOM AVE 0 EDIF PRINCIPAL | I49: =VLOOKUP(C49,'mayo-26'!B:H,7,0) -> AV 0 N 10-61 | J49: COMUNEROS | K49: =VLOOKUP(C49,'mayo-26'!B:J,9,0) -> NO | L49: =VLOOKUP(C49,'mayo-26'!B:K,10,0) -> MOVISTAR | M49: CÚCUTA MPO | N49: CUCUTA ZONA NORTE | O49: 1002 - CICL FACT DIRECTA CUCUTA NORTE | P49: ASEO INTEGRAL | Q49: NO RESIDENCIAL - ASEO PP | R49: COMERCIAL RANGO 3 | S49: NO AFORADO | T49: Ocupado | U49: 2026 | V49: 6 | W49: 1081874956 | X49: 1081893428 | Y49: 46182 | Z49: 46207 | AA49: 114389.91 | AB49: 114389.91 | AC49: 37709.5 | AD49: 0 | AE49: 1261.41 | AF49: 0 | AG49: 0 | AH49: 0 | AI49: 0 | AJ49: 114389.91 | AK49: 345405.28 | AL49: 2 | AM49: 376.2 | AN49: 0 | AS49: =VLOOKUP(C49,'mayo-26'!B:AS,44,0) -> SERVICIOSPUBLICOS.TC@TELEFONICA.COM; D.CRUZ02@TELEFONICA.COM | AT49: =VLOOKUP(C49,'mayo-26'!B:AT,45,0) -> CORREO ELECTRONICO CERTIFICADO 472
A50: dcce048d2d44bb9bb758d52174df4fff501bcea79cc8aa7746d87631c35caf9e923811387994c0168167d84a6ecbe92e | B50: 455370 | C50: 3187 | D50: 3187 | E50: 80123513 | F50: 80123513 | G50: 890501434- 2 | H50: MUNICIPIO DE SAN JOSE DE CUCUTA - SEDE TONCHALA | I50: =VLOOKUP(C50,'mayo-26'!B:H,7,0) -> CALLE 10 NO 0E-16 EDF CENTRO EMPRESARIAL BLOQUE B HOTEL TONCHALA | J50: MOTILONES | K50: =VLOOKUP(C50,'mayo-26'!B:J,9,0) -> NO | L50: =VLOOKUP(C50,'mayo-26'!B:K,10,0) -> COLEGIOS ZONA NORTE | M50: CÚCUTA MPO | N50: CUCUTA ZONA NORTE | O50: 1002 - CICL FACT DIRECTA CUCUTA NORTE | P50: ASEO INTEGRAL | Q50: NO RESIDENCIAL - ASEO GP | R50: OFICIAL | S50: AFORO ORDINARIO-EXTRAORDINARIO | T50: Ocupado | U50: 2026 | V50: 6 | W50: 1081874961 | X50: 1081893433 | Y50: 46182 | Z50: 46207 | AA50: 200465.52 | AB50: 200465.52 | AC50: 0 | AD50: 858 | AE50: 0 | AF50: 0 | AG50: 0 | AH50: 0 | AI50: 0 | AJ50: 200465.52 | AK50: 598512.14 | AL50: 3 | AM50: 250.8 | AN50: 0 | AS50: =VLOOKUP(C50,'mayo-26'!B:AS,44,0) -> AREAFINANCIERA@SEMCUCUTA.GOV.CO | AT50: =VLOOKUP(C50,'mayo-26'!B:AT,45,0) -> CARTERA
A51: 61c52c4e62ad43d4af746ea42be05a69168b03628b053c549e09623acb1fc1c30264558ca976e31c7c2dd973a8103486 | B51: 455370 | C51: 3191 | D51: 3191 | E51: 80123517 | F51: 80123517 | G51: 890501434- 2 | H51: MUNICIPIO DE SAN JOSE DE CUCUTA - SEDE TONCHALA | I51: =VLOOKUP(C51,'mayo-26'!B:H,7,0) -> CALLE 10 NO 0E-16 EDF CENTRO EMPRESARIAL BLOQUE B HOTEL TONCHALA | J51: CLARET | K51: =VLOOKUP(C51,'mayo-26'!B:J,9,0) -> NO | L51: =VLOOKUP(C51,'mayo-26'!B:K,10,0) -> COLEGIOS ZONA NORTE | M51: CÚCUTA MPO | N51: CUCUTA ZONA NORTE | O51: 1002 - CICL FACT DIRECTA CUCUTA NORTE | P51: ASEO INTEGRAL | Q51: NO RESIDENCIAL - ASEO GP | R51: OFICIAL | S51: AFORO ORDINARIO-EXTRAORDINARIO | T51: Ocupado | U51: 2026 | V51: 6 | W51: 1081874965 | X51: 1081893437 | Y51: 46182 | Z51: 46207 | AA51: 172380.44 | AB51: 172380.44 | AC51: 0 | AD51: 710 | AE51: 0 | AF51: 0 | AG51: 0 | AH51: 0 | AI51: 0 | AJ51: 172380.44 | AK51: 514917.58 | AL51: 3 | AM51: 250.8 | AN51: 0 | AS51: =VLOOKUP(C51,'mayo-26'!B:AS,44,0) -> AREAFINANCIERA@SEMCUCUTA.GOV.CO | AT51: =VLOOKUP(C51,'mayo-26'!B:AT,45,0) -> CARTERA
A52: 7fdfe12a8c9ba658630f66ea6bff3ef9492ae8f6a6f5dad8b4d5b73618294aa683c81cf639ebc730b718816cca11dc55 | B52: 232 | C52: 3195 | D52: 3195 | E52: 80123521 | F52: 80123521 | G52: 830122566 | H52: TELECOM AVE 0 EDIF PRINCIPAL | I52: =VLOOKUP(C52,'mayo-26'!B:H,7,0) -> AV 0 N 10-61 | J52: CUCUTA 75 | K52: =VLOOKUP(C52,'mayo-26'!B:J,9,0) -> NO | L52: =VLOOKUP(C52,'mayo-26'!B:K,10,0) -> MOVISTAR | M52: CÚCUTA MPO | N52: CUCUTA ZONA NORTE | O52: 1002 - CICL FACT DIRECTA CUCUTA NORTE | P52: ASEO INTEGRAL | Q52: NO RESIDENCIAL - ASEO PP | R52: COMERCIAL RANGO 3 | S52: NO AFORADO | T52: Ocupado | U52: 2026 | V52: 6 | W52: 1081874970 | X52: 1081893442 | Y52: 46182 | Z52: 46207 | AA52: 114389.91 | AB52: 114389.91 | AC52: 37709.5 | AD52: 0 | AE52: 1261.41 | AF52: 0 | AG52: 0 | AH52: 0 | AI52: 0 | AJ52: 114389.91 | AK52: 346896.43 | AL52: 2 | AM52: 376.2 | AN52: 0 | AS52: =VLOOKUP(C52,'mayo-26'!B:AS,44,0) -> SERVICIOSPUBLICOS.TC@TELEFONICA.COM; D.CRUZ02@TELEFONICA.COM | AT52: =VLOOKUP(C52,'mayo-26'!B:AT,45,0) -> CORREO ELECTRONICO CERTIFICADO 472
A53: dcaa73ec517adc39616e5c5ed8a635bd16178b94da6266aaa857db275ca3360a03480dcda3e4080169ab7658402dedbf | B53: 455370 | C53: 3199 | D53: 3199 | E53: 80123525 | F53: 80123525 | G53: 890501434- 2 | H53: MUNICIPIO DE SAN JOSE DE CUCUTA - SEDE TONCHALA | I53: =VLOOKUP(C53,'mayo-26'!B:H,7,0) -> CALLE 10 NO 0E-16 EDF CENTRO EMPRESARIAL BLOQUE B HOTEL TONCHALA | J53: BELISARIO BETANCOURT | K53: =VLOOKUP(C53,'mayo-26'!B:J,9,0) -> NO | L53: =VLOOKUP(C53,'mayo-26'!B:K,10,0) -> COLEGIOS ZONA NORTE | M53: CÚCUTA MPO | N53: CUCUTA ZONA NORTE | O53: 1002 - CICL FACT DIRECTA CUCUTA NORTE | P53: ASEO INTEGRAL | Q53: NO RESIDENCIAL - ASEO GP | R53: OFICIAL | S53: AFORO ORDINARIO-EXTRAORDINARIO | T53: Ocupado | U53: 2026 | V53: 6 | W53: 1081874974 | X53: 1081893446 | Y53: 46182 | Z53: 46207 | AA53: 354174.36 | AB53: 354174.36 | AC53: 0 | AD53: 1668 | AE53: 0 | AF53: 0 | AG53: 0 | AH53: 0 | AI53: 0 | AJ53: 354174.36 | AK53: 1056022.8 | AL53: 3 | AM53: 250.8 | AN53: 0 | AS53: =VLOOKUP(C53,'mayo-26'!B:AS,44,0) -> AREAFINANCIERA@SEMCUCUTA.GOV.CO | AT53: =VLOOKUP(C53,'mayo-26'!B:AT,45,0) -> CARTERA
A54: 2e5877ec5ea00c865d1a4185cc8a90c8acca8bddceb45e5439c8a87a4596ca3295cd3d600919649c588f4af191c33b1b | B54: 3204 | C54: 3203 | D54: 3203 | E54: 80123529 | F54: 80123529 | G54: 901199390 | H54: CORPORACION ZONA FRANCA INDUSTRIAL DE BIENES Y DE SERVICIOS DE | I54: =VLOOKUP(C54,'mayo-26'!B:H,7,0) -> AV LIBERTADORES ENTRE CALLES 3 Y 5 FRENTE AL RELOJ DE SOL | J54: ZONA FRANCA | K54: =VLOOKUP(C54,'mayo-26'!B:J,9,0) -> ZONA NORTE | L54: =VLOOKUP(C54,'mayo-26'!B:K,10,0) -> NO | M54: CÚCUTA MPO | N54: CUCUTA DIRECTA | O54: 1002 - CICL FACT DIRECTA CUCUTA NORTE | P54: ASEO INTEGRAL | Q54: NO RESIDENCIAL - ASEO GP | R54: COMERCIAL | S54: AFORO ORDINARIO-EXTRAORDINARIO | T54: Ocupado | U54: 2026 | V54: 6 | W54: 1081874976 | X54: 1081893448 | Y54: 46182 | Z54: 46207 | AA54: 198795 | AB54: 198795 | AC54: 66265 | AD54: 500 | AE54: 0 | AF54: 0 | AG54: 0 | AH54: 0 | AI54: 0 | AJ54: 198795 | AK54: 398396.25 | AL54: 1 | AM54: 376.2 | AN54: 0 | AS54: =VLOOKUP(C54,'mayo-26'!B:AS,44,0) -> GERENTE@ZONAFRANCACUCUTA.COM | AT54: =VLOOKUP(C54,'mayo-26'!B:AT,45,0) -> VERIFICADOR
A55: e20b1467380e799564604aa3dcf294dbcdc56a174bd7ac257c2963019baf730798327dfa6dc52b73f094b83692298573 | B55: 3208 | C55: 3207 | D55: 3207 | E55: 80127923 | F55: 80127923 | G55: 901134015 | H55: TUBOS DEL ORIENTE | I55: =VLOOKUP(C55,'mayo-26'!B:H,7,0) -> KDX 70-B 305016 1116 | J55: LA INSULA | K55: =VLOOKUP(C55,'mayo-26'!B:J,9,0) -> NO | L55: =VLOOKUP(C55,'mayo-26'!B:K,10,0) -> NO | M55: CÚCUTA MPO | N55: CUCUTA DIRECTA | O55: 1002 - CICL FACT DIRECTA CUCUTA NORTE | P55: ASEO INTEGRAL | Q55: NO RESIDENCIAL - ASEO GP | R55: COMERCIAL | S55: AFORO ORDINARIO-EXTRAORDINARIO | T55: Ocupado | U55: 2026 | V55: 6 | W55: 1081874980 | X55: 1081893452 | Y55: 46182 | Z55: 46207 | AA55: 128487.44 | AB55: 128487.44 | AC55: 42829.15 | AD55: 253 | AE55: 0 | AF55: 0 | AG55: 0 | AH55: 0 | AI55: 0 | AJ55: 128487.44 | AK55: 128487.44 | AL55: 0 | AM55: 376.2 | AN55: 0 | AS55: =VLOOKUP(C55,'mayo-26'!B:AS,44,0) -> CONTABILIDAD@TUBOSDELORIENTE.COM | AT55: =VLOOKUP(C55,'mayo-26'!B:AT,45,0) -> CORREO ELECTRONICO CERTIFICADO 472
A56: 22a187316a8aed765145b0d4aabf316edcf5b168aafcb7b4e75d1b3c546f70f0f8d6ab208202df1da99f31dea70f76d8 | B56: 3212 | C56: 3211 | D56: 3211 | E56: 80195803 | F56: 80195803 | G56: 860016640 | H56: TCC S.A.S NIT. 860.016.640-4 | I56: =VLOOKUP(C56,'mayo-26'!B:H,7,0) -> AVE 8 0-195 1092 | J56: BARRIO NO LISTADO | K56: =VLOOKUP(C56,'mayo-26'!B:J,9,0) -> NO | L56: =VLOOKUP(C56,'mayo-26'!B:K,10,0) -> NO | M56: CÚCUTA MPO | N56: CUCUTA DIRECTA | O56: 1002 - CICL FACT DIRECTA CUCUTA NORTE | P56: ASEO INTEGRAL | Q56: NO RESIDENCIAL - ASEO GP | R56: COMERCIAL | S56: AFORO PERMANENTE | T56: Ocupado | U56: 2026 | V56: 6 | W56: 1081874985 | X56: 1081893457 | Y56: 46182 | Z56: 46207 | AA56: 540370.2 | AB56: 540370.2 | AC56: 180123.4 | AD56: 1700 | AE56: 0 | AF56: 0 | AG56: 0 | AH56: 0 | AI56: 0 | AJ56: 540370.2 | AK56: 540370.2 | AL56: 0 | AM56: 376.2 | AN56: 0 | AS56: =VLOOKUP(C56,'mayo-26'!B:AS,44,0) -> AIFLOREZ@TCC.COM.CO | AT56: =VLOOKUP(C56,'mayo-26'!B:AT,45,0) -> CORREO ELECTRONICO CERTIFICADO 472
A57: 840cb99a90751385b5209c0c65808d105e188886546670086498b671ac3dd5cf91c0eded6d0e6ec8a0b2fc80ea56e66f | B57: 670 | C57: 3215 | D57: 3215 | E57: 80204161 | F57: 80204161 | G57: 890105652-3 | H57: ROYAL FILMS | I57: =VLOOKUP(C57,'mayo-26'!B:H,7,0) -> A11 CC JARDIN PLAZA | J57: PRADOS NORTE | K57: =VLOOKUP(C57,'mayo-26'!B:J,9,0) -> NO | L57: =VLOOKUP(C57,'mayo-26'!B:K,10,0) -> NO | M57: CÚCUTA MPO | N57: CUCUTA ZONA NORTE | O57: 1002 - CICL FACT DIRECTA CUCUTA NORTE | P57: ASEO INTEGRAL | Q57: NO RESIDENCIAL - ASEO GP | R57: COMERCIAL | S57: AFORO ORDINARIO-EXTRAORDINARIO | T57: Ocupado | U57: 2026 | V57: 6 | W57: 1081874989 | X57: 1081893461 | Y57: 46182 | Z57: 46207 | AA57: 262840.37 | AB57: 262840.37 | AC57: 87613.46 | AD57: 725 | AE57: 0 | AF57: 0 | AG57: 0 | AH57: 0 | AI57: 0 | AJ57: 262840.37 | AK57: 262840.37 | AL57: 0 | AM57: 376.2 | AN57: 0 | AS57: =VLOOKUP(C57,'mayo-26'!B:AS,44,0) -> MULTICINEJARDINPLAZACUCUTA@ROYAL.FILMS.COM; serviciospublicos@royal-films.com | AT57: =VLOOKUP(C57,'mayo-26'!B:AT,45,0) -> CORREO ELECTRONICO CERTIFICADO 472
A58: 7a9e12cff5500f14fcd14735994870be650e35fe5ceac3e50ff457b2aa1d645a2b008fd1a7e60887a05db5458e9f3e23 | B58: 3220 | C58: 3219 | D58: 3219 | E58: 80205197 | F58: 80205197 | G58: 900069828 | H58: CONJUNTO RESIDENCIAL PORTACHUELO RESERVADO NIT. 900.069.828-3 | I58: =VLOOKUP(C58,'mayo-26'!B:H,7,0) -> CLL 14AN 4-81 TORRE 1 | J58: PORTACHUELO | K58: =VLOOKUP(C58,'mayo-26'!B:J,9,0) -> CR PORTACHUELO | L58: =VLOOKUP(C58,'mayo-26'!B:K,10,0) -> CR PORTACHUELO | M58: CÚCUTA MPO | N58: CUCUTA DIRECTA | O58: 1002 - CICL FACT DIRECTA CUCUTA NORTE | P58: ASEO INTEGRAL | Q58: RESIDENCIAL | R58: ESTRATO 3 | S58: NO AFORADO | T58: Ocupado | U58: 2026 | V58: 6 | W58: 1081874993 | X58: 1081893465 | Y58: 46182 | Z58: 46207 | AA58: 416258.3 | AB58: 49934.3 | AC58: -1650.7 | AD58: 0 | AE58: 0 | AF58: 1831620 | AG58: 366324 | AH58: 0 | AI58: 0 | AJ58: 416258.3 | AK58: 416258.3 | AL58: 0 | AM58: 242.77 | AN58: 0 | AS58: =VLOOKUP(C58,'mayo-26'!B:AS,44,0) -> CONJUNTOPORTACHUELORESERVADO@GMAIL.COM | AT58: =VLOOKUP(C58,'mayo-26'!B:AT,45,0) -> VERIFICADOR
A59: 6e6fa7f577741831fdc0ecb17acff41fc55d4445b1eada252217a694b6616ef188313d5f8858663fb78994dbf3636a1d | B59: 455370 | C59: 3223 | D59: 3223 | E59: 80206517 | F59: 80206517 | G59: 890501434- 2 | H59: MUNICIPIO DE SAN JOSE DE CUCUTA - SEDE TONCHALA | I59: =VLOOKUP(C59,'mayo-26'!B:H,7,0) -> CALLE 10 NO 0E-16 EDF CENTRO EMPRESARIAL BLOQUE B HOTEL TONCHALA | J59: PESCADERO | K59: =VLOOKUP(C59,'mayo-26'!B:J,9,0) -> NO | L59: =VLOOKUP(C59,'mayo-26'!B:K,10,0) -> COLEGIOS ZONA NORTE | M59: CÚCUTA MPO | N59: CUCUTA ZONA NORTE | O59: 1002 - CICL FACT DIRECTA CUCUTA NORTE | P59: ASEO INTEGRAL | Q59: NO RESIDENCIAL - ASEO GP | R59: OFICIAL | S59: AFORO ORDINARIO-EXTRAORDINARIO | T59: Ocupado | U59: 2026 | V59: 6 | W59: 1081874998 | X59: 1081893470 | Y59: 46182 | Z59: 46207 | AA59: 236520.68 | AB59: 236520.68 | AC59: 0 | AD59: 1048 | AE59: 0 | AF59: 0 | AG59: 0 | AH59: 0 | AI59: 0 | AJ59: 236520.68 | AK59: 705829.46 | AL59: 3 | AM59: 250.8 | AN59: 0 | AS59: =VLOOKUP(C59,'mayo-26'!B:AS,44,0) -> AREAFINANCIERA@SEMCUCUTA.GOV.CO | AT59: =VLOOKUP(C59,'mayo-26'!B:AT,45,0) -> CARTERA
A60: d5a7cbc404355031b3daaf1cb639a567542e305ff5ae85886e124c52c6506b87b926df32c278c685c1c1576c182c08a7 | B60: 455370 | C60: 3227 | D60: 3227 | E60: 80206521 | F60: 80206521 | G60: 890501434- 2 | H60: MUNICIPIO DE SAN JOSE DE CUCUTA - SEDE TONCHALA | I60: =VLOOKUP(C60,'mayo-26'!B:H,7,0) -> CALLE 10 NO 0E-16 EDF CENTRO EMPRESARIAL BLOQUE B HOTEL TONCHALA | J60: OSPINA PEREZ | K60: =VLOOKUP(C60,'mayo-26'!B:J,9,0) -> NO | L60: =VLOOKUP(C60,'mayo-26'!B:K,10,0) -> COLEGIOS ZONA NORTE | M60: CÚCUTA MPO | N60: CUCUTA ZONA NORTE | O60: 1002 - CICL FACT DIRECTA CUCUTA NORTE | P60: ASEO INTEGRAL | Q60: NO RESIDENCIAL - ASEO GP | R60: OFICIAL | S60: AFORO ORDINARIO-EXTRAORDINARIO | T60: Ocupado | U60: 2026 | V60: 6 | W60: 1081875002 | X60: 1081893474 | Y60: 46182 | Z60: 46207 | AA60: 238418.32 | AB60: 238418.32 | AC60: 0 | AD60: 1058 | AE60: 0 | AF60: 0 | AG60: 0 | AH60: 0 | AI60: 0 | AJ60: 238418.32 | AK60: 711477.74 | AL60: 3 | AM60: 250.8 | AN60: 0 | AS60: =VLOOKUP(C60,'mayo-26'!B:AS,44,0) -> AREAFINANCIERA@SEMCUCUTA.GOV.CO | AT60: =VLOOKUP(C60,'mayo-26'!B:AT,45,0) -> CARTERA
A61: 1ea9b364340bd3648cdbad03daebfc253000f8186a04b6b0bda225e90845ff69286a1433161d0481cb83f08f301ccec3 | B61: 455370 | C61: 3231 | D61: 3231 | E61: 80206525 | F61: 80206525 | G61: 890501434- 2 | H61: MUNICIPIO DE SAN JOSE DE CUCUTA - SEDE TONCHALA | I61: =VLOOKUP(C61,'mayo-26'!B:H,7,0) -> CALLE 10 NO 0E-16 EDF CENTRO EMPRESARIAL BLOQUE B HOTEL TONCHALA | J61: EL SALADO | K61: =VLOOKUP(C61,'mayo-26'!B:J,9,0) -> NO | L61: =VLOOKUP(C61,'mayo-26'!B:K,10,0) -> COLEGIOS ZONA NORTE | M61: CÚCUTA MPO | N61: CUCUTA ZONA NORTE | O61: 1002 - CICL FACT DIRECTA CUCUTA NORTE | P61: ASEO INTEGRAL | Q61: NO RESIDENCIAL - ASEO GP | R61: OFICIAL | S61: AFORO ORDINARIO-EXTRAORDINARIO | T61: Ocupado | U61: 2026 | V61: 6 | W61: 1081875006 | X61: 1081893478 | Y61: 46182 | Z61: 46207 | AA61: 986468 | AB61: 986468 | AC61: 0 | AD61: 5000 | AE61: 0 | AF61: 0 | AG61: 0 | AH61: 0 | AI61: 0 | AJ61: 986468 | AK61: 2938029.7 | AL61: 3 | AM61: 250.8 | AN61: 0 | AS61: =VLOOKUP(C61,'mayo-26'!B:AS,44,0) -> AREAFINANCIERA@SEMCUCUTA.GOV.CO | AT61: =VLOOKUP(C61,'mayo-26'!B:AT,45,0) -> CARTERA
A62: a3de69b5bc75c3620bb985f42a2b40d614d7401ff1d3069879680259be9bfdd8ee8afc0d92499b3411c9a56116f53f3d | B62: 3236 | C62: 3235 | D62: 3235 | E62: 80211584 | F62: 80211584 | G62: 800083514 | H62: ARROCERA SAN VALETIN Y CIA LTA NIT. 800.083.514-1 | I62: =VLOOKUP(C62,'mayo-26'!B:H,7,0) -> CLL 7N 5-31 ZONA INDUSTRIAL | J62: ZONA INDUSTRIAL | K62: =VLOOKUP(C62,'mayo-26'!B:J,9,0) -> NO | L62: =VLOOKUP(C62,'mayo-26'!B:K,10,0) -> NO | M62: CÚCUTA MPO | N62: CUCUTA DIRECTA | O62: 1002 - CICL FACT DIRECTA CUCUTA NORTE | P62: ASEO INTEGRAL | Q62: NO RESIDENCIAL - ASEO GP | R62: INDUSTRIAL | S62: AFORO ORDINARIO-EXTRAORDINARIO | T62: Ocupado | U62: 2026 | V62: 6 | W62: 1081875011 | X62: 1081893483 | Y62: 46182 | Z62: 46207 | AA62: 111232.45 | AB62: 111232.45 | AC62: 25669.03 | AD62: 252.5 | AE62: 0 | AF62: 0 | AG62: 0 | AH62: 0 | AI62: 0 | AJ62: 111232.45 | AK62: 111232.45 | AL62: 0 | AM62: 326.04 | AN62: 0 | AS62: =VLOOKUP(C62,'mayo-26'!B:AS,44,0) -> ARROCERASSANVALENTIN@HOTMAIL.COM | AT62: =VLOOKUP(C62,'mayo-26'!B:AT,45,0) -> CORREO ELECTRONICO CERTIFICADO 472
A63: 40b7bb624009ccdc8a4fcd348026aa5bdc87888fd4deefc7ac93c2e7d1dcbc0a739a81229ac2f2889a9e89955d13e980 | B63: 455370 | C63: 3239 | D63: 3239 | E63: 80212697 | F63: 80212697 | G63: 890501434- 2 | H63: MUNICIPIO DE SAN JOSE DE CUCUTA - SEDE TONCHALA | I63: =VLOOKUP(C63,'mayo-26'!B:H,7,0) -> CALLE 10 NO 0E-16 EDF CENTRO EMPRESARIAL BLOQUE B HOTEL TONCHALA | J63: LOMA DE BOLIVAR | K63: =VLOOKUP(C63,'mayo-26'!B:J,9,0) -> NO | L63: =VLOOKUP(C63,'mayo-26'!B:K,10,0) -> COLEGIOS ZONA NORTE | M63: CÚCUTA MPO | N63: CUCUTA ZONA NORTE | O63: 1002 - CICL FACT DIRECTA CUCUTA NORTE | P63: ASEO INTEGRAL | Q63: NO RESIDENCIAL - ASEO GP | R63: OFICIAL | S63: AFORO ORDINARIO-EXTRAORDINARIO | T63: Ocupado | U63: 2026 | V63: 6 | W63: 1081875015 | X63: 1081893487 | Y63: 46182 | Z63: 46207 | AA63: 132530 | AB63: 132530 | AC63: 0 | AD63: 500 | AE63: 0 | AF63: 0 | AG63: 0 | AH63: 0 | AI63: 0 | AJ63: 132530 | AK63: 396303.7 | AL63: 3 | AM63: 250.8 | AN63: 0 | AS63: =VLOOKUP(C63,'mayo-26'!B:AS,44,0) -> AREAFINANCIERA@SEMCUCUTA.GOV.CO | AT63: =VLOOKUP(C63,'mayo-26'!B:AT,45,0) -> CARTERA
A64: 42fc0aa76b0a77ccd4d4ebb6837447843c5577b64075a1bf369c6c1e7b4792403df96daafee63cdbbf0db7894819e6fa | B64: 455370 | C64: 3243 | D64: 3243 | E64: 80212701 | F64: 80212701 | G64: 890501434- 2 | H64: MUNICIPIO DE SAN JOSE DE CUCUTA - SEDE TONCHALA | I64: =VLOOKUP(C64,'mayo-26'!B:H,7,0) -> CALLE 10 NO 0E-16 EDF CENTRO EMPRESARIAL BLOQUE B HOTEL TONCHALA | J64: PANAMERICANO | K64: =VLOOKUP(C64,'mayo-26'!B:J,9,0) -> NO | L64: =VLOOKUP(C64,'mayo-26'!B:K,10,0) -> COLEGIOS ZONA NORTE | M64: CÚCUTA MPO | N64: CUCUTA ZONA NORTE | O64: 1002 - CICL FACT DIRECTA CUCUTA NORTE | P64: ASEO INTEGRAL | Q64: NO RESIDENCIAL - ASEO GP | R64: OFICIAL | S64: AFORO ORDINARIO-EXTRAORDINARIO | T64: Ocupado | U64: 2026 | V64: 6 | W64: 1081875019 | X64: 1081893491 | Y64: 46182 | Z64: 46207 | AA64: 190977.32 | AB64: 190977.32 | AC64: 0 | AD64: 808 | AE64: 0 | AF64: 0 | AG64: 0 | AH64: 0 | AI64: 0 | AJ64: 190977.32 | AK64: 570270.74 | AL64: 3 | AM64: 250.8 | AN64: 0 | AS64: =VLOOKUP(C64,'mayo-26'!B:AS,44,0) -> AREAFINANCIERA@SEMCUCUTA.GOV.CO | AT64: =VLOOKUP(C64,'mayo-26'!B:AT,45,0) -> CARTERA
A65: 11fc78f4a396077c67ae2e6b3923da1c0a2481b8610e8fe84fb2cf681df7375b49b82c179aa6e6911c56fe05fa738033 | B65: 455370 | C65: 3247 | D65: 3247 | E65: 80212705 | F65: 80212705 | G65: 890501434- 2 | H65: MUNICIPIO DE SAN JOSE DE CUCUTA - SEDE TONCHALA | I65: =VLOOKUP(C65,'mayo-26'!B:H,7,0) -> CALLE 10 NO 0E-16 EDF CENTRO EMPRESARIAL BLOQUE B HOTEL TONCHALA | J65: CARLOS PIZARRO | K65: =VLOOKUP(C65,'mayo-26'!B:J,9,0) -> NO | L65: =VLOOKUP(C65,'mayo-26'!B:K,10,0) -> COLEGIOS ZONA NORTE | M65: CÚCUTA MPO | N65: CUCUTA ZONA NORTE | O65: 1002 - CICL FACT DIRECTA CUCUTA NORTE | P65: ASEO INTEGRAL | Q65: NO RESIDENCIAL - ASEO GP | R65: OFICIAL | S65: AFORO ORDINARIO-EXTRAORDINARIO | T65: Ocupado | U65: 2026 | V65: 6 | W65: 1081875024 | X65: 1081893496 | Y65: 46182 | Z65: 46207 | AA65: 199896.23 | AB65: 199896.23 | AC65: 0 | AD65: 855 | AE65: 0 | AF65: 0 | AG65: 0 | AH65: 0 | AI65: 0 | AJ65: 199896.23 | AK65: 596817.66 | AL65: 3 | AM65: 250.8 | AN65: 0 | AS65: =VLOOKUP(C65,'mayo-26'!B:AS,44,0) -> AREAFINANCIERA@SEMCUCUTA.GOV.CO | AT65: =VLOOKUP(C65,'mayo-26'!B:AT,45,0) -> CARTERA
A66: 86e7bcfe1c2db53c62500ff48fe6fd6d430f82adbbc99a25cf083b1e2c84f350dce8bba3e1b0bdc3bd2bc41fc0794e02 | B66: 455370 | C66: 3251 | D66: 3251 | E66: 80212709 | F66: 80212709 | G66: 890501434- 2 | H66: MUNICIPIO DE SAN JOSE DE CUCUTA - SEDE TONCHALA | I66: =VLOOKUP(C66,'mayo-26'!B:H,7,0) -> CALLE 10 NO 0E-16 EDF CENTRO EMPRESARIAL BLOQUE B HOTEL TONCHALA | J66: BARRIO NUEVO | K66: =VLOOKUP(C66,'mayo-26'!B:J,9,0) -> NO | L66: =VLOOKUP(C66,'mayo-26'!B:K,10,0) -> COLEGIOS ZONA NORTE | M66: CÚCUTA MPO | N66: CUCUTA ZONA NORTE | O66: 1002 - CICL FACT DIRECTA CUCUTA NORTE | P66: ASEO INTEGRAL | Q66: NO RESIDENCIAL - ASEO GP | R66: OFICIAL | S66: AFORO ORDINARIO-EXTRAORDINARIO | T66: Ocupado | U66: 2026 | V66: 6 | W66: 1081875026 | X66: 1081893498 | Y66: 46182 | Z66: 46207 | AA66: 134048.12 | AB66: 134048.12 | AC66: 0 | AD66: 508 | AE66: 0 | AF66: 0 | AG66: 0 | AH66: 0 | AI66: 0 | AJ66: 134048.12 | AK66: 400822.34 | AL66: 3 | AM66: 250.8 | AN66: 0 | AS66: =VLOOKUP(C66,'mayo-26'!B:AS,44,0) -> AREAFINANCIERA@SEMCUCUTA.GOV.CO | AT66: =VLOOKUP(C66,'mayo-26'!B:AT,45,0) -> CARTERA
A67: de0ad5bfbd317c3a9c2501a24ecd6e124ca14a01e0b524307426474f5103c6bf816b25be844797579da9d4f1a6f1f9d1 | B67: 328522 | C67: 325715 | D67: 325715 | E67: 572351 | F67: 572351 | G67: 901959258 | H67: PRINT PACK CARIBE S.A.S | I67: =VLOOKUP(C67,'mayo-26'!B:H,7,0) -> AVE 7N 4 - 62 | J67: ZONA INDUSTRIAL | K67: =VLOOKUP(C67,'mayo-26'!B:J,9,0) -> ZONA NORTE | L67: =VLOOKUP(C67,'mayo-26'!B:K,10,0) -> CARIBE | M67: CÚCUTA MPO | N67: CUCUTA DIRECTA | O67: 1002 - CICL FACT DIRECTA CUCUTA NORTE | P67: ASEO INTEGRAL | Q67: NO RESIDENCIAL - ASEO PP | R67: COMERCIAL RANGO 3 | S67: NO AFORADO | T67: Ocupado | U67: 2026 | V67: 6 | W67: 1081875149 | X67: 1081893621 | Y67: 46182 | Z67: 46207 | AA67: 113128.5 | AB67: 113128.5 | AC67: 37709.5 | AD67: 0 | AE67: 0 | AF67: 0 | AG67: 0 | AH67: 0 | AI67: 0 | AJ67: 113128.5 | AK67: 113128.5 | AL67: 0 | AM67: 376.2 | AN67: 0 | AS67: =VLOOKUP(C67,'mayo-26'!B:AS,44,0) -> PRINTPACKCARIBE@HOTMAIL.COM | AT67: =VLOOKUP(C67,'mayo-26'!B:AT,45,0) -> CORREO ELECTRONICO CERTIFICADO 472-VERIFICADOR
A68: 347856ec681392831cc9566f88c9d3c844c32008722da123d5c2ac20f16cdcc52fa3ff5f535c5417ed33b58c85055a7d | B68: 455370 | C68: 3259 | D68: 3259 | E68: 80212717 | F68: 80212717 | G68: 890501434- 2 | H68: MUNICIPIO DE SAN JOSE DE CUCUTA - SEDE TONCHALA | I68: =VLOOKUP(C68,'mayo-26'!B:H,7,0) -> CALLE 10 NO 0E-16 EDF CENTRO EMPRESARIAL BLOQUE B HOTEL TONCHALA | J68: MOTILONES | K68: =VLOOKUP(C68,'mayo-26'!B:J,9,0) -> NO | L68: =VLOOKUP(C68,'mayo-26'!B:K,10,0) -> COLEGIOS ZONA NORTE | M68: CÚCUTA MPO | N68: CUCUTA ZONA NORTE | O68: 1002 - CICL FACT DIRECTA CUCUTA NORTE | P68: ASEO INTEGRAL | Q68: NO RESIDENCIAL - ASEO GP | R68: OFICIAL | S68: AFORO ORDINARIO-EXTRAORDINARIO | T68: Ocupado | U68: 2026 | V68: 6 | W68: 1081875030 | X68: 1081893502 | Y68: 46182 | Z68: 46207 | AA68: 301040.44 | AB68: 301040.44 | AC68: 0 | AD68: 1388 | AE68: 0 | AF68: 0 | AG68: 0 | AH68: 0 | AI68: 0 | AJ68: 301040.44 | AK68: 897870.98 | AL68: 3 | AM68: 250.8 | AN68: 0 | AS68: =VLOOKUP(C68,'mayo-26'!B:AS,44,0) -> AREAFINANCIERA@SEMCUCUTA.GOV.CO | AT68: =VLOOKUP(C68,'mayo-26'!B:AT,45,0) -> CARTERA
A69: 9499dd5117330a9d2b6690cb9056de33995b7b1515e6675fb536bea4f2b2f83912c77fcb2b2007633346c12f86839425 | B69: 455370 | C69: 3263 | D69: 3263 | E69: 80212721 | F69: 80212721 | G69: 890501434- 2 | H69: MUNICIPIO DE SAN JOSE DE CUCUTA - SEDE TONCHALA | I69: =VLOOKUP(C69,'mayo-26'!B:H,7,0) -> CALLE 10 NO 0E-16 EDF CENTRO EMPRESARIAL BLOQUE B HOTEL TONCHALA | J69: PALMERAS | K69: =VLOOKUP(C69,'mayo-26'!B:J,9,0) -> NO | L69: =VLOOKUP(C69,'mayo-26'!B:K,10,0) -> COLEGIOS ZONA NORTE | M69: CÚCUTA MPO | N69: CUCUTA ZONA NORTE | O69: 1002 - CICL FACT DIRECTA CUCUTA NORTE | P69: ASEO INTEGRAL | Q69: NO RESIDENCIAL - ASEO GP | R69: OFICIAL | S69: AFORO ORDINARIO-EXTRAORDINARIO | T69: Ocupado | U69: 2026 | V69: 6 | W69: 1081875034 | X69: 1081893506 | Y69: 46182 | Z69: 46207 | AA69: 165359.17 | AB69: 165359.17 | AC69: 0 | AD69: 673 | AE69: 0 | AF69: 0 | AG69: 0 | AH69: 0 | AI69: 0 | AJ69: 165359.17 | AK69: 494018.94 | AL69: 3 | AM69: 250.8 | AN69: 0 | AS69: =VLOOKUP(C69,'mayo-26'!B:AS,44,0) -> AREAFINANCIERA@SEMCUCUTA.GOV.CO | AT69: =VLOOKUP(C69,'mayo-26'!B:AT,45,0) -> CARTERA
A70: 0c2ef62303a9a2ce019375c3a22eebe344a8a9e667deaf31c1322f299e530a49334ba1751c4f93f88b482f8421e182e9 | B70: 455370 | C70: 3267 | D70: 3267 | E70: 80212725 | F70: 80212725 | G70: 890501434- 2 | H70: MUNICIPIO DE SAN JOSE DE CUCUTA - SEDE TONCHALA | I70: =VLOOKUP(C70,'mayo-26'!B:H,7,0) -> CALLE 10 NO 0E-16 EDF CENTRO EMPRESARIAL BLOQUE B HOTEL TONCHALA | J70: CUNDINAMARCA | K70: =VLOOKUP(C70,'mayo-26'!B:J,9,0) -> NO | L70: =VLOOKUP(C70,'mayo-26'!B:K,10,0) -> COLEGIOS ZONA NORTE | M70: CÚCUTA MPO | N70: CUCUTA ZONA NORTE | O70: 1002 - CICL FACT DIRECTA CUCUTA NORTE | P70: ASEO INTEGRAL | Q70: NO RESIDENCIAL - ASEO GP | R70: OFICIAL | S70: AFORO ORDINARIO-EXTRAORDINARIO | T70: Ocupado | U70: 2026 | V70: 6 | W70: 1081875038 | X70: 1081893510 | Y70: 46182 | Z70: 46207 | AA70: 417176 | AB70: 417176 | AC70: 0 | AD70: 2000 | AE70: 0 | AF70: 0 | AG70: 0 | AH70: 0 | AI70: 0 | AJ70: 417176 | AK70: 1243545.7 | AL70: 3 | AM70: 250.8 | AN70: 0 | AS70: =VLOOKUP(C70,'mayo-26'!B:AS,44,0) -> AREAFINANCIERA@SEMCUCUTA.GOV.CO | AT70: =VLOOKUP(C70,'mayo-26'!B:AT,45,0) -> CARTERA
A71: 347f97e342740423645063cbea2ecd3ea84573b12cea1f2fc0ced7287ad4f6973a7a3d94a4617d5c2ada9ed46294d116 | B71: 326716 | C71: 326715 | D71: 326715 | E71: 590022 | F71: 590022 | G71: 860010973 | H71: ALMACAFE - OTROS | I71: =VLOOKUP(C71,'mayo-26'!B:H,7,0) -> CLL 2 6 - 59 1001 | J71: CALLEJON | K71: =VLOOKUP(C71,'mayo-26'!B:J,9,0) -> NO | L71: =VLOOKUP(C71,'mayo-26'!B:K,10,0) -> NO | M71: CÚCUTA MPO | N71: CUCUTA DIRECTA | O71: 1002 - CICL FACT DIRECTA CUCUTA NORTE | P71: ASEO INTEGRAL | Q71: NO RESIDENCIAL - ASEO GP | R71: INDUSTRIAL | S71: AFORO ORDINARIO-EXTRAORDINARIO | T71: Ocupado | U71: 2026 | V71: 6 | W71: 1081875154 | X71: 1081893626 | Y71: 46182 | Z71: 46207 | AA71: 126650.77 | AB71: 126650.77 | AC71: 29227.1 | AD71: 315 | AE71: 0 | AF71: 0 | AG71: 0 | AH71: 0 | AI71: 0 | AJ71: 126590.79 | AK71: 126590.79 | AL71: 0 | AM71: 326.04 | AN71: 0 | AQ71: 59.98 | AS71: =VLOOKUP(C71,'mayo-26'!B:AS,44,0) -> CUCUTA.ALMACAFE@ALMACAFE.COM.CO | AT71: =VLOOKUP(C71,'mayo-26'!B:AT,45,0) -> CORREO ELECTRONICO CERTIFICADO 472
A72: 0658e657d530f5e4464a294075a1fa36a5f1e9d2d844deadd728a68098f549f5fab48cd15e4c9d5fbeaebba98b082ad0 | B72: 326728 | C72: 326727 | D72: 326727 | E72: 590147 | F72: 590147 | G72: 800092777-1 | H72: GRUPO NOVA S.A | I72: =VLOOKUP(C72,'mayo-26'!B:H,7,0) -> CALLE 18 5-107 ZONA INDUSTRIAL | J72: ZONA INDUSTRIAL | K72: =VLOOKUP(C72,'mayo-26'!B:J,9,0) -> NO | L72: =VLOOKUP(C72,'mayo-26'!B:K,10,0) -> GRUPO NOVA | M72: CÚCUTA MPO | N72: CUCUTA ZONA NORTE | O72: 1002 - CICL FACT DIRECTA CUCUTA NORTE | P72: ASEO INTEGRAL | Q72: NO RESIDENCIAL - ASEO GP | R72: INDUSTRIAL | S72: AFORO ORDINARIO-EXTRAORDINARIO | T72: Ocupado | U72: 2026 | V72: 6 | W72: 1081875158 | X72: 1081893630 | Y72: 46182 | Z72: 46207 | AA72: 111232.45 | AB72: 111232.45 | AC72: 25669.03 | AD72: 252.5 | AE72: 0 | AF72: 0 | AG72: 0 | AH72: 0 | AI72: 0 | AJ72: 111232.45 | AK72: 111232.45 | AL72: 0 | AM72: 326.04 | AN72: 0 | AS72: =VLOOKUP(C72,'mayo-26'!B:AS,44,0) -> 800092777@FACTUREINBOX.CO | AT72: =VLOOKUP(C72,'mayo-26'!B:AT,45,0) -> CORREO ELECTRONICO CERTIFICADO 472
A73: c912120c19a6090e3a7f6749730b2295c1c8df1294102c9851f8417e50193cb803b831332b1c8bbf554f8d11b2581ed3 | B73: 326736 | C73: 326735 | D73: 326735 | E73: 590264 | F73: 590264 | G73: 900949670-3 | H73: JEMA PROJECTS S.A.S | I73: =VLOOKUP(C73,'mayo-26'!B:H,7,0) -> CLL 8N 4 - 61 1219 | J73: ZONA INDUSTRIAL | K73: =VLOOKUP(C73,'mayo-26'!B:J,9,0) -> NO | L73: =VLOOKUP(C73,'mayo-26'!B:K,10,0) -> NO | M73: CÚCUTA MPO | N73: CUCUTA DIRECTA | O73: 1002 - CICL FACT DIRECTA CUCUTA NORTE | P73: ASEO INTEGRAL | Q73: NO RESIDENCIAL - ASEO GP | R73: INDUSTRIAL | S73: AFORO ORDINARIO-EXTRAORDINARIO | T73: Ocupado | U73: 2026 | V73: 6 | W73: 1081875161 | X73: 1081893633 | Y73: 46182 | Z73: 46207 | AA73: 142685.81 | AB73: 142685.81 | AC73: 32927.49 | AD73: 380 | AE73: 0 | AF73: 0 | AG73: 0 | AH73: 0 | AI73: 0 | AJ73: 142685.81 | AK73: 142685.81 | AL73: 0 | AM73: 326.04 | AN73: 0 | AS73: =VLOOKUP(C73,'mayo-26'!B:AS,44,0) -> JEMAPROJECTSAS@GMAIL.COM | AT73: =VLOOKUP(C73,'mayo-26'!B:AT,45,0) -> CORREO ELECTRONICO CERTIFICADO 472
A74: ded087fe2ee5e285c97106a1f93b95571f08f94fcf3f52fbe5272543d9cbd548cc945dd9851194b1bb01801464a098c6 | B74: 326740 | C74: 326739 | D74: 326739 | E74: 590298 | F74: 590298 | G74: 890503844-8 | H74: TRAPEROS EL MEJOR LTDA - OTROS | I74: =VLOOKUP(C74,'mayo-26'!B:H,7,0) -> CLL 8N 4 - 13 1219 | J74: ZONA INDUSTRIAL | K74: =VLOOKUP(C74,'mayo-26'!B:J,9,0) -> NO | L74: =VLOOKUP(C74,'mayo-26'!B:K,10,0) -> NO | M74: CÚCUTA MPO | N74: CUCUTA DIRECTA | O74: 1002 - CICL FACT DIRECTA CUCUTA NORTE | P74: ASEO INTEGRAL | Q74: NO RESIDENCIAL - ASEO GP | R74: INDUSTRIAL | S74: AFORO ORDINARIO-EXTRAORDINARIO | T74: Ocupado | U74: 2026 | V74: 6 | W74: 1081875164 | X74: 1081893636 | Y74: 46182 | Z74: 46207 | AA74: 205592.6 | AB74: 205592.6 | AC74: 47444.45 | AD74: 635 | AE74: 0 | AF74: 0 | AG74: 0 | AH74: 0 | AI74: 0 | AJ74: 205592.6 | AK74: 205592.6 | AL74: 0 | AM74: 326.04 | AN74: 0 | AS74: =VLOOKUP(C74,'mayo-26'!B:AS,44,0) -> CONTABILIDADTRAPEROSELMEJOR@GMAIL.COM | AT74: =VLOOKUP(C74,'mayo-26'!B:AT,45,0) -> CORREO ELECTRONICO CERTIFICADO 472
A75: c8c179be39aae9533f619c9caf46db017f9c6bf91300073a42af80c9de7e40f4ced3c84a3c2cfeb114c97808e44ae9bf | B75: 455370 | C75: 3271 | D75: 3271 | E75: 80212729 | F75: 80212729 | G75: 890501434- 2 | H75: MUNICIPIO DE SAN JOSE DE CUCUTA - SEDE TONCHALA | I75: =VLOOKUP(C75,'mayo-26'!B:H,7,0) -> CALLE 10 NO 0E-16 EDF CENTRO EMPRESARIAL BLOQUE B HOTEL TONCHALA | J75: SEVILLA | K75: =VLOOKUP(C75,'mayo-26'!B:J,9,0) -> NO | L75: =VLOOKUP(C75,'mayo-26'!B:K,10,0) -> COLEGIOS ZONA NORTE | M75: CÚCUTA MPO | N75: CUCUTA ZONA NORTE | O75: 1002 - CICL FACT DIRECTA CUCUTA NORTE | P75: ASEO INTEGRAL | Q75: NO RESIDENCIAL - ASEO GP | R75: OFICIAL | S75: AFORO ORDINARIO-EXTRAORDINARIO | T75: Ocupado | U75: 2026 | V75: 6 | W75: 1081875042 | X75: 1081893514 | Y75: 46182 | Z75: 46207 | AA75: 199896.23 | AB75: 199896.23 | AC75: 0 | AD75: 855 | AE75: 0 | AF75: 0 | AG75: 0 | AH75: 0 | AI75: 0 | AJ75: 199896.23 | AK75: 596817.66 | AL75: 3 | AM75: 250.8 | AN75: 0 | AS75: =VLOOKUP(C75,'mayo-26'!B:AS,44,0) -> AREAFINANCIERA@SEMCUCUTA.GOV.CO | AT75: =VLOOKUP(C75,'mayo-26'!B:AT,45,0) -> CARTERA
A76: fb3afaf3c5b2c34a0321dfcd3b8c2f8ade34ecaeff1e04797b3115608154a7f14858c63387adc39360326abe0b67c1ad | B76: 455370 | C76: 3275 | D76: 3275 | E76: 80212733 | F76: 80212733 | G76: 890501434- 2 | H76: MUNICIPIO DE SAN JOSE DE CUCUTA - SEDE TONCHALA | I76: =VLOOKUP(C76,'mayo-26'!B:H,7,0) -> CALLE 10 NO 0E-16 EDF CENTRO EMPRESARIAL BLOQUE B HOTEL TONCHALA | J76: ATALAYA I ETAPA | K76: =VLOOKUP(C76,'mayo-26'!B:J,9,0) -> NO | L76: =VLOOKUP(C76,'mayo-26'!B:K,10,0) -> COLEGIOS ZONA NORTE | M76: CÚCUTA MPO | N76: CUCUTA ZONA NORTE | O76: 1002 - CICL FACT DIRECTA CUCUTA NORTE | P76: ASEO INTEGRAL | Q76: NO RESIDENCIAL - ASEO GP | R76: OFICIAL | S76: AFORO ORDINARIO-EXTRAORDINARIO | T76: Ocupado | U76: 2026 | V76: 6 | W76: 1081875045 | X76: 1081893517 | Y76: 46182 | Z76: 46207 | AA76: 178642.65 | AB76: 178642.65 | AC76: 0 | AD76: 743 | AE76: 0 | AF76: 0 | AG76: 0 | AH76: 0 | AI76: 0 | AJ76: 178642.65 | AK76: 533556.9 | AL76: 3 | AM76: 250.8 | AN76: 0 | AS76: =VLOOKUP(C76,'mayo-26'!B:AS,44,0) -> AREAFINANCIERA@SEMCUCUTA.GOV.CO | AT76: =VLOOKUP(C76,'mayo-26'!B:AT,45,0) -> CARTERA
A77: 83cfc6ad918d511dea13db99f03b96cd25c3403a67466e5e8ddfd586f1cb4f97bb73bba96157634b0fe2b284b13d1bf3 | B77: 455370 | C77: 3279 | D77: 3279 | E77: 80212737 | F77: 80212737 | G77: 890501434- 2 | H77: MUNICIPIO DE SAN JOSE DE CUCUTA - SEDE TONCHALA | I77: =VLOOKUP(C77,'mayo-26'!B:H,7,0) -> CALLE 10 NO 0E-16 EDF CENTRO EMPRESARIAL BLOQUE B HOTEL TONCHALA | J77: LOS OLIVOS | K77: =VLOOKUP(C77,'mayo-26'!B:J,9,0) -> NO | L77: =VLOOKUP(C77,'mayo-26'!B:K,10,0) -> COLEGIOS ZONA NORTE | M77: CÚCUTA MPO | N77: CUCUTA ZONA NORTE | O77: 1002 - CICL FACT DIRECTA CUCUTA NORTE | P77: ASEO INTEGRAL | Q77: NO RESIDENCIAL - ASEO GP | R77: OFICIAL | S77: AFORO ORDINARIO-EXTRAORDINARIO | T77: Ocupado | U77: 2026 | V77: 6 | W77: 1081875051 | X77: 1081893523 | Y77: 46182 | Z77: 46207 | AA77: 286238.84 | AB77: 286238.84 | AC77: 0 | AD77: 1310 | AE77: 0 | AF77: 0 | AG77: 0 | AH77: 0 | AI77: 0 | AJ77: 286238.84 | AK77: 853814.38 | AL77: 3 | AM77: 250.8 | AN77: 0 | AS77: =VLOOKUP(C77,'mayo-26'!B:AS,44,0) -> AREAFINANCIERA@SEMCUCUTA.GOV.CO | AT77: =VLOOKUP(C77,'mayo-26'!B:AT,45,0) -> CARTERA
A78: 199ea59406de7caa156ee61884b86ed9e687f7ba22f23c726e9b027bbd32eada8a9538b3421fec28228c860e54b1256f | B78: 455370 | C78: 3283 | D78: 3283 | E78: 80215347 | F78: 80215347 | G78: 890501434- 2 | H78: MUNICIPIO DE SAN JOSE DE CUCUTA - SEDE TONCHALA | I78: =VLOOKUP(C78,'mayo-26'!B:H,7,0) -> CALLE 10 NO 0E-16 EDF CENTRO EMPRESARIAL BLOQUE B HOTEL TONCHALA | J78: EL SALADO | K78: =VLOOKUP(C78,'mayo-26'!B:J,9,0) -> NO | L78: =VLOOKUP(C78,'mayo-26'!B:K,10,0) -> COLEGIOS ZONA NORTE | M78: CÚCUTA MPO | N78: CUCUTA ZONA NORTE | O78: 1002 - CICL FACT DIRECTA CUCUTA NORTE | P78: ASEO INTEGRAL | Q78: NO RESIDENCIAL - ASEO GP | R78: OFICIAL | S78: AFORO ORDINARIO-EXTRAORDINARIO | T78: Ocupado | U78: 2026 | V78: 6 | W78: 1081875055 | X78: 1081893527 | Y78: 46182 | Z78: 46207 | AA78: 85658.29 | AB78: 85658.29 | AC78: 0 | AD78: 253 | AE78: 0 | AF78: 0 | AG78: 0 | AH78: 0 | AI78: 0 | AJ78: 85658.29 | AK78: 256791.18 | AL78: 3 | AM78: 250.8 | AN78: 0 | AS78: =VLOOKUP(C78,'mayo-26'!B:AS,44,0) -> AREAFINANCIERA@SEMCUCUTA.GOV.CO | AT78: =VLOOKUP(C78,'mayo-26'!B:AT,45,0) -> CARTERA
A79: 1eb41c23a8ffba191d0ab3cf3594af37ca784ef7b5710df7360feb6ccd9aabc1977dc89cab03a4f74bf6b0b410d2acbc | B79: 503 | C79: 3287 | D79: 3287 | E79: 80217312 | F79: 80217312 | G79: 805003626-4 | H79: STF GROUP SA | I79: =VLOOKUP(C79,'mayo-26'!B:H,7,0) -> CLL 10 0E-51 SUB 4 ARM 8 LOCAL 1 | J79: PRADOS NORTE | K79: =VLOOKUP(C79,'mayo-26'!B:J,9,0) -> NO | L79: =VLOOKUP(C79,'mayo-26'!B:K,10,0) -> VERTEBRA | M79: CÚCUTA MPO | N79: CUCUTA DIRECTA | O79: 1002 - CICL FACT DIRECTA CUCUTA NORTE | P79: ASEO INTEGRAL | Q79: NO RESIDENCIAL - ASEO GP | R79: COMERCIAL | S79: AFORO ORDINARIO-EXTRAORDINARIO | T79: Ocupado | U79: 2026 | V79: 6 | W79: 1081875058 | X79: 1081893530 | Y79: 46182 | Z79: 46207 | AA79: 262840.37 | AB79: 262840.37 | AC79: 87613.46 | AD79: 725 | AE79: 0 | AF79: 0 | AG79: 0 | AH79: 0 | AI79: 0 | AJ79: 262840.37 | AK79: 262840.37 | AL79: 0 | AM79: 376.2 | AN79: 0 | AS79: =VLOOKUP(C79,'mayo-26'!B:AS,44,0) -> FACTURAS@VERTEBRA.TECH | AT79: =VLOOKUP(C79,'mayo-26'!B:AT,45,0) -> CORREO ELECTRONICO CERTIFICADO 472
A80: 0c5798119fa004cdfcae36f4f69de6ac533b91139ffd8b829f9ccb18b4fad0ee35c75a2df34ad87846db76e6491ac82f | B80: 455370 | C80: 3291 | D80: 3291 | E80: 80218483 | F80: 80218483 | G80: 890501434- 2 | H80: MUNICIPIO DE SAN JOSE DE CUCUTA - SEDE TONCHALA | I80: =VLOOKUP(C80,'mayo-26'!B:H,7,0) -> CALLE 10 NO 0E-16 EDF CENTRO EMPRESARIAL BLOQUE B HOTEL TONCHALA | J80: TRIGAL DEL NORTE | K80: =VLOOKUP(C80,'mayo-26'!B:J,9,0) -> NO | L80: =VLOOKUP(C80,'mayo-26'!B:K,10,0) -> COLEGIOS ZONA NORTE | M80: CÚCUTA MPO | N80: CUCUTA ZONA NORTE | O80: 1002 - CICL FACT DIRECTA CUCUTA NORTE | P80: ASEO INTEGRAL | Q80: NO RESIDENCIAL - ASEO GP | R80: OFICIAL | S80: AFORO ORDINARIO-EXTRAORDINARIO | T80: Ocupado | U80: 2026 | V80: 6 | W80: 1081875061 | X80: 1081893533 | Y80: 46182 | Z80: 46207 | AA80: 568987.2 | AB80: 568987.2 | AC80: 0 | AD80: 2800 | AE80: 0 | AF80: 0 | AG80: 0 | AH80: 0 | AI80: 0 | AJ80: 568987.2 | AK80: 1695408.1 | AL80: 3 | AM80: 250.8 | AN80: 0 | AS80: =VLOOKUP(C80,'mayo-26'!B:AS,44,0) -> AREAFINANCIERA@SEMCUCUTA.GOV.CO | AT80: =VLOOKUP(C80,'mayo-26'!B:AT,45,0) -> CARTERA
A81: ff4a7d0c8da41935f0acf6438222ba68e4ce4d2b4d4d98c3297ef6659dfc864439d4970b458190d94c01608f276a97c7 | B81: 3300 | C81: 3299 | D81: 3299 | E81: 80222486 | F81: 80222486 | G81: 899999239 | H81: INST. COL. DE BIENESTAR FAMILIAR | I81: =VLOOKUP(C81,'mayo-26'!B:H,7,0) -> AV 6 1-105 KDX 46A INSULA | J81: LA INSULA | K81: =VLOOKUP(C81,'mayo-26'!B:J,9,0) -> NO | L81: =VLOOKUP(C81,'mayo-26'!B:K,10,0) -> BIENESTAR FAMILIAR | M81: CÚCUTA MPO | N81: CUCUTA DIRECTA | O81: 1002 - CICL FACT DIRECTA CUCUTA NORTE | P81: ASEO INTEGRAL | Q81: NO RESIDENCIAL - ASEO GP | R81: OFICIAL | S81: AFORO ORDINARIO-EXTRAORDINARIO | T81: Ocupado | U81: 2026 | V81: 6 | W81: 1081875065 | X81: 1081893537 | Y81: 46182 | Z81: 46207 | AA81: 85563.42 | AB81: 85563.42 | AC81: 0 | AD81: 252.5 | AE81: 0 | AF81: 0 | AG81: 0 | AH81: 0 | AI81: 0 | AJ81: 85563.42 | AK81: 85563.42 | AL81: 0 | AM81: 250.8 | AN81: 0 | AS81: =VLOOKUP(C81,'mayo-26'!B:AS,44,0) -> MAYRA.SALCEDO@ICBF.GOV.CO | AT81: =VLOOKUP(C81,'mayo-26'!B:AT,45,0) -> CORREO ELECTRONICO CERTIFICADO 472
A82: 364714ec40ffbd72d3986aca49bf20904e94e13c320bbf3c1637038c1763861377c34741ab8f1e9b0ee449ebd6bb771a | B82: 3304 | C82: 3303 | D82: 3303 | E82: 80223054 | F82: 80223054 | G82: 901447404 | H82: ELBERT NAUN ARIAS URIBE | I82: =VLOOKUP(C82,'mayo-26'!B:H,7,0) -> AVE 5 8N-46 ZONA INDUSTRIAL | J82: ZONA INDUSTRIAL | K82: =VLOOKUP(C82,'mayo-26'!B:J,9,0) -> NO | L82: =VLOOKUP(C82,'mayo-26'!B:K,10,0) -> NO | M82: CÚCUTA MPO | N82: CUCUTA DIRECTA | O82: 1002 - CICL FACT DIRECTA CUCUTA NORTE | P82: ASEO INTEGRAL | Q82: NO RESIDENCIAL - ASEO PP | R82: INDUSTRIAL RANGO 3 | S82: NO AFORADO | T82: Ocupado | U82: 2026 | V82: 6 | W82: 1081875069 | X82: 1081893541 | Y82: 46182 | Z82: 46207 | AA82: 98044.7 | AB82: 98044.7 | AC82: 22625.7 | AD82: 0 | AE82: 0 | AF82: 0 | AG82: 0 | AH82: 0 | AI82: 0 | AJ82: 98044.7 | AK82: 196768 | AL82: 1 | AM82: 326.04 | AN82: 0 | AS82: =VLOOKUP(C82,'mayo-26'!B:AS,44,0) -> IANCOMPANY03@GMAIL.COM | AT82: =VLOOKUP(C82,'mayo-26'!B:AT,45,0) -> CORREO ELECTRONICO CERTIFICADO 472
A83: 1c42fec38cdb8d3fa8be904ce27b359285892189cd5bd8c756504559af8adc4dd1b80ac425936c7d1c3df4febc5bea21 | B83: 147 | C83: 3311 | D83: 3311 | E83: 80230160 | F83: 80230160 | G83: 800141397-5 | H83: POLICIA NACIONAL-DIRECCION LOGISTICA Y FINANCIERA | I83: =VLOOKUP(C83,'mayo-26'!B:H,7,0) -> AVE 3 CLL 24 GARITA # 1 | J83: SAN FAUSTINO | K83: =VLOOKUP(C83,'mayo-26'!B:J,9,0) -> NO | L83: =VLOOKUP(C83,'mayo-26'!B:K,10,0) -> POLICIA | M83: CÚCUTA MPO | N83: CUCUTA DIRECTA RURAL | O83: 1002 - CICL FACT DIRECTA CUCUTA NORTE | P83: ASEO INTEGRAL | Q83: NO RESIDENCIAL - ASEO GP | R83: OFICIAL | S83: AFORO ORDINARIO-EXTRAORDINARIO | T83: Ocupado | U83: 2026 | V83: 6 | W83: 1081875073 | X83: 1081893545 | Y83: 46182 | Z83: 46207 | AA83: 51712.42 | AB83: 51712.42 | AC83: 0 | AD83: 252.5 | AE83: 0 | AF83: 0 | AG83: 0 | AH83: 0 | AI83: 0 | AJ83: 51712.42 | AK83: 103438.11 | AL83: 2 | AM83: 250.8 | AN83: 0 | AS83: =VLOOKUP(C83,'mayo-26'!B:AS,44,0) -> MECUC.GUBIR@POLICIA.GOV.CO | AT83: =VLOOKUP(C83,'mayo-26'!B:AT,45,0) -> CORREO ELECTRONICO CERTIFICADO 472
A84: 6400bba4ffc6b93788f66a74dccd92cc27f95871e787f2ebd84b9a5e2aebc3b4e1320c7bf9d0f05e0b896bc75b7db935 | B84: 3320 | C84: 3319 | D84: 3319 | E84: 80231088 | F84: 80231088 | G84: 900121262-7 | H84: PLASTICOS FORMOSA LIMITADA | I84: =VLOOKUP(C84,'mayo-26'!B:H,7,0) -> AV 7 A 1 141 BRR PANAMERICANO BG UNO Y DOS | J84: PANAMERICANO | K84: =VLOOKUP(C84,'mayo-26'!B:J,9,0) -> NO | L84: =VLOOKUP(C84,'mayo-26'!B:K,10,0) -> NO | M84: CÚCUTA MPO | N84: CUCUTA DIRECTA | O84: 1002 - CICL FACT DIRECTA CUCUTA NORTE | P84: ASEO INTEGRAL | Q84: NO RESIDENCIAL - ASEO GP | R84: INDUSTRIAL | S84: AFORO ORDINARIO-EXTRAORDINARIO | T84: Ocupado | U84: 2026 | V84: 6 | W84: 1081875076 | X84: 1081893548 | Y84: 46182 | Z84: 46207 | AA84: 1510599.6 | AB84: 1510599.6 | AC84: 348599.91 | AD84: 5925 | AE84: 0 | AF84: 0 | AG84: 0 | AH84: 0 | AI84: 0 | AJ84: 1510599.6 | AK84: 1510599.6 | AL84: 0 | AM84: 326.04 | AN84: 0 | AS84: =VLOOKUP(C84,'mayo-26'!B:AS,44,0) -> CEXTERIOR@PLASTICOSFORMOSA.COM | AT84: =VLOOKUP(C84,'mayo-26'!B:AT,45,0) -> CORREO ELECTRONICO CERTIFICADO 472
A85: 0c644e48128441bb30f6672179ab42607b05a1e45acf8a4b23ed1397ba585e8d5e9bd89f4c45f2c0b96330929854f824 | B85: 3324 | C85: 3323 | D85: 3323 | E85: 80231294 | F85: 80231294 | G85: 901376551 | H85: INDUSTRIAS DARWIN GARCIA | I85: =VLOOKUP(C85,'mayo-26'!B:H,7,0) -> AVE 6 15 - 04 1114 | J85: EL SALADO | K85: =VLOOKUP(C85,'mayo-26'!B:J,9,0) -> NO | L85: =VLOOKUP(C85,'mayo-26'!B:K,10,0) -> NO | M85: CÚCUTA MPO | N85: CUCUTA DIRECTA | O85: 1002 - CICL FACT DIRECTA CUCUTA NORTE | P85: ASEO INTEGRAL | Q85: NO RESIDENCIAL - ASEO GP | R85: INDUSTRIAL | S85: AFORO ORDINARIO-EXTRAORDINARIO | T85: Ocupado | U85: 2026 | V85: 6 | W85: 1081875080 | X85: 1081893552 | Y85: 46182 | Z85: 46207 | AA85: 141452.37 | AB85: 141452.37 | AC85: 32642.86 | AD85: 375 | AE85: 0 | AF85: 0 | AG85: 0 | AH85: 0 | AI85: 0 | AJ85: 141452.37 | AK85: 141452.37 | AL85: 0 | AM85: 326.04 | AN85: 0 | AS85: =VLOOKUP(C85,'mayo-26'!B:AS,44,0) -> INDUSTRIAS_DG@HOTMAIL.COM | AT85: =VLOOKUP(C85,'mayo-26'!B:AT,45,0) -> CORREO ELECTRONICO CERTIFICADO 472
A86: 16ea7cd0d26029418e8b08cfbe47fc575df5306bbf2421cf443b03ca1dbfa7440e25cec1e9eb1da580479cf4b3128b73 | B86: 379563 | C86: 3331 | D86: 3331 | E86: 80268022 | F86: 80268022 | G86: 805003626 | H86: STUDIO F/STUDIO GROUP SA | I86: =VLOOKUP(C86,'mayo-26'!B:H,7,0) -> CC JARDIN PLAZA L65 | J86: PRADOS NORTE | K86: =VLOOKUP(C86,'mayo-26'!B:J,9,0) -> NO | L86: =VLOOKUP(C86,'mayo-26'!B:K,10,0) -> VERTEBRA | M86: CÚCUTA MPO | N86: CUCUTA ZONA NORTE | O86: 1002 - CICL FACT DIRECTA CUCUTA NORTE | P86: ASEO INTEGRAL | Q86: NO RESIDENCIAL - ASEO GP | R86: COMERCIAL | S86: AFORO ORDINARIO-EXTRAORDINARIO | T86: Ocupado | U86: 2026 | V86: 6 | W86: 1081875083 | X86: 1081893555 | Y86: 46182 | Z86: 46207 | AA86: 262840.37 | AB86: 262840.37 | AC86: 87613.46 | AD86: 725 | AE86: 0 | AF86: 0 | AG86: 0 | AH86: 0 | AI86: 0 | AJ86: 262840.37 | AK86: 262840.37 | AL86: 0 | AM86: 376.2 | AN86: 0 | AS86: =VLOOKUP(C86,'mayo-26'!B:AS,44,0) -> FACTURAS@VERTEBRA.TECH | AT86: =VLOOKUP(C86,'mayo-26'!B:AT,45,0) -> CORREO ELECTRONICO CERTIFICADO 472
A87: b9f1bb60ed447cc68c5d4cfd3cc60e9425bed64eba6cbcc43a28fad7ca278d0aef21b93aed710bdcdc2bc82ef69b1fa4 | B87: 341068 | C87: 341067 | D87: 341067 | E87: 134 | F87: 134 | G87: 890401958 | H87: INCOLMINE S.A. (MINA 1PRESIDENT) | I87: =VLOOKUP(C87,'mayo-26'!B:H,7,0) -> VIA A SAN FAUSTINO 443976 | J87: CERRO TASAJERO | K87: =VLOOKUP(C87,'mayo-26'!B:J,9,0) -> NO | L87: =VLOOKUP(C87,'mayo-26'!B:K,10,0) -> NO | M87: CÚCUTA MPO | N87: CUCUTA DIRECTA | O87: 1002 - CICL FACT DIRECTA CUCUTA NORTE | P87: ASEO INTEGRAL | Q87: NO RESIDENCIAL - ASEO GP | R87: INDUSTRIAL | S87: AFORO ORDINARIO-EXTRAORDINARIO | T87: Ocupado | U87: 2026 | V87: 6 | W87: 1081875169 | X87: 1081893641 | Y87: 46182 | Z87: 46207 | AA87: 727348.71 | AB87: 727348.71 | AC87: 167849.71 | AD87: 2750 | AE87: 0 | AF87: 0 | AG87: 0 | AH87: 0 | AI87: 0 | AJ87: 727348.71 | AK87: 730329.95 | AL87: 1 | AM87: 326.04 | AN87: 0 | AS87: =VLOOKUP(C87,'mayo-26'!B:AS,44,0) -> FACTURAS@INCOLMINESA.COM;NELLY.LEON@INCOLMINESA.COM | AT87: =VLOOKUP(C87,'mayo-26'!B:AT,45,0) -> CORREO ELECTRONICO CERTIFICADO 472
A88: 00e36449032b5b14a599b6bc09fa4b9e3085667505b36ed59bce87e20ed5da038dd3fa9f276b35256a3f3622a3a0c18e | B88: 699 | C88: 359375 | D88: 359814 | E88: 1032589 | F88: 1032589 | G88: 900480569 | H88: JERONIMO MARTINS COLOMBIA SAS | I88: =VLOOKUP(C88,'mayo-26'!B:H,7,0) -> CLL 12 4-52 CENTRO | J88: OSPINA PEREZ | K88: =VLOOKUP(C88,'mayo-26'!B:J,9,0) -> NO | L88: =VLOOKUP(C88,'mayo-26'!B:K,10,0) -> ARA CUCUTA | M88: CÚCUTA MPO | N88: CUCUTA ZONA NORTE | O88: 1002 - CICL FACT DIRECTA CUCUTA NORTE | P88: ASEO INTEGRAL | Q88: NO RESIDENCIAL - ASEO GP | R88: COMERCIAL | S88: AFORO ORDINARIO-EXTRAORDINARIO | T88: Ocupado | U88: 2026 | V88: 6 | W88: 1081875173 | X88: 1081893645 | Y88: 46182 | Z88: 46207 | AA88: 439320.89 | AB88: 439320.89 | AC88: 146440.3 | AD88: 1345 | AE88: 0 | AF88: 0 | AG88: 0 | AH88: 0 | AI88: 0 | AJ88: 439320.89 | AK88: 879507.6 | AL88: 1 | AM88: 376.2 | AN88: 0 | AS88: =VLOOKUP(C88,'mayo-26'!B:AS,44,0) -> COORDINADOR.OPERACIONES.R11@JERONIMO-MARTINS.COM | AT88: =VLOOKUP(C88,'mayo-26'!B:AT,45,0) -> CORREO ELECTRONICO CERTIFICADO 472
A89: d36d7c296cf185cca04c901879fe5ba25664554d41a995a2ac6b8b58b7b0e3caa2f8ef4a6f20a54791e5dcae54746741 | B89: 699 | C89: 384359 | D89: 398615 | E89: 1062121 | F89: 1062121 | G89: 900480569 | H89: JERONIMO MARTINS COLOMBIA SAS | I89: =VLOOKUP(C89,'mayo-26'!B:H,7,0) -> CLL 12 4-52 CENTRO | J89: VIRGILIO BARCO | K89: =VLOOKUP(C89,'mayo-26'!B:J,9,0) -> NO | L89: =VLOOKUP(C89,'mayo-26'!B:K,10,0) -> ARA CUCUTA | M89: CÚCUTA MPO | N89: CUCUTA ZONA NORTE | O89: 1002 - CICL FACT DIRECTA CUCUTA NORTE | P89: ASEO INTEGRAL | Q89: NO RESIDENCIAL - ASEO GP | R89: COMERCIAL | S89: AFORO ORDINARIO-EXTRAORDINARIO | T89: Ocupado | U89: 2026 | V89: 6 | W89: 1081875177 | X89: 1081893649 | Y89: 46182 | Z89: 46207 | AA89: 684116.47 | AB89: 684116.47 | AC89: 228038.82 | AD89: 2205 | AE89: 0.02 | AF89: 0 | AG89: 0 | AH89: 0 | AI89: 0 | AJ89: 684116.47 | AK89: 1369160.8 | AL89: 2 | AM89: 376.2 | AN89: 0 | AS89: =VLOOKUP(C89,'mayo-26'!B:AS,44,0) -> COORDINADOR.OPERACIONES.R11@JERONIMO-MARTINS.COM | AT89: =VLOOKUP(C89,'mayo-26'!B:AT,45,0) -> CORREO ELECTRONICO CERTIFICADO 472
A90: dfa531ca6c51c794c16e5c95e60c4dc20c8686b9b5652ba0a8af57460afad14f6efa67cad0b4cb37a32a931d03f399e1 | B90: 699 | C90: 424607 | D90: 440248 | E90: 1040382 | F90: 1040382 | G90: 900480569 | H90: JERONIMO MARTINS COLOMBIA SAS | I90: =VLOOKUP(C90,'mayo-26'!B:H,7,0) -> CLL 12 4-52 CENTRO | J90: PRADOS NORTE | K90: =VLOOKUP(C90,'mayo-26'!B:J,9,0) -> NO | L90: =VLOOKUP(C90,'mayo-26'!B:K,10,0) -> ARA CUCUTA | M90: CÚCUTA MPO | N90: CUCUTA ZONA NORTE | O90: 1002 - CICL FACT DIRECTA CUCUTA NORTE | P90: ASEO INTEGRAL | Q90: NO RESIDENCIAL - ASEO GP | R90: COMERCIAL | S90: AFORO ORDINARIO-EXTRAORDINARIO | T90: Ocupado | U90: 2026 | V90: 6 | W90: 1081875181 | X90: 1081893653 | Y90: 46182 | Z90: 46207 | AA90: 675577.08 | AB90: 675577.08 | AC90: 225192.37 | AD90: 2175 | AE90: 0 | AF90: 0 | AG90: 0 | AH90: 0 | AI90: 0 | AJ90: 675577.08 | AK90: 675577.08 | AL90: 0 | AM90: 376.2 | AN90: 0 | AS90: =VLOOKUP(C90,'mayo-26'!B:AS,44,0) -> COORDINADOR.OPERACIONES.R11@JERONIMO-MARTINS.COM | AT90: =VLOOKUP(C90,'mayo-26'!B:AT,45,0) -> CORREO ELECTRONICO CERTIFICADO 472
A91: 01d7ced8ef289914ce0e914adf941322e984425297b1db0c4fa9fe40be6afca2cac4ebc873447ae0984f80033a9f0548 | B91: 551414 | C91: 476095 | D91: 517335 | G91: 901461238 | H91: CARBONES MINERALES BC | I91: =VLOOKUP(C91,'mayo-26'!B:H,7,0) -> CORREGIMIENTO SAN FAUSTINO | J91: SIN DETERMINAR | K91: =VLOOKUP(C91,'mayo-26'!B:J,9,0) -> NO | L91: =VLOOKUP(C91,'mayo-26'!B:K,10,0) -> NO | M91: CÚCUTA MPO | N91: CUCUTA DIRECTA | O91: 1002 - CICL FACT DIRECTA CUCUTA NORTE | P91: ASEO INTEGRAL | Q91: NO RESIDENCIAL - ASEO GP | R91: COMERCIAL | S91: AFORO ORDINARIO-EXTRAORDINARIO | T91: Ocupado | U91: 2026 | V91: 6 | W91: 1081875183 | X91: 1081893655 | Y91: 46182 | Z91: 46207 | AA91: 229789.2 | AB91: 229789.2 | AC91: 66265 | AD91: 500 | AE91: 30994.2 | AF91: 0 | AG91: 0 | AH91: 0 | AI91: 0 | AJ91: 229789.2 | AK91: 2173440.7 | AL91: 10 | AM91: 376.2 | AN91: 0 | AS91: =VLOOKUP(C91,'mayo-26'!B:AS,44,0) -> CARBONESMINERALESBC@GMAIL.COM | AT91: =VLOOKUP(C91,'mayo-26'!B:AT,45,0) -> CORREO ELECTRONICO CERTIFICADO 472
A92: 03320ef276a08e0873f266fc4948ac000770ee0f5f20fbd6a72bd585518bc3f1d6ed7bdf316f74d7e02d4f2c4a15a105 | B92: 595130 | C92: 498511 | D92: 551616 | G92: 1254988 | H92: ESPERANZA CASTRO MUNEVAR | I92: =VLOOKUP(C92,'mayo-26'!B:H,7,0) -> CLL 14AN 4A-81 TORRE 1 APTO 104 | J92: PORTACHUELO | K92: =VLOOKUP(C92,'mayo-26'!B:J,9,0) -> CR PORTACHUELO | L92: =VLOOKUP(C92,'mayo-26'!B:K,10,0) -> CR PORTACHUELO | M92: CÚCUTA MPO | N92: CUCUTA DIRECTA | O92: 1002 - CICL FACT DIRECTA CUCUTA NORTE | P92: ASEO INTEGRAL | Q92: RESIDENCIAL | R92: ESTRATO 3 | S92: NO AFORADO | T92: Ocupado | U92: 2026 | V92: 6 | W92: 1081875188 | X92: 1081893660 | Y92: 46182 | Z92: 46207 | AA92: 49934.3 | AB92: 49934.3 | AC92: -1650.7 | AD92: 0 | AE92: 0 | AF92: 0 | AG92: 0 | AH92: 0 | AI92: 0 | AJ92: 49934.3 | AK92: 49935.06 | AL92: 1 | AM92: 242.77 | AN92: 0 | AS92: =VLOOKUP(C92,'mayo-26'!B:AS,44,0) | AT92: =VLOOKUP(C92,'mayo-26'!B:AT,45,0) -> VERIFICADOR
A93: 22e61c91832a6c2587fe99f90254a3293fec83c2f236d303dd38cbc2cabebd10d7ee7266f91447bfb6e8835f90ca8693 | B93: 595134 | C93: 498515 | D93: 551620 | G93: 1254992 | H93: JHOVANY FERNANDO ZAMBRANO JIMENEZ | I93: =VLOOKUP(C93,'mayo-26'!B:H,7,0) -> CLL 14AN 4A-81 TORRE 1 APTO 204 | J93: PORTACHUELO | K93: =VLOOKUP(C93,'mayo-26'!B:J,9,0) -> CR PORTACHUELO | L93: =VLOOKUP(C93,'mayo-26'!B:K,10,0) -> CR PORTACHUELO | M93: CÚCUTA MPO | N93: CUCUTA DIRECTA | O93: 1002 - CICL FACT DIRECTA CUCUTA NORTE | P93: ASEO INTEGRAL | Q93: RESIDENCIAL | R93: ESTRATO 3 | S93: NO AFORADO | T93: Ocupado | U93: 2026 | V93: 6 | W93: 1081875192 | X93: 1081893664 | Y93: 46182 | Z93: 46207 | AA93: 49934.3 | AB93: 49934.3 | AC93: -1650.7 | AD93: 0 | AE93: 0 | AF93: 0 | AG93: 0 | AH93: 0 | AI93: 0 | AJ93: 49934.3 | AK93: 49934.3 | AL93: 0 | AM93: 242.77 | AN93: 0 | AS93: =VLOOKUP(C93,'mayo-26'!B:AS,44,0) | AT93: =VLOOKUP(C93,'mayo-26'!B:AT,45,0) -> VERIFICADOR
A94: c505c18f8c0a6ce2a3099d4031173a0fa6dc1561edefbce651b64dd4ffaef70aa06c44a69fee98192326b645b6d892c7 | B94: 595138 | C94: 498519 | D94: 551624 | G94: 1254996 | H94: ALEJANDRINA ANTOLINEZ JAIMES | I94: =VLOOKUP(C94,'mayo-26'!B:H,7,0) -> CLL 14AN 4A-81 TORRE 1 APTO 304 | J94: PORTACHUELO | K94: =VLOOKUP(C94,'mayo-26'!B:J,9,0) -> CR PORTACHUELO | L94: =VLOOKUP(C94,'mayo-26'!B:K,10,0) -> CR PORTACHUELO | M94: CÚCUTA MPO | N94: CUCUTA DIRECTA | O94: 1002 - CICL FACT DIRECTA CUCUTA NORTE | P94: ASEO INTEGRAL | Q94: RESIDENCIAL | R94: ESTRATO 3 | S94: NO AFORADO | T94: Ocupado | U94: 2026 | V94: 6 | W94: 1081875196 | X94: 1081893668 | Y94: 46182 | Z94: 46207 | AA94: 50495.66 | AB94: 50495.66 | AC94: -1650.7 | AD94: 0 | AE94: 561.36 | AF94: 0 | AG94: 0 | AH94: 0 | AI94: 0 | AJ94: 50495.66 | AK94: 151248.59 | AL94: 3 | AM94: 242.77 | AN94: 0 | AS94: =VLOOKUP(C94,'mayo-26'!B:AS,44,0) | AT94: =VLOOKUP(C94,'mayo-26'!B:AT,45,0) -> VERIFICADOR
A95: e0d0c7b2ec18928cc5ab8db3bf46b6964314d20e934da2336af4e3380a39bf94fbe71938e6ecf9b4cf810022b6328025 | B95: 595142 | C95: 498523 | D95: 551628 | G95: 1255000 | H95: CARMEN JOHANNA OLARTE | I95: =VLOOKUP(C95,'mayo-26'!B:H,7,0) -> CLL 14AN 4A-81 TORRE 1 APTO 404 | J95: PORTACHUELO | K95: =VLOOKUP(C95,'mayo-26'!B:J,9,0) -> CR PORTACHUELO | L95: =VLOOKUP(C95,'mayo-26'!B:K,10,0) -> CR PORTACHUELO | M95: CÚCUTA MPO | N95: CUCUTA DIRECTA | O95: 1002 - CICL FACT DIRECTA CUCUTA NORTE | P95: ASEO INTEGRAL | Q95: RESIDENCIAL | R95: ESTRATO 3 | S95: NO AFORADO | T95: Ocupado | U95: 2026 | V95: 6 | W95: 1081875199 | X95: 1081893671 | Y95: 46182 | Z95: 46207 | AA95: 53994.58 | AB95: 53994.58 | AC95: -1650.7 | AD95: 0 | AE95: 4060.28 | AF95: 0 | AG95: 0 | AH95: 0 | AI95: 0 | AJ95: 53993.7 | AK95: 53993.7 | AL95: 0 | AM95: 242.77 | AN95: 0 | AQ95: 0.88 | AS95: =VLOOKUP(C95,'mayo-26'!B:AS,44,0) | AT95: =VLOOKUP(C95,'mayo-26'!B:AT,45,0) -> VERIFICADOR
A96: e5e210184ba99217620c1e834f1574d09e6486201eeb4853c46341025ed25ba3ec43c7f94e322ea420f763291a6700f2 | B96: 595146 | C96: 498527 | D96: 551632 | G96: 1255004 | H96: FERNANDO ENRIQUE MENDOZA LARA | I96: =VLOOKUP(C96,'mayo-26'!B:H,7,0) -> CLL 14AN 4A-81 TORRE 2 APTO 104 | J96: PORTACHUELO | K96: =VLOOKUP(C96,'mayo-26'!B:J,9,0) -> CR PORTACHUELO | L96: =VLOOKUP(C96,'mayo-26'!B:K,10,0) -> CR PORTACHUELO | M96: CÚCUTA MPO | N96: CUCUTA DIRECTA | O96: 1002 - CICL FACT DIRECTA CUCUTA NORTE | P96: ASEO INTEGRAL | Q96: RESIDENCIAL | R96: ESTRATO 3 | S96: NO AFORADO | T96: Ocupado | U96: 2026 | V96: 6 | W96: 1081875203 | X96: 1081893675 | Y96: 46182 | Z96: 46207 | AA96: 53994.58 | AB96: 53994.58 | AC96: -1650.7 | AD96: 0 | AE96: 4060.28 | AF96: 0 | AG96: 0 | AH96: 0 | AI96: 0 | AJ96: 53994.58 | AK96: 337498.7 | AL96: 6 | AM96: 242.77 | AN96: 0 | AS96: =VLOOKUP(C96,'mayo-26'!B:AS,44,0) | AT96: =VLOOKUP(C96,'mayo-26'!B:AT,45,0) -> VERIFICADOR
A97: 4a75411427a61ef89d9d808c4691628340558b5b2bcb800f15d0a31df0ba7b7bcf0ff6aa568b2c83aaf42f470275a253 | B97: 595150 | C97: 498531 | D97: 551636 | G97: 1255008 | H97: JOSE ANGARITA LAGUADO | I97: =VLOOKUP(C97,'mayo-26'!B:H,7,0) -> CLL 14AN 4A-81 TORRE 2 APTO 204 | J97: PORTACHUELO | K97: =VLOOKUP(C97,'mayo-26'!B:J,9,0) -> CR PORTACHUELO | L97: =VLOOKUP(C97,'mayo-26'!B:K,10,0) -> CR PORTACHUELO | M97: CÚCUTA MPO | N97: CUCUTA DIRECTA | O97: 1002 - CICL FACT DIRECTA CUCUTA NORTE | P97: ASEO INTEGRAL | Q97: RESIDENCIAL | R97: ESTRATO 3 | S97: NO AFORADO | T97: Ocupado | U97: 2026 | V97: 6 | W97: 1081875206 | X97: 1081893678 | Y97: 46182 | Z97: 46207 | AA97: 50494.66 | AB97: 50494.66 | AC97: -1650.7 | AD97: 0 | AE97: 560.36 | AF97: 0 | AG97: 0 | AH97: 0 | AI97: 0 | AJ97: 50494.66 | AK97: 151196.14 | AL97: 2 | AM97: 242.77 | AN97: 0 | AS97: =VLOOKUP(C97,'mayo-26'!B:AS,44,0) | AT97: =VLOOKUP(C97,'mayo-26'!B:AT,45,0) -> VERIFICADOR
A98: 552f5249de9455c71a12b070052a569e74c3de8c1719d10cb0d807af24ba5881f0f01772d7b63d8d0505b599d2f0b081 | B98: 595154 | C98: 498535 | D98: 551640 | G98: 1255012 | H98: GERSON JAVIER RINCON SANDOVAL | I98: =VLOOKUP(C98,'mayo-26'!B:H,7,0) -> CLL 14AN 4A-81 TORRE 2 APTO 304 | J98: PORTACHUELO | K98: =VLOOKUP(C98,'mayo-26'!B:J,9,0) -> CR PORTACHUELO | L98: =VLOOKUP(C98,'mayo-26'!B:K,10,0) -> CR PORTACHUELO | M98: CÚCUTA MPO | N98: CUCUTA DIRECTA | O98: 1002 - CICL FACT DIRECTA CUCUTA NORTE | P98: ASEO INTEGRAL | Q98: RESIDENCIAL | R98: ESTRATO 3 | S98: NO AFORADO | T98: Ocupado | U98: 2026 | V98: 6 | W98: 1081875208 | X98: 1081893680 | Y98: 46182 | Z98: 46207 | AA98: 53994.58 | AB98: 53994.58 | AC98: -1650.7 | AD98: 0 | AE98: 4060.28 | AF98: 0 | AG98: 0 | AH98: 0 | AI98: 0 | AJ98: 53994.58 | AK98: 337498.7 | AL98: 6 | AM98: 242.77 | AN98: 0 | AS98: =VLOOKUP(C98,'mayo-26'!B:AS,44,0) | AT98: =VLOOKUP(C98,'mayo-26'!B:AT,45,0) -> VERIFICADOR
A99: fe05f64e239f8f3a355147a84e368813606611563717cc4c28c0ad32d802cdb1a6448337d7e5aa47e6f122a66b910136 | B99: 595158 | C99: 498539 | D99: 551644 | G99: 1255016 | H99: ROCIO DEL PILAR BAUTISTA | I99: =VLOOKUP(C99,'mayo-26'!B:H,7,0) -> CLL 14AN 4A-81 TORRE 2 APTO 404 | J99: PORTACHUELO | K99: =VLOOKUP(C99,'mayo-26'!B:J,9,0) -> CR PORTACHUELO | L99: =VLOOKUP(C99,'mayo-26'!B:K,10,0) -> CR PORTACHUELO | M99: CÚCUTA MPO | N99: CUCUTA DIRECTA | O99: 1002 - CICL FACT DIRECTA CUCUTA NORTE | P99: ASEO INTEGRAL | Q99: RESIDENCIAL | R99: ESTRATO 3 | S99: NO AFORADO | T99: Ocupado | U99: 2026 | V99: 6 | W99: 1081875212 | X99: 1081893684 | Y99: 46182 | Z99: 46207 | AA99: 53994.58 | AB99: 53994.58 | AC99: -1650.7 | AD99: 0 | AE99: 4060.28 | AF99: 0 | AG99: 0 | AH99: 0 | AI99: 0 | AJ99: 53994.58 | AK99: 337498.7 | AL99: 6 | AM99: 242.77 | AN99: 0 | AS99: =VLOOKUP(C99,'mayo-26'!B:AS,44,0) | AT99: =VLOOKUP(C99,'mayo-26'!B:AT,45,0) -> VERIFICADOR
A100: 84b25ad80ca721255e79b3cbca0683bb8b82340367d0ccaa8038af42b9f30357332dc0188cf1bc4dee52f438fa8d18f5 | B100: 595162 | C100: 498543 | D100: 551648 | G100: 1255020 | H100: JOSE CLODOMIRO ANGARITA LAGUADO | I100: =VLOOKUP(C100,'mayo-26'!B:H,7,0) -> CLL 14AN 4A-81 TORRE 3 APTO 104 | J100: PORTACHUELO | K100: =VLOOKUP(C100,'mayo-26'!B:J,9,0) -> CR PORTACHUELO | L100: =VLOOKUP(C100,'mayo-26'!B:K,10,0) -> CR PORTACHUELO | M100: CÚCUTA MPO | N100: CUCUTA DIRECTA | O100: 1002 - CICL FACT DIRECTA CUCUTA NORTE | P100: ASEO INTEGRAL | Q100: RESIDENCIAL | R100: ESTRATO 3 | S100: NO AFORADO | T100: Ocupado | U100: 2026 | V100: 6 | W100: 1081875217 | X100: 1081893689 | Y100: 46182 | Z100: 46207 | AA100: 49934.3 | AB100: 49934.3 | AC100: -1650.7 | AD100: 0 | AE100: 0 | AF100: 0 | AG100: 0 | AH100: 0 | AI100: 0 | AJ100: 49934.3 | AK100: 49934.3 | AL100: 0 | AM100: 242.77 | AN100: 0 | AS100: =VLOOKUP(C100,'mayo-26'!B:AS,44,0) | AT100: =VLOOKUP(C100,'mayo-26'!B:AT,45,0) -> VERIFICADOR
...

Sheet mayo-26
A1: Cliente | B1: Cuenta | C1: Producto | D1: NIC | E1: NIS | F1: Identificación | G1: Nombres | H1: direccion | I1: barrio | J1: Planilla | K1: Grupo empresarial | L1: Nombre Municipio | M1: Cod. Localidad | N1: Ciclo de consumo | O1: Plan de facturación | P1: Categoría | Q1: Subcategoría | R1: Método de análisis | S1: Estado | T1: Año | U1: Mes(es) | V1: Factura | W1: Cuenta de cobro | X1: Generada el | Y1: Vence el | Z1: Total Cuenta | AA1: Monto facturado | AB1: Subsidio y/o Contribuciones | AC1: Consumo | AD1: VALOR INGRESOS INTERESES | AE1: Valor De Financiaciones | AF1: Cuota | AG1: Interes Financiacion | AH1: TOTAL IMPUESTO | AI1: Saldo pendiente | AJ1: Deuda Total | AK1: Cuentas Vencidas | AL1: Valor_Otros | AM1: Valor Nota | AN1: Valor Movimiento SA | AO1: Valor de pago | AP1: Valor Movimiento AS | AQ1: Fecha de Pago | AR1: Saldo a favor | AS1: CORREO | AT1: MEDIO DE ENVIO | AU1: responsable | AV1: FECHA
A2: 2743 | B2: 2742 | C2: 2742 | D2: 90255897 | E2: 90255897 | F2: 890506116-8 | G2: ALCALDIA PAMPLONITA | H2: #N/A | I2: PAMPLONITA | J2: DF | K2: DF | L2: CÚCUTA MPO | M2: CUCUTA ZONA SUR | N2: 1001 - CICL FACT PARQUE GUAYABAL( 63) | O2: DIS. FINAL Y TRATAMIENTO | P2: NO RESIDENCIAL - ASEO GP | Q2: OFICIAL | R2: AFORO PERMANENTE | S2: Ocupado | T2: 2026 | U2: 5 | V2: 1081522141 | W2: 1081540211 | X2: 08-05-2026 | Y2: 03-06-2026 | Z2: 173662.47 | AA2: 173662.47 | AB2: 0 | AC2: 3690 | AD2: 0 | AE2: 0 | AF2: 0 | AG2: 0 | AH2: 0 | AI2: 173662.47 | AJ2: 173662.47 | AK2: 0 | AL2: 50571.45 | AM2: 0 | AR2: 0 | AS2: serviciospublicos@pamplonita-nortedesantander.gov.co | AT2: CORREO ELECTRONICO CERTIFICADO 472 | AU2: ANGEL | AV2: 46171
A3: 2747 | B3: 2746 | C3: 2746 | D3: 90256627 | E3: 90256627 | F3: 800099237 | G3: EMPODURANIA | H3: AVENIDA 2 NO. 8-57 | I3: 0 | J3: NO | K3: DF | L3: CÚCUTA MPO | M3: CUCUTA ZONA SUR | N3: 1001 - CICL FACT PARQUE GUAYABAL( 63) | O3: DIS. FINAL Y TRATAMIENTO | P3: NO RESIDENCIAL - ASEO GP | Q3: INDUSTRIAL | R3: AFORO PERMANENTE | S3: Ocupado | T3: 2026 | U3: 5 | V3: 1081522145 | W3: 1081540215 | X3: 08-05-2026 | Y3: 03-06-2026 | Z3: 2077831.4 | AA3: 2077831.4 | AB3: 0 | AC3: 44150 | AD3: 0 | AE3: 0 | AF3: 0 | AG3: 0 | AH3: 0 | AI3: 2077831.4 | AJ3: 2077831.4 | AK3: 0 | AL3: 605075.75 | AM3: 0 | AR3: 0 | AS3: CONTACTENOS@DURANIA-NORTEDESANTANDER.GOV.CO | AT3: CORREO ELECTRONICO CERTIFICADO 472 | AU3: ANGEL | AV3: 46169
A4: 2751 | B4: 2750 | C4: 2750 | D4: 90257709 | E4: 90257709 | F4: 890501404 | G4: MUNICIPIO DE GRAMALOTE | H4: CARRERA 5 NO 7 ¿ 72 | I4: 0 | J4: NO | K4: DF | L4: CÚCUTA MPO | M4: CUCUTA ZONA SUR | N4: 1001 - CICL FACT PARQUE GUAYABAL( 63) | O4: DIS. FINAL Y TRATAMIENTO | P4: NO RESIDENCIAL - ASEO GP | Q4: OFICIAL | R4: AFORO PERMANENTE | S4: Ocupado | T4: 2026 | U4: 5 | V4: 1081522150 | W4: 1081540220 | X4: 08-05-2026 | Y4: 03-06-2026 | Z4: 2062771.3 | AA4: 2062771.3 | AB4: 0 | AC4: 43830 | AD4: 0 | AE4: 0 | AF4: 0 | AG4: 0 | AH4: 0 | AI4: 2062771.3 | AJ4: 2062771.3 | AK4: 0 | AL4: 600690.15 | AM4: 0 | AR4: 0 | AS4: TESORERIA@GRAMALOTE-NORTEDESANTANDER.GOV.CO | AT4: CORREO ELECTRONICO CERTIFICADO 472 | AU4: ANGEL | AV4: 46169
A5: 2755 | B5: 2754 | C5: 2754 | D5: 90257713 | E5: 90257713 | F5: 890502611 | G5: MUNICIPIO DE LOURDES | H5: CARRERA 4 CON CALLE 3 ¿ 36 | I5: 0 | J5: NO | K5: DF | L5: CÚCUTA MPO | M5: CUCUTA ZONA SUR | N5: 1001 - CICL FACT PARQUE GUAYABAL( 63) | O5: DIS. FINAL Y TRATAMIENTO | P5: NO RESIDENCIAL - ASEO GP | Q5: OFICIAL | R5: AFORO PERMANENTE | S5: Ocupado | T5: 2026 | U5: 5 | V5: 1081522154 | W5: 1081540224 | X5: 08-05-2026 | Y5: 03-06-2026 | Z5: 1650970 | AA5: 1650970 | AB5: 0 | AC5: 35080 | AD5: 0 | AE5: 0 | AF5: 0 | AG5: 0 | AH5: 0 | AI5: 1650970 | AJ5: 1650970 | AK5: 0 | AL5: 480771.4 | AM5: 0 | AR5: 0 | AS5: TESORERIA@LOURDES-NORTEDESANTANDER.GOV.CO | AT5: CORREO ELECTRONICO CERTIFICADO 472 | AU5: ANGEL | AV5: 46169
A6: 407715 | B6: 383058 | C6: 395995 | F6: 901196259-1 | G6: EXPLOTACIONES MINERAS DEL NORTE FC S.A.S. | H6: #N/A | I6: #N/A | J6: DF | K6: DF | L6: CÚCUTA MPO | M6: CUCUTA DIRECTA | N6: 1001 - CICL FACT PARQUE GUAYABAL( 63) | O6: DIS. FINAL Y TRATAMIENTO | P6: NO RESIDENCIAL - ASEO GP | Q6: INDUSTRIAL | R6: AFORO PERMANENTE | S6: Ocupado | T6: 2026 | U6: 5 | V6: 1081522164 | W6: 1081540234 | X6: 08-05-2026 | Y6: 03-06-2026 | Z6: 82843.8 | AA6: 82843.8 | AB6: 0 | AC6: 1950 | AD6: 0 | AE6: 0 | AF6: 0 | AG6: 0 | AH6: 0 | AI6: 82843.8 | AJ6: 82843.8 | AK6: 0 | AL6: 17795.7 | AM6: 0 | AR6: 0 | AS6: FACTURACIONEMNFC@HOTMAIL.COM | AT6: CORREO ELECTRONICO CERTIFICADO 472 | AU6: ANGEL | AV6: 46171
A7: 2744 | B7: 2743 | C7: 2743 | D7: 90256510 | E7: 90256510 | F7: 800099262 | G7: ALCALDIA MUNICIPIO DE SANTIAGO | H7: CARRERA 3 NO. 2-31 | I7: 0 | J7: NO | K7: DF | L7: CÚCUTA MPO | M7: CUCUTA ZONA SUR | N7: 1001 - CICL FACT PARQUE GUAYABAL( 63) | O7: DIS. FINAL Y TRATAMIENTO | P7: NO RESIDENCIAL - ASEO GP | Q7: OFICIAL | R7: AFORO PERMANENTE | S7: Ocupado | T7: 2026 | U7: 5 | V7: 1081522151 | W7: 1081540221 | X7: 08-05-2026 | Y7: 03-06-2026 | Z7: 1063623.8 | AA7: 1063623.8 | AB7: 0 | AC7: 22600 | AD7: 0 | AE7: 0 | AF7: 0 | AG7: 0 | AH7: 0 | AI7: 1063623.8 | AJ7: 2467983.7 | AK7: 1 | AL7: 309733 | AM7: 0 | AR7: 0 | AS7: TESORERIA@SANTIAGO-NORTEDESANTANDER.GOV.CO | AT7: CORREO ELECTRONICO CERTIFICADO 472 | AU7: ANGEL | AV7: 46169
A8: 2748 | B8: 2747 | C8: 2747 | D8: 90256652 | E8: 90256652 | F8: 890503483-2 | G8: ALCALDIA BUCARASICA | H8: CALLE 2 NO. 3-35 | I8: 0 | J8: NO | K8: DF | L8: CÚCUTA MPO | M8: CUCUTA ZONA SUR | N8: 1001 - CICL FACT PARQUE GUAYABAL( 63) | O8: DIS. FINAL Y TRATAMIENTO | P8: NO RESIDENCIAL - ASEO GP | Q8: OFICIAL | R8: AFORO PERMANENTE | S8: Ocupado | T8: 2026 | U8: 5 | V8: 1081522155 | W8: 1081540225 | X8: 08-05-2026 | Y8: 03-06-2026 | Z8: 973262.84 | AA8: 973262.84 | AB8: 0 | AC8: 20680 | AD8: 0 | AE8: 0 | AF8: 0 | AG8: 0 | AH8: 0 | AI8: 973262.84 | AJ8: 973262.84 | AK8: 0 | AL8: 283419.4 | AM8: 0 | AR8: 0 | AS8: HACIENDA@BUCARASICA-NORTEDESANTANDER.GOV.CO | AT8: CORREO ELECTRONICO CERTIFICADO 472 | AU8: ANGEL | AV8: 46170
A9: 2752 | B9: 2751 | C9: 2751 | D9: 90257710 | E9: 90257710 | F9: 890501876 | G9: MUNICIPIO DE SAN CAYETANO | H9: CARRERA 4 N 3 -61 | I9: 0 | J9: NO | K9: DF | L9: CÚCUTA MPO | M9: CUCUTA ZONA SUR | N9: 1001 - CICL FACT PARQUE GUAYABAL( 63) | O9: DIS. FINAL Y TRATAMIENTO | P9: NO RESIDENCIAL - ASEO GP | Q9: OFICIAL | R9: AFORO PERMANENTE | S9: Ocupado | T9: 2026 | U9: 5 | V9: 1081522159 | W9: 1081540229 | X9: 08-05-2026 | Y9: 03-06-2026 | Z9: 5359534.4 | AA9: 5359534.4 | AB9: 0 | AC9: 113880 | AD9: 0 | AE9: 0 | AF9: 0 | AG9: 0 | AH9: 0 | AI9: 5359534.4 | AJ9: 5359534.4 | AK9: 0 | AL9: 1560725.4 | AM9: 0 | AR9: 0 | AS9: tesoreria@sancayetano-nortedesantander.gov.co | AT9: CORREO ELECTRONICO CERTIFICADO 472 | AU9: ANGEL | AV9: 46170
A10: 2760 | B10: 2759 | C10: 2759 | D10: 90290491 | E10: 90290491 | F10: 901238264-9 | G10: ADM PUB SERV PUBL DOMICILIA ACU ALC ASEO | H10: CRA 5 6-03 BARR PERPETUO SOCORRO | I10: HERRAN | J10: DF | K10: DF | L10: CÚCUTA MPO | M10: CUCUTA ZONA SUR | N10: 1001 - CICL FACT PARQUE GUAYABAL( 63) | O10: DIS. FINAL Y TRATAMIENTO | P10: NO RESIDENCIAL - ASEO GP | Q10: INDUSTRIAL | R10: AFORO PERMANENTE | S10: Ocupado | T10: 2026 | U10: 5 | V10: 1081522162 | W10: 1081540232 | X10: 08-05-2026 | Y10: 03-06-2026 | Z10: 693708.62 | AA10: 693708.62 | AB10: 0 | AC10: 14740 | AD10: 0 | AE10: 0 | AF10: 0 | AG10: 0 | AH10: 0 | AI10: 693708.62 | AJ10: 1276819.2 | AK10: 1 | AL10: 202011.7 | AM10: 0 | AR10: 0 | AS10: APCMANOBAHERRAN@GMAIL.COM | AT10: CORREO ELECTRONICO CERTIFICADO 472 | AU10: ANGEL | AV10: 46171
A11: 369348 | B11: 362075 | C11: 365048 | F11: 901085013 | G11: IBEROAMERICANA DE HIDROCARBUROS ENERGY COLOMBIA S.A.S | H11: #N/A | I11: #N/A | J11: DF | K11: DF | L11: CÚCUTA MPO | M11: CUCUTA DIRECTA | N11: 1001 - CICL FACT PARQUE GUAYABAL( 63) | O11: DIS. FINAL Y TRATAMIENTO | P11: NO RESIDENCIAL - ASEO GP | Q11: INDUSTRIAL | R11: AFORO PERMANENTE | S11: Ocupado | T11: 2026 | U11: 5 | V11: 1081522165 | W11: 1081540235 | X11: 08-05-2026 | Y11: 03-06-2026 | Z11: 21666.84 | AA11: 21666.84 | AB11: 0 | AC11: 510 | AD11: 0 | AE11: 0 | AF11: 0 | AG11: 0 | AH11: 0 | AI11: 21666.84 | AJ11: 21666.84 | AK11: 0 | AL11: 4654.26 | AM11: 0 | AR11: 0 | AS11: FROJAS@IHSAENERGY.CO | AT11: CORREO ELECTRONICO CERTIFICADO 472 | AU11: ANGEL | AV11: 46171
A12: 584 | B12: 583 | C12: 583 | D12: 90275668 | E12: 90275668 | F12: 807005252-1 | G12: ECOAMBIENTAL DEL NORTE SAS ESP | H12: CARRERA 7 NO. 3-17 VILLA DEL ROSARIO | I12: SIN DETERMINAR | J12: DF | K12: DF | L12: CÚCUTA MPO | M12: CUCUTA ZONA SUR | N12: 1001 - CICL FACT PARQUE GUAYABAL( 63) | O12: DIS. FINAL Y TRATAMIENTO | P12: NO RESIDENCIAL - ASEO GP | Q12: INDUSTRIAL | R12: AFORO PERMANENTE | S12: Ocupado | T12: 2026 | U12: 5 | V12: 1081522140 | W12: 1081540210 | X12: 08-05-2026 | Y12: 03-06-2026 | Z12: 10810600 | AA12: 10810600 | AB12: 0 | AC12: 227270 | AD12: 114592.31 | AE12: 0 | AF12: 0 | AG12: 0 | AH12: 0 | AI12: 10810600 | AJ12: 22153268 | AK12: 2 | AL12: 3114735.4 | AM12: 0 | AR12: 0 | AS12: ecoambiental807@gmail.com | AT12: CORREO ELECTRONICO CERTIFICADO 472 | AU12: ANGEL | AV12: 46171
A13: 2742 | B13: 2741 | C13: 2741 | D13: 90254686 | E13: 90254686 | F13: 807000581-5 | G13: EMPRESAS PUBLICAS MUNICIPALES DE CHINACOTA EMCHINAC | H13: CRA 4A 13-35 BARRIO LAS COLINAS/CHINACOTA | I13: 0 | J13: NO | K13: DF | L13: CÚCUTA MPO | M13: CUCUTA ZONA SUR | N13: 1001 - CICL FACT PARQUE GUAYABAL( 63) | O13: DIS. FINAL Y TRATAMIENTO | P13: NO RESIDENCIAL - ASEO GP | Q13: INDUSTRIAL | R13: AFORO PERMANENTE | S13: Ocupado | T13: 2026 | U13: 5 | V13: 1081522139 | W13: 1081540209 | X13: 08-05-2026 | Y13: 03-06-2026 | Z13: 13292790 | AA13: 13292790 | AB13: 0 | AC13: 281990 | AD13: 21494.15 | AE13: 0 | AF13: 0 | AG13: 0 | AH13: 0 | AI13: 13292790 | AJ13: 13292790 | AK13: 0 | AL13: 3864673 | AM13: 0 | AR13: 0 | AS13: EMCHINAC@EMCHINACESP-CHINACOTA.GOV.CO | AT13: CORREO ELECTRONICO CERTIFICADO 472 | AU13: ANGEL | AV13: 46170
A14: 2746 | B14: 2745 | C14: 2745 | D14: 90256586 | E14: 90256586 | F14: 800099251 | G14: ALCALDIA MUNICIPIO RAGONVALIA | H14: CALLE 6 NO. 2-32 | I14: 0 | J14: NO | K14: DF | L14: CÚCUTA MPO | M14: CUCUTA ZONA SUR | N14: 1001 - CICL FACT PARQUE GUAYABAL( 63) | O14: DIS. FINAL Y TRATAMIENTO | P14: NO RESIDENCIAL - ASEO GP | Q14: OFICIAL | R14: AFORO PERMANENTE | S14: Ocupado | T14: 2026 | U14: 5 | V14: 1081522143 | W14: 1081540213 | X14: 08-05-2026 | Y14: 03-06-2026 | Z14: 1375180.9 | AA14: 1375180.9 | AB14: 0 | AC14: 29220 | AD14: 0 | AE14: 0 | AF14: 0 | AG14: 0 | AH14: 0 | AI14: 1375180.9 | AJ14: 3283114.9 | AK14: 1 | AL14: 400460.1 | AM14: 0 | AR14: 0 | AS14: HACIENDA@RAGONVALIA-NORTEDESANTANDER.GOV.CO | AT14: CORREO ELECTRONICO CERTIFICADO 472 | AU14: ANGEL | AV14: 46170
A15: 2750 | B15: 2749 | C15: 2749 | D15: 90257708 | E15: 90257708 | F15: 890501981 | G15: MUNICIPIO DE VILLA CARO | H15: PALACIO MPAL VILLA CARO | I15: 0 | J15: NO | K15: DF | L15: CÚCUTA MPO | M15: CUCUTA ZONA SUR | N15: 1001 - CICL FACT PARQUE GUAYABAL( 63) | O15: DIS. FINAL Y TRATAMIENTO | P15: NO RESIDENCIAL - ASEO GP | Q15: OFICIAL | R15: AFORO PERMANENTE | S15: Ocupado | T15: 2026 | U15: 5 | V15: 1081522149 | W15: 1081540219 | X15: 08-05-2026 | Y15: 03-06-2026 | Z15: 804306.67 | AA15: 804306.67 | AB15: 0 | AC15: 17090 | AD15: 0 | AE15: 0 | AF15: 0 | AG15: 0 | AH15: 0 | AI15: 804306.67 | AJ15: 804306.67 | AK15: 0 | AL15: 234218.45 | AM15: 0 | AR15: 0 | AS15: tesoreria@villacaro-nortedesantander.gov.co | AT15: CORREO ELECTRONICO CERTIFICADO 472 | AU15: ANGEL | AV15: 46170
A16: 2758 | B16: 2757 | C16: 2757 | D16: 90267356 | E16: 90267356 | F16: 890501436-7 | G16: ALCALDIA MUNICIPIO DE ARBOLEDAS | H16: CRA 6 CALLE 2 Y 3 NO 6-25 | I16: 0 | J16: NO | K16: DF | L16: CÚCUTA MPO | M16: CUCUTA ZONA SUR | N16: 1001 - CICL FACT PARQUE GUAYABAL( 63) | O16: DIS. FINAL Y TRATAMIENTO | P16: NO RESIDENCIAL - ASEO GP | Q16: OFICIAL | R16: AFORO PERMANENTE | S16: Ocupado | T16: 2026 | U16: 5 | V16: 1081522153 | W16: 1081540223 | X16: 08-05-2026 | Y16: 03-06-2026 | Z16: 2025120.9 | AA16: 2025120.9 | AB16: 0 | AC16: 43030 | AD16: 0 | AE16: 0 | AF16: 0 | AG16: 0 | AH16: 0 | AI16: 2025120.9 | AJ16: 2025121.8 | AK16: 1 | AL16: 589726.15 | AM16: 0 | AR16: 0 | AS16: tesoreria@arboledas-nortedesantander.gov.co | AT16: CORREO ELECTRONICO CERTIFICADO 472 | AU16: ANGEL | AV16: 46170
A17: 608069 | B17: 502777 | C17: 558548 | F17: 900508526 | G17: EMPRESA DE SOLUCIONES AMBIENTALES PARA COLOMBIA S.A.S E.S.P | H17: KM 7 VDA EL CUCHARO | I17: #N/A | J17: DF | K17: DF | L17: CÚCUTA MPO | M17: CUCUTA DIRECTA | N17: 1001 - CICL FACT PARQUE GUAYABAL( 63) | O17: DIS. FINAL Y TRATAMIENTO | P17: NO RESIDENCIAL - ASEO GP | Q17: COMERCIAL | R17: NO AFORADO | S17: Ocupado | T17: 2026 | U17: 5 | V17: 1081523254 | W17: 1081541324 | X17: 08-05-2026 | Y17: 03-06-2026 | Z17: 2144661 | AA17: 2144661 | AB17: 0 | AC17: 0 | AD17: 0 | AE17: 0 | AF17: 0 | AG17: 0 | AH17: 0 | AI17: 2144661 | AJ17: 2144661 | AK17: 0 | AL17: 624537 | AM17: 0 | AR17: 0 | AS17: empsacol@hotmail.com | AT17: CORREO ELECTRONICO CERTIFICADO 472 | AU17: ANGEL | AV17: 46171
A18: 2293 | B18: 2292 | C18: 2292 | D18: 90265701 | E18: 90265701 | F18: 890501301-1 | G18: SOCIEDAD MEJORAS PUBLICAS DE CUCUTA | H18: CALLE 4AN # 4-89 PESCADERO | I18: PESCADERO | J18: NO | K18: DF | L18: CÚCUTA MPO | M18: CUCUTA DIRECTA | N18: 1001 - CICL FACT PARQUE GUAYABAL( 63) | O18: DIS. FINAL Y TRATAMIENTO | P18: NO RESIDENCIAL - ASEO GP | Q18: INDUSTRIAL | R18: AFORO PERMANENTE | S18: Ocupado | T18: 2026 | U18: 5 | V18: 1081522144 | W18: 1081540214 | X18: 08-05-2026 | Y18: 03-06-2026 | Z18: 4131569 | AA18: 4131569 | AB18: 0 | AC18: 97250 | AD18: 0 | AE18: 0 | AF18: 0 | AG18: 0 | AH18: 0 | AI18: 4131569 | AJ18: 4131569 | AK18: 0 | AL18: 887503.5 | AM18: 0 | AR18: 0 | AS18: contacto@smpcucuta.com | AT18: CORREO ELECTRONICO CERTIFICADO 472 | AU18: ANGEL | AV18: 46170
A19: 2741 | B19: 2740 | C19: 2740 | D19: 90253728 | E19: 90253728 | F19: 800250853-1 | G19: ALCALDIA MUNICIPAL PUERTO SANT | H19: CARERA 2 NO. 2-35 | I19: 0 | J19: NO | K19: DF | L19: CÚCUTA MPO | M19: CUCUTA ZONA SUR | N19: 1001 - CICL FACT PARQUE GUAYABAL( 63) | O19: DIS. FINAL Y TRATAMIENTO | P19: NO RESIDENCIAL - ASEO GP | Q19: OFICIAL | R19: AFORO PERMANENTE | S19: Ocupado | T19: 2026 | U19: 5 | V19: 1081522147 | W19: 1081540217 | X19: 08-05-2026 | Y19: 03-06-2026 | Z19: 4748186.1 | AA19: 4748186.1 | AB19: 0 | AC19: 100890 | AD19: 0 | AE19: 0 | AF19: 0 | AG19: 0 | AH19: 0 | AI19: 4748186.1 | AJ19: 4748186.1 | AK19: 0 | AL19: 1382697.4 | AM19: 0 | AR19: 0 | AS19: TESORERIA@PUERTOSANTANDER-NORTEDESANTANDER.GOV.CO | AT19: CORREO ELECTRONICO CERTIFICADO 472 | AU19: ANGEL | AV19: 46170
A20: 2745 | B20: 2744 | C20: 2744 | D20: 90256525 | E20: 90256525 | F20: 800099263-8 | G20: MUNICIPIO DE SARDINATA | H20: CALLE 6 NO. 6 55 CENTRO SARDINATA | I20: 0 | J20: NO | K20: DF | L20: CÚCUTA MPO | M20: CUCUTA ZONA SUR | N20: 1001 - CICL FACT PARQUE GUAYABAL( 63) | O20: DIS. FINAL Y TRATAMIENTO | P20: NO RESIDENCIAL - ASEO GP | Q20: OFICIAL | R20: AFORO PERMANENTE | S20: Ocupado | T20: 2026 | U20: 5 | V20: 1081522152 | W20: 1081540222 | X20: 08-05-2026 | Y20: 03-06-2026 | Z20: 10621178 | AA20: 10621178 | AB20: 0 | AC20: 225680 | AD20: 0 | AE20: 0 | AF20: 0 | AG20: 0 | AH20: 0 | AI20: 10621178 | AJ20: 32110854 | AK20: 2 | AL20: 3092944.4 | AM20: 0 | AR20: 0 | AT20: CORREO ELECTRONICO CERTIFICADO 472 | AU20: ANGEL | AV20: 46170
A21: 2749 | B21: 2748 | C21: 2748 | D21: 90257658 | E21: 90257658 | F21: 890501549 | G21: MPIO DE SALAZAR DE LAS PALMAS | H21: CALLE 2 CARRERA 6 ESQUINA | I21: 0 | J21: NO | K21: DF | L21: CÚCUTA MPO | M21: CUCUTA ZONA SUR | N21: 1001 - CICL FACT PARQUE GUAYABAL( 63) | O21: DIS. FINAL Y TRATAMIENTO | P21: NO RESIDENCIAL - ASEO GP | Q21: INDUSTRIAL | R21: AFORO PERMANENTE | S21: Ocupado | T21: 2026 | U21: 5 | V21: 1081522156 | W21: 1081540226 | X21: 08-05-2026 | Y21: 03-06-2026 | Z21: 3614909 | AA21: 3614909 | AB21: 0 | AC21: 76810 | AD21: 0 | AE21: 0 | AF21: 0 | AG21: 0 | AH21: 0 | AI21: 370867.61 | AJ21: 370867.61 | AK21: 0 | AL21: 1052681.1 | AM21: 0 | AP21: 3244041.4 | AR21: 0 | AS21: HACIENDA@SALAZARDELASPALMAS-NORTEDESANTANDER.GOV.CO | AT21: CORREO ELECTRONICO CERTIFICADO 472 | AU21: ANGEL | AV21: 46170
A22: 2753 | B22: 2752 | C22: 2752 | D22: 90257711 | E22: 90257711 | F22: 807002043 | G22: EMZULIA E.S.P | H22: CLL 7 NO 2-03 BARRIO CENTRO MUNICIPIO EL ZULIA | I22: 0 | J22: NO | K22: DF | L22: CÚCUTA MPO | M22: CUCUTA ZONA SUR | N22: 1001 - CICL FACT PARQUE GUAYABAL( 63) | O22: DIS. FINAL Y TRATAMIENTO | P22: NO RESIDENCIAL - ASEO GP | Q22: INDUSTRIAL | R22: AFORO PERMANENTE | S22: Ocupado | T22: 2026 | U22: 5 | V22: 1081522160 | W22: 1081540230 | X22: 08-05-2026 | Y22: 03-06-2026 | Z22: 21318598 | AA22: 21318598 | AB22: 0 | AC22: 452980 | AD22: 0 | AE22: 0 | AF22: 0 | AG22: 0 | AH22: 0 | AI22: 21318598 | AJ22: 21318598 | AK22: 0 | AL22: 6208090.9 | AM22: 0 | AR22: 0 | AS22: emzulia.esp@gmail.com | AT22: CORREO ELECTRONICO CERTIFICADO 472 | AU22: ANGEL | AV22: 46170
A23: 2757 | B23: 2756 | C23: 2756 | D23: 90257826 | E23: 90257826 | F23: 890505662 | G23: MUNICIPIO DE BOCHALEMA | H23: CALLE 3 NO 3 - 08 | I23: 0 | J23: NO | K23: DF | L23: CÚCUTA MPO | M23: CUCUTA ZONA SUR | N23: 1001 - CICL FACT PARQUE GUAYABAL( 63) | O23: DIS. FINAL Y TRATAMIENTO | P23: NO RESIDENCIAL - ASEO GP | Q23: OFICIAL | R23: AFORO PERMANENTE | S23: Ocupado | T23: 2026 | U23: 5 | V23: 1081522163 | W23: 1081540233 | X23: 08-05-2026 | Y23: 03-06-2026 | Z23: 4599467 | AA23: 4599467 | AB23: 0 | AC23: 97730 | AD23: 0 | AE23: 0 | AF23: 0 | AG23: 0 | AH23: 0 | AI23: 4599467 | AJ23: 4599467.3 | AK23: 1 | AL23: 1339389.6 | AM23: 0 | AR23: 0 | AS23: UNISEPUBLICOS@BOCHALEMA-NORTEDESANTANDER.GOV.CO | AT23: CORREO ELECTRONICO CERTIFICADO 472 | AU23: ANGEL | AV23: 46170
A24: 433 | B24: 432 | C24: 432 | D24: 90253757 | E24: 90253757 | F24: 901347799 | G24: CURTIEMBRES CUCUTA SAS NIT.901.347.799-4 | H24: KM 6 #49-40 VIA SAUFASTINO EL SERRITO | I24: SIN DETERMINAR | J24: NO | K24: DF | L24: CÚCUTA MPO | M24: CUCUTA ZONA SUR | N24: 1001 - CICL FACT PARQUE GUAYABAL( 63) | O24: DIS. FINAL Y TRATAMIENTO | P24: NO RESIDENCIAL - ASEO GP | Q24: INDUSTRIAL | R24: AFORO PERMANENTE | S24: Ocupado | T24: 2026 | U24: 5 | V24: 1081522135 | W24: 1081540205 | X24: 08-05-2026 | Y24: 03-06-2026 | Z24: 849255.16 | AA24: 849255.16 | AB24: 0 | AC24: 19990 | AD24: 0 | AE24: 0 | AF24: 0 | AG24: 0 | AH24: 0 | AI24: 849255.16 | AJ24: 849255.16 | AK24: 0 | AL24: 182428.74 | AM24: 0 | AR24: 0 | AS24: CURTIEMBRESCUCUTA@GMAIL.COM | AT24: CORREO ELECTRONICO CERTIFICADO 472 | AU24: ANGEL | AV24: 46170
A25: 505 | B25: 504 | C25: 504 | D25: 90268059 | E25: 90268059 | F25: 60366490 | G25: NATALIA ANDREA ROJAS | H25: CLL 21 0E- 20 CAOBOS | I25: BARRIO BLANCO | J25: NO | K25: DF | L25: CÚCUTA MPO | M25: CUCUTA DIRECTA | N25: 1001 - CICL FACT PARQUE GUAYABAL( 63) | O25: DIS. FINAL Y TRATAMIENTO | P25: NO RESIDENCIAL - ASEO GP | Q25: INDUSTRIAL | R25: AFORO PERMANENTE | S25: Ocupado | T25: 2026 | U25: 5 | V25: 1081522138 | W25: 1081540208 | X25: 08-05-2026 | Y25: 03-06-2026 | Z25: 799606.96 | AA25: 799606.96 | AB25: 0 | AC25: 17780 | AD25: 44241.44 | AE25: 0 | AF25: 0 | AG25: 0 | AH25: 0 | AI25: 799606.96 | AJ25: 3608549.1 | AK25: 4 | AL25: 162260.28 | AM25: 0 | AR25: 0 | AS25: NAROHE10@HOTMAIL.COM | AT25: CORREO ELECTRONICO CERTIFICADO 472 | AU25: ANGEL | AV25: 46171
A26: 125141 | B26: 125140 | C26: 125140 | D26: 590301 | E26: 590301 | F26: 890104633-9 | G26: UNIVERSIDAD SIMON BOLIVAR-OTROS | H26: AVE 3 # 13-82 | I26: LA PLAYA | J26: NO | K26: NO | L26: CÚCUTA MPO | M26: CUCUTA DIRECTA | N26: 1002 - CICL FACT DIRECTA CUCUTA NORTE | O26: ASEO INTEGRAL | P26: NO RESIDENCIAL - ASEO PP | Q26: COMERCIAL RANGO 3 | R26: NO AFORADO | S26: Ocupado | T26: 2026 | U26: 5 | V26: 1081522458 | W26: 1081540528 | X26: 08-05-2026 | Y26: 03-06-2026 | Z26: 114427.12 | AA26: 114427.12 | AB26: 37970.5 | AC26: 0 | AD26: 515.62 | AE26: 0 | AF26: 0 | AG26: 0 | AH26: 0 | AI26: 114427.12 | AJ26: 114427.12 | AK26: 0 | AL26: 376.2 | AM26: 0 | AR26: 0 | AS26: facturaelectronicacucuta@unisimon.edu.co; 890104633_201@FACTURENINBOX.CO | AT26: CORREO ELECTRONICO CERTIFICADO 472 | AU26: Liliana | AV26: 46167
A27: 699 | B27: 210448 | C27: 210448 | D27: 32901 | E27: 32901 | F27: 900480569 | G27: JERONIMO MARTINS COLOMBIA SAS | H27: CLL 12 4-52 CENTRO | I27: MOTILONES | J27: NO | K27: ARA CUCUTA | L27: CÚCUTA MPO | M27: CUCUTA ZONA NORTE | N27: 1002 - CICL FACT DIRECTA CUCUTA NORTE | O27: ASEO INTEGRAL | P27: NO RESIDENCIAL - ASEO GP | Q27: COMERCIAL | R27: AFORO ORDINARIO-EXTRAORDINARIO | S27: Ocupado | T27: 2026 | U27: 5 | V27: 1081522462 | W27: 1081540532 | X27: 08-05-2026 | Y27: 03-06-2026 | Z27: 572010.44 | AA27: 572010.44 | AB27: 190670.15 | AC27: 1808 | AD27: 0 | AE27: 0 | AF27: 0 | AG27: 0 | AH27: 0 | AI27: 572010.44 | AJ27: 572010.44 | AK27: 0 | AL27: 376.2 | AM27: 0 | AR27: 0 | AS27: COORDINADOR.OPERACIONES.R11@JERONIMO-MARTINS.COM | AT27: CORREO ELECTRONICO CERTIFICADO 472 | AU27: ANGEL | AV27: 46163
A28: 699 | B28: 217824 | C28: 217824 | D28: 40634 | E28: 40634 | F28: 900480569 | G28: JERONIMO MARTINS COLOMBIA SAS | H28: CLL 12 4-52 CENTRO | I28: ATALAYA I ETAPA | J28: NO | K28: ARA CUCUTA | L28: CÚCUTA MPO | M28: CUCUTA ZONA NORTE | N28: 1002 - CICL FACT DIRECTA CUCUTA NORTE | O28: ASEO INTEGRAL | P28: NO RESIDENCIAL - ASEO GP | Q28: COMERCIAL | R28: AFORO ORDINARIO-EXTRAORDINARIO | S28: Ocupado | T28: 2026 | U28: 5 | V28: 1081522465 | W28: 1081540535 | X28: 08-05-2026 | Y28: 03-06-2026 | Z28: 391215.46 | AA28: 391215.46 | AB28: 130405.16 | AC28: 1173 | AD28: 0 | AE28: 0 | AF28: 0 | AG28: 0 | AH28: 0 | AI28: 391215.46 | AJ28: 391215.46 | AK28: 0 | AL28: 376.2 | AM28: 0 | AR28: 0 | AS28: COORDINADOR.OPERACIONES.R11@JERONIMO-MARTINS.COM | AT28: CORREO ELECTRONICO CERTIFICADO 472 | AU28: ANGEL | AV28: 46163
A29: 297 | B29: 221700 | C29: 221700 | D29: 44643 | E29: 44643 | F29: 807004352-3 | G29: EMPRESA SOCIAL DEL ESTADO E.S.E IMSALUD | H29: AVE 4 17-89 - 0239431 | I29: CLARET | J29: NO | K29: IMSALUD | L29: CÚCUTA MPO | M29: CUCUTA ZONA NORTE | N29: 1002 - CICL FACT DIRECTA CUCUTA NORTE | O29: ASEO INTEGRAL | P29: NO RESIDENCIAL - ASEO PP | Q29: OFICIAL RANGO 3 | R29: NO AFORADO | S29: Ocupado | T29: 2026 | U29: 5 | V29: 1081522469 | W29: 1081540539 | X29: 08-05-2026 | Y29: 03-06-2026 | Z29: 75941 | AA29: 75941 | AB29: 0 | AC29: 0 | AD29: 0 | AE29: 0 | AF29: 0 | AG29: 0 | AH29: 0 | AI29: 75941 | AJ29: 75941 | AK29: 0 | AL29: 250.8 | AM29: 0 | AR29: 0 | AS29: SUBFINANCIERA@IMSALUD.GOV.CO | AT29: CORREO ELECTRONICO CERTIFICADO 472 | AU29: ANGEL | AV29: 46164
A30: 280920 | B30: 223224 | C30: 223224 | D30: 46259 | E30: 46259 | F30: 900576569 | G30: SUPERMERCADO BETEL PLUSS | H30: AVE 12 5AN-84 1142 | I30: ANTONIA SANTOS | J30: NO | K30: BETEL | L30: CÚCUTA MPO | M30: CUCUTA DIRECTA | N30: 1002 - CICL FACT DIRECTA CUCUTA NORTE | O30: ASEO INTEGRAL | P30: NO RESIDENCIAL - ASEO PP | Q30: COMERCIAL RANGO 3 | R30: NO AFORADO | S30: Ocupado | T30: 2026 | U30: 5 | V30: 1081522474 | W30: 1081540544 | X30: 08-05-2026 | Y30: 03-06-2026 | Z30: 124715.52 | AA30: 124715.52 | AB30: 37970.5 | AC30: 0 | AD30: 10804.02 | AE30: 0 | AF30: 0 | AG30: 0 | AH30: 0 | AI30: 124715.52 | AJ30: 766477.09 | AK30: 7 | AL30: 376.2 | AM30: 0 | AR30: 0 | AS30: COORDTESORERIASUPERBETEL@GMAIL.COM | AT30: CORREO ELECTRONICO CERTIFICADO 472 | AU30: ANGEL | AV30: 46163
A31: 228357 | B31: 228356 | C31: 228356 | D31: 154946 | E31: 154946 | F31: 899999034-1 | G31: SENA | H31: AVE 5 2N-80 1077 | I31: PESCADERO | J31: NO | K31: NO | L31: CÚCUTA MPO | M31: CUCUTA DIRECTA | N31: 1002 - CICL FACT DIRECTA CUCUTA NORTE | O31: ASEO INTEGRAL | P31: NO RESIDENCIAL - ASEO GP | Q31: OFICIAL | R31: AFORO PERMANENTE | S31: Ocupado | T31: 2026 | U31: 5 | V31: 1081522477 | W31: 1081540547 | X31: 08-05-2026 | Y31: 03-06-2026 | Z31: 3916261.3 | AA31: 3916261.3 | AB31: 0 | AC31: 14025 | AD31: 0 | AE31: 0 | AF31: 0 | AG31: 0 | AH31: 0 | AI31: 3916261.3 | AJ31: 15780078 | AK31: 4 | AL31: 1216250.8 | AM31: 0 | AR31: 0 | AS31: jayalar@sena.edu.co | AT31: CORREO ELECTRONICO CERTIFICADO 472 | AU31: Liliana | AV31: 46167
A32: 297 | B32: 231632 | C32: 231632 | D32: 206717 | E32: 206717 | F32: 807004352-3 | G32: EMPRESA SOCIAL DEL ESTADO E.S.E IMSALUD | H32: AVE 4 17-89 - 0239431 | I32: ANTONIA SANTOS | J32: NO | K32: IMSALUD | L32: CÚCUTA MPO | M32: CUCUTA ZONA NORTE | N32: 1002 - CICL FACT DIRECTA CUCUTA NORTE | O32: ASEO INTEGRAL | P32: NO RESIDENCIAL - ASEO GP | Q32: OFICIAL | R32: AFORO ORDINARIO-EXTRAORDINARIO | S32: Ocupado | T32: 2026 | U32: 5 | V32: 1081522482 | W32: 1081540552 | X32: 08-05-2026 | Y32: 03-06-2026 | Z32: 104595.85 | AA32: 104595.85 | AB32: 0 | AC32: 350 | AD32: 0 | AE32: 0 | AF32: 0 | AG32: 0 | AH32: 0 | AI32: 104595.85 | AJ32: 104595.85 | AK32: 0 | AL32: 250.8 | AM32: 0 | AR32: 0 | AS32: SUBFINANCIERA@IMSALUD.GOV.CO | AT32: CORREO ELECTRONICO CERTIFICADO 472 | AU32: ANGEL | AV32: 46164
A33: 297 | B33: 232416 | C33: 232416 | D33: 215210 | E33: 215210 | F33: 807004352-3 | G33: EMPRESA SOCIAL DEL ESTADO E.S.E IMSALUD | H33: AVE 4 17-89 - 0239431 | I33: LA HERMITA | J33: NO | K33: IMSALUD | L33: CÚCUTA MPO | M33: CUCUTA ZONA NORTE | N33: 1002 - CICL FACT DIRECTA CUCUTA NORTE | O33: ASEO INTEGRAL | P33: NO RESIDENCIAL - ASEO GP | Q33: OFICIAL | R33: AFORO ORDINARIO-EXTRAORDINARIO | S33: Ocupado | T33: 2026 | U33: 5 | V33: 1081522485 | W33: 1081540555 | X33: 08-05-2026 | Y33: 03-06-2026 | Z33: 106493.96 | AA33: 106493.96 | AB33: 0 | AC33: 360 | AD33: 0 | AE33: 0 | AF33: 0 | AG33: 0 | AH33: 0 | AI33: 106493.96 | AJ33: 106493.96 | AK33: 0 | AL33: 250.8 | AM33: 0 | AR33: 0 | AS33: SUBFINANCIERA@IMSALUD.GOV.CO | AT33: CORREO ELECTRONICO CERTIFICADO 472 | AU33: ANGEL | AV33: 46164
A34: 141 | B34: 238452 | C34: 238452 | D34: 313539 | E34: 313539 | F34: 890500514 | G34: CENTRALES ELECTRICAS DEL NORTE DE SANTANDER S.A. EMPRESA DE SERVICIOS PUBLICOS | H34: AV 2 CALLE 39 LIBERTAD | I34: BELEN | J34: NO | K34: CENS | L34: CÚCUTA MPO | M34: CUCUTA ZONA NORTE | N34: 1002 - CICL FACT DIRECTA CUCUTA NORTE | O34: ASEO INTEGRAL | P34: NO RESIDENCIAL - ASEO GP | Q34: COMERCIAL | R34: AFORO ORDINARIO-EXTRAORDINARIO | S34: Ocupado | T34: 2026 | U34: 5 | V34: 1081522489 | W34: 1081540559 | X34: 08-05-2026 | Y34: 03-06-2026 | Z34: 227503.48 | AA34: 227503.48 | AB34: 75834.5 | AC34: 598 | AD34: 0 | AE34: 0 | AF34: 0 | AG34: 0 | AH34: 0 | AI34: 227503.48 | AJ34: 227503.48 | AK34: 0 | AL34: 376.2 | AM34: 0 | AR34: 0 | AS34: FACTURAELECTRONICACENS@GRUPO-EPM.COM | AT34: CORREO ELECTRONICO CERTIFICADO 472 | AU34: ANGEL | AV34: 46163
A35: 699 | B35: 24176 | C35: 24176 | D35: 207240 | E35: 207240 | F35: 900480569 | G35: JERONIMO MARTINS COLOMBIA SAS | H35: CLL 12 4-52 CENTRO | I35: VALLE ESTHER | J35: NO | K35: ARA CUCUTA | L35: CÚCUTA MPO | M35: CUCUTA ZONA SUR | N35: 1002 - CICL FACT DIRECTA CUCUTA NORTE | O35: ASEO INTEGRAL | P35: NO RESIDENCIAL - ASEO GP | Q35: COMERCIAL | R35: AFORO ORDINARIO-EXTRAORDINARIO | S35: Ocupado | T35: 2026 | U35: 5 | V35: 1081522454 | W35: 1081540524 | X35: 08-05-2026 | Y35: 03-06-2026 | Z35: 199601.25 | AA35: 199601.25 | AB35: 66533.75 | AC35: 500 | AD35: 0 | AE35: 0 | AF35: 0 | AG35: 0 | AH35: 0 | AI35: 199601.25 | AJ35: 413502.74 | AK35: 1 | AL35: 376.2 | AM35: 0 | AR35: 0 | AS35: COORDINADOR.OPERACIONES.R11@JERONIMO-MARTINS.COM | AT35: CORREO ELECTRONICO CERTIFICADO 472 | AU35: ANGEL | AV35: 46163
A36: 285191 | B36: 248380 | C36: 248380 | D36: 533675 | E36: 533675 | F36: 900276962 | G36: D1 S A S | H36: KDX 73-2 1116 | I36: NIÑA CECI | J36: NO | K36: D1 | L36: CÚCUTA MPO | M36: CUCUTA DIRECTA | N36: 1002 - CICL FACT DIRECTA CUCUTA NORTE | O36: ASEO INTEGRAL | P36: NO RESIDENCIAL - ASEO PP | Q36: COMERCIAL RANGO 3 | R36: NO AFORADO | S36: Ocupado | T36: 2026 | U36: 5 | V36: 1081522492 | W36: 1081540562 | X36: 08-05-2026 | Y36: 03-06-2026 | Z36: 113911.5 | AA36: 113911.5 | AB36: 37970.5 | AC36: 0 | AD36: 0 | AE36: 0 | AF36: 0 | AG36: 0 | AH36: 0 | AI36: 113911.5 | AJ36: 113911.5 | AK36: 0 | AL36: 376.2 | AM36: 0 | AR36: 0 | AS36: ALBA.CELIS@D1.COM.CO;CARMEN.DAVILA@D1.COM.CO | AT36: CORREO ELECTRONICO CERTIFICADO 472 | AU36: ANGEL | AV36: 46163
A37: 285191 | B37: 255284 | C37: 255284 | D37: 577190 | E37: 577190 | F37: 900276962 | G37: D1 S A S | H37: KDX 73-2 1116 | I37: MOTILONES | J37: NO | K37: D1 | L37: CÚCUTA MPO | M37: CUCUTA DIRECTA | N37: 1002 - CICL FACT DIRECTA CUCUTA NORTE | O37: ASEO INTEGRAL | P37: NO RESIDENCIAL - ASEO PP | Q37: COMERCIAL RANGO 3 | R37: NO AFORADO | S37: Ocupado | T37: 2026 | U37: 5 | V37: 1081522496 | W37: 1081540566 | X37: 08-05-2026 | Y37: 03-06-2026 | Z37: 113911.5 | AA37: 113911.5 | AB37: 37970.5 | AC37: 0 | AD37: 0 | AE37: 0 | AF37: 0 | AG37: 0 | AH37: 0 | AI37: 113911.5 | AJ37: 113911.5 | AK37: 0 | AL37: 376.2 | AM37: 0 | AR37: 0 | AS37: ALBA.CELIS@D1.COM.CO;CARMEN.DAVILA@D1.COM.CO | AT37: CORREO ELECTRONICO CERTIFICADO 472 | AU37: ANGEL | AV37: 46163
A38: 271157 | B38: 271156 | C38: 271156 | D38: 689156 | E38: 689156 | F38: 900373778-6 | G38: AEROPUERTO DE O | H38: AVD AEROPUERTO CAMILO DAZA | I38: AEROPUERTO | J38: ZONA NORTE | K38: NO | L38: CÚCUTA MPO | M38: CUCUTA DIRECTA | N38: 1002 - CICL FACT DIRECTA CUCUTA NORTE | O38: ASEO INTEGRAL | P38: NO RESIDENCIAL - ASEO PP | Q38: COMERCIAL RANGO 1 | R38: NO AFORADO | S38: Ocupado | T38: 2026 | U38: 5 | V38: 1081522499 | W38: 1081540569 | X38: 08-05-2026 | Y38: 03-06-2026 | Z38: 77082.02 | AA38: 77082.02 | AB38: 25380.5 | AC38: 0 | AD38: 940.52 | AE38: 0 | AF38: 0 | AG38: 0 | AH38: 0 | AI38: 77082.02 | AJ38: 209503.68 | AK38: 2 | AL38: 376.2 | AM38: 0 | AR38: 0 | AS38: CARLOS.PICON@AEROORIENTE.COM.CO | AT38: VERIFICADOR | AU38: MARTIN | AV38: 46163
A39: 285477 | B39: 285476 | C39: 285476 | D39: 60519 | E39: 60519 | F39: 60519 | G39: JOSE MIGUEL CAICEDO GONZALES | H39: KDX 175 (AVE 7 4-49) | I39: PANAMERICANO | J39: ZONA NORTE | K39: NO | L39: CÚCUTA MPO | M39: CUCUTA ZONA NORTE | N39: 1002 - CICL FACT DIRECTA CUCUTA NORTE | O39: ASEO INTEGRAL | P39: NO RESIDENCIAL - ASEO PP | Q39: INDUSTRIAL RANGO 3 | R39: NO AFORADO | S39: Ocupado | T39: 2026 | U39: 5 | V39: 1081522505 | W39: 1081540575 | X39: 08-05-2026 | Y39: 03-06-2026 | Z39: 98723.3 | AA39: 98723.3 | AB39: 22782.3 | AC39: 0 | AD39: 0 | AE39: 0 | AF39: 0 | AG39: 0 | AH39: 0 | AI39: 98723.3 | AJ39: 98723.3 | AK39: 0 | AL39: 326.04 | AM39: 0 | AR39: 0 | AS39: VILLAREALCONTABILIDAD@GMAIL.COM | AT39: VERIFICADOR | AU39: MARTIN | AV39: 46163
A40: 297 | B40: 291584 | C40: 291584 | D40: 76578 | E40: 76578 | F40: 807004352-3 | G40: EMPRESA SOCIAL DEL ESTADO E.S.E IMSALUD | H40: AVE 4 17-89 - 0239431 | I40: EL SALADO | J40: NO | K40: IMSALUD | L40: CÚCUTA MPO | M40: CUCUTA ZONA NORTE | N40: 1002 - CICL FACT DIRECTA CUCUTA NORTE | O40: ASEO INTEGRAL | P40: NO RESIDENCIAL - ASEO GP | Q40: OFICIAL | R40: AFORO ORDINARIO-EXTRAORDINARIO | S40: Ocupado | T40: 2026 | U40: 5 | V40: 1081522509 | W40: 1081540579 | X40: 08-05-2026 | Y40: 03-06-2026 | Z40: 104595.85 | AA40: 104595.85 | AB40: 0 | AC40: 350 | AD40: 0 | AE40: 0 | AF40: 0 | AG40: 0 | AH40: 0 | AI40: 104595.85 | AJ40: 104595.85 | AK40: 0 | AL40: 250.8 | AM40: 0 | AR40: 0 | AS40: SUBFINANCIERA@IMSALUD.GOV.CO | AT40: CORREO ELECTRONICO CERTIFICADO 472 | AU40: ANGEL | AV40: 46164
A41: 297 | B41: 300728 | C41: 300728 | D41: 215903 | E41: 215903 | F41: 807004352-3 | G41: EMPRESA SOCIAL DEL ESTADO E.S.E IMSALUD | H41: AVE 4 17-89 - 0239431 | I41: TOLEDO PLATA | J41: NO | K41: IMSALUD | L41: CÚCUTA MPO | M41: CUCUTA ZONA NORTE | N41: 1002 - CICL FACT DIRECTA CUCUTA NORTE | O41: ASEO INTEGRAL | P41: NO RESIDENCIAL - ASEO GP | Q41: OFICIAL | R41: AFORO ORDINARIO-EXTRAORDINARIO | S41: Ocupado | T41: 2026 | U41: 5 | V41: 1081522513 | W41: 1081540583 | X41: 08-05-2026 | Y41: 03-06-2026 | Z41: 104595.85 | AA41: 104595.85 | AB41: 0 | AC41: 350 | AD41: 0 | AE41: 0 | AF41: 0 | AG41: 0 | AH41: 0 | AI41: 104595.85 | AJ41: 104595.85 | AK41: 0 | AL41: 250.8 | AM41: 0 | AR41: 0 | AS41: SUBFINANCIERA@IMSALUD.GOV.CO | AT41: CORREO ELECTRONICO CERTIFICADO 472 | AU41: ANGEL | AV41: 46164
A42: 297 | B42: 309204 | C42: 309204 | D42: 322755 | E42: 322755 | F42: 807004352-3 | G42: EMPRESA SOCIAL DEL ESTADO E.S.E IMSALUD | H42: AVE 4 17-89 - 0239431 | I42: LOMA DE BOLIVAR | J42: NO | K42: IMSALUD | L42: CÚCUTA MPO | M42: CUCUTA ZONA NORTE | N42: 1002 - CICL FACT DIRECTA CUCUTA NORTE | O42: ASEO INTEGRAL | P42: NO RESIDENCIAL - ASEO GP | Q42: OFICIAL | R42: AFORO ORDINARIO-EXTRAORDINARIO | S42: Ocupado | T42: 2026 | U42: 5 | V42: 1081522516 | W42: 1081540586 | X42: 08-05-2026 | Y42: 03-06-2026 | Z42: 779417.69 | AA42: 779417.69 | AB42: 0 | AC42: 1663 | AD42: 0 | AE42: 0 | AF42: 0 | AG42: 0 | AH42: 0 | AI42: 779417.69 | AJ42: 779417.69 | AK42: 0 | AL42: 425850.8 | AM42: 0 | AR42: 0 | AS42: SUBFINANCIERA@IMSALUD.GOV.CO | AT42: CORREO ELECTRONICO CERTIFICADO 472 | AU42: ANGEL | AV42: 46164
A43: 314877 | B43: 314876 | C43: 314876 | D43: 451976 | E43: 451976 | F43: 860503159 | G43: PASH SAS | H43: AVE LIBERTADORES CANAL BOGOTA LOC 23 1079 | I43: PRADOS NORTE | J43: ZONA NORTE | K43: PASH | L43: CÚCUTA MPO | M43: CUCUTA DIRECTA | N43: 1002 - CICL FACT DIRECTA CUCUTA NORTE | O43: ASEO INTEGRAL | P43: NO RESIDENCIAL - ASEO GP | Q43: COMERCIAL | R43: AFORO ORDINARIO-EXTRAORDINARIO | S43: Ocupado | T43: 2026 | U43: 5 | V43: 1081522521 | W43: 1081540591 | X43: 08-05-2026 | Y43: 03-06-2026 | Z43: 189636.19 | AA43: 189636.19 | AB43: 63212.07 | AC43: 465 | AD43: 0 | AE43: 0 | AF43: 0 | AG43: 0 | AH43: 0 | AI43: 189636.19 | AJ43: 189636.19 | AK43: 0 | AL43: 376.2 | AM43: 0 | AR43: 0 | AS43: SERVICIOSPUBLICOS@PASH.COM.CO; abayona@tekstelas.com; kguavita@tekstelas.com | AT43: VERIFICADOR | AU43: MARTIN | AV43: 46163
A44: 232 | B44: 3156 | C44: 3156 | D44: 80123482 | E44: 80123482 | F44: 830122566 | G44: TELECOM AVE 0 EDIF PRINCIPAL | H44: AV 0 N 10-61 | I44: ZONA INDUSTRIAL | J44: NO | K44: MOVISTAR | L44: CÚCUTA MPO | M44: CUCUTA ZONA NORTE | N44: 1002 - CICL FACT DIRECTA CUCUTA NORTE | O44: ASEO INTEGRAL | P44: NO RESIDENCIAL - ASEO PP | Q44: COMERCIAL RANGO 3 | R44: NO AFORADO | S44: Ocupado | T44: 2026 | U44: 5 | V44: 1081522297 | W44: 1081540367 | X44: 08-05-2026 | Y44: 03-06-2026 | Z44: 113911.5 | AA44: 113911.5 | AB44: 37970.5 | AC44: 0 | AD44: 0 | AE44: 0 | AF44: 0 | AG44: 0 | AH44: 0 | AI44: 113911.5 | AJ44: 231015.37 | AK44: 1 | AL44: 376.2 | AM44: 0 | AR44: 0 | AS44: SERVICIOSPUBLICOS.TC@TELEFONICA.COM; D.CRUZ02@TELEFONICA.COM | AT44: CORREO ELECTRONICO CERTIFICADO 472 | AU44: ANGEL | AV44: 46164
A45: 232 | B45: 3160 | C45: 3160 | D45: 80123486 | E45: 80123486 | F45: 830122566 | G45: TELECOM AVE 0 EDIF PRINCIPAL | H45: AV 0 N 10-61 | I45: PANAMERICANO | J45: NO | K45: MOVISTAR | L45: CÚCUTA MPO | M45: CUCUTA ZONA NORTE | N45: 1002 - CICL FACT DIRECTA CUCUTA NORTE | O45: ASEO INTEGRAL | P45: NO RESIDENCIAL - ASEO PP | Q45: COMERCIAL RANGO 3 | R45: NO AFORADO | S45: Ocupado | T45: 2026 | U45: 5 | V45: 1081522302 | W45: 1081540372 | X45: 08-05-2026 | Y45: 03-06-2026 | Z45: 113911.5 | AA45: 113911.5 | AB45: 37970.5 | AC45: 0 | AD45: 0 | AE45: 0 | AF45: 0 | AG45: 0 | AH45: 0 | AI45: 113911.5 | AJ45: 231015.37 | AK45: 1 | AL45: 376.2 | AM45: 0 | AR45: 0 | AS45: SERVICIOSPUBLICOS.TC@TELEFONICA.COM; D.CRUZ02@TELEFONICA.COM | AT45: CORREO ELECTRONICO CERTIFICADO 472 | AU45: ANGEL | AV45: 46164
A46: 3165 | B46: 3164 | C46: 3164 | D46: 80123490 | E46: 80123490 | F46: 800215546 | G46: COMPLEJO CARCELARIO Y PEN. | H46: AV PANAMERICANA VIA SALADO | I46: SAN GERARDO | J46: NO | K46: MODELO | L46: CÚCUTA MPO | M46: CUCUTA DIRECTA | N46: 1002 - CICL FACT DIRECTA CUCUTA NORTE | O46: ASEO INTEGRAL | P46: NO RESIDENCIAL - ASEO GP | Q46: OFICIAL | R46: AFORO PERMANENTE | S46: Ocupado | T46: 2026 | U46: 5 | V46: 1081522304 | W46: 1081540374 | X46: 08-05-2026 | Y46: 03-06-2026 | Z46: 13700758 | AA46: 13700758 | AB46: 0 | AC46: 71980 | AD46: 0 | AE46: 0 | AF46: 0 | AG46: 0 | AH46: 0 | AI46: 13700758 | AJ46: 13700758 | AK46: 0 | AL46: 250.8 | AM46: 0 | AR46: 0 | AS46: SERVICIOSPUBLICOS.ORIENTE@INPEC.GOV.CO | AT46: CORREO ELECTRONICO CERTIFICADO 472 | AU46: ANGEL | AV46: 46169
A47: 3169 | B47: 3168 | C47: 3168 | D47: 80123494 | E47: 80123494 | F47: 8070375 | G47: SUBESTACION DE POLICIA BELEN | H47: AV 26 26 - 27 | I47: BELEN | J47: NO | K47: POLICIA | L47: CÚCUTA MPO | M47: CUCUTA DIRECTA | N47: 1002 - CICL FACT DIRECTA CUCUTA NORTE | O47: ASEO INTEGRAL | P47: NO RESIDENCIAL - ASEO GP | Q47: OFICIAL | R47: AFORO ORDINARIO-EXTRAORDINARIO | S47: Ocupado | T47: 2026 | U47: 5 | V47: 1081522309 | W47: 1081540379 | X47: 08-05-2026 | Y47: 03-06-2026 | Z47: 119780.73 | AA47: 119780.73 | AB47: 0 | AC47: 430 | AD47: 0 | AE47: 0 | AF47: 0 | AG47: 0 | AH47: 0 | AI47: 119780.73 | AJ47: 237518.52 | AK47: 1 | AL47: 250.8 | AM47: 0 | AR47: 0 | AS47: LUIS.GONZALEZ0973@CORREO.POLICIA.GOV.CO | AT47: CORREO ELECTRONICO CERTIFICADO 472 | AU47: ANGEL | AV47: 46163
A48: 3173 | B48: 3172 | C48: 3172 | D48: 80123498 | E48: 80123498 | F48: 8072589 | G48: ESCUELA LA DIVINA PASTORA | H48: CLLE 31 # 31-60 LA DIVINA PASTORA | I48: DIVINA PASTORA | J48: NO | K48: COLEGIOS ZONA NORTE | L48: CÚCUTA MPO | M48: CUCUTA DIRECTA | N48: 1002 - CICL FACT DIRECTA CUCUTA NORTE | O48: ASEO INTEGRAL | P48: NO RESIDENCIAL - ASEO GP | Q48: OFICIAL | R48: AFORO ORDINARIO-EXTRAORDINARIO | S48: Ocupado | T48: 2026 | U48: 5 | V48: 1081522314 | W48: 1081540384 | X48: 08-05-2026 | Y48: 03-06-2026 | Z48: 360840.7 | AA48: 360840.7 | AB48: 0 | AC48: 1700 | AD48: 0 | AE48: 0 | AF48: 0 | AG48: 0 | AH48: 0 | AI48: 360840.7 | AJ48: 876316.5 | AK48: 3 | AL48: 250.8 | AM48: 0 | AR48: 0 | AS48: AREAFINANCIERA@SEMCUCUTA.GOV.CO | AT48: CARTERA | AU48: yelitza | AV48: 46164
A49: 455370 | B49: 3176 | C49: 3176 | D49: 80123502 | E49: 80123502 | F49: 890501434- 2 | G49: MUNICIPIO DE SAN JOSE DE CUCUTA - SEDE TONCHALA | H49: CALLE 10 NO 0E-16 EDF CENTRO EMPRESARIAL BLOQUE B HOTEL TONCHALA | I49: BARRIO NO LISTADO | J49: NO | K49: COLEGIOS ZONA NORTE | L49: CÚCUTA MPO | M49: CUCUTA ZONA NORTE | N49: 1002 - CICL FACT DIRECTA CUCUTA NORTE | O49: ASEO INTEGRAL | P49: NO RESIDENCIAL - ASEO GP | Q49: OFICIAL | R49: AFORO ORDINARIO-EXTRAORDINARIO | S49: Ocupado | T49: 2026 | U49: 5 | V49: 1081522317 | W49: 1081540387 | X49: 08-05-2026 | Y49: 03-06-2026 | Z49: 354766.75 | AA49: 354766.75 | AB49: 0 | AC49: 1668 | AD49: 0 | AE49: 0 | AF49: 0 | AG49: 0 | AH49: 0 | AI49: 354766.75 | AJ49: 864314.46 | AK49: 3 | AL49: 250.8 | AM49: 0 | AR49: 0 | AS49: AREAFINANCIERA@SEMCUCUTA.GOV.CO | AT49: CARTERA | AU49: yelitza | AV49: 46164
A50: 455370 | B50: 3184 | C50: 3184 | D50: 80123510 | E50: 80123510 | F50: 890501434- 2 | G50: MUNICIPIO DE SAN JOSE DE CUCUTA - SEDE TONCHALA | H50: CALLE 10 NO 0E-16 EDF CENTRO EMPRESARIAL BLOQUE B HOTEL TONCHALA | I50: BUENOS AIRES | J50: NO | K50: COLEGIOS ZONA NORTE | L50: CÚCUTA MPO | M50: CUCUTA ZONA NORTE | N50: 1002 - CICL FACT DIRECTA CUCUTA NORTE | O50: ASEO INTEGRAL | P50: NO RESIDENCIAL - ASEO GP | Q50: OFICIAL | R50: AFORO ORDINARIO-EXTRAORDINARIO | S50: Ocupado | T50: 2026 | U50: 5 | V50: 1081522321 | W50: 1081540391 | X50: 08-05-2026 | Y50: 03-06-2026 | Z50: 229871.11 | AA50: 229871.11 | AB50: 0 | AC50: 1010 | AD50: 0 | AE50: 0 | AF50: 0 | AG50: 0 | AH50: 0 | AI50: 229871.11 | AJ50: 617522.34 | AK50: 3 | AL50: 250.8 | AM50: 0 | AR50: 0 | AS50: AREAFINANCIERA@SEMCUCUTA.GOV.CO | AT50: CARTERA | AU50: yelitza | AV50: 46164
A51: 455370 | B51: 3188 | C51: 3188 | D51: 80123514 | E51: 80123514 | F51: 890501434- 2 | G51: MUNICIPIO DE SAN JOSE DE CUCUTA - SEDE TONCHALA | H51: CALLE 10 NO 0E-16 EDF CENTRO EMPRESARIAL BLOQUE B HOTEL TONCHALA | I51: LA FLORIDA (ATALAYA) | J51: NO | K51: COLEGIOS ZONA NORTE | L51: CÚCUTA MPO | M51: CUCUTA ZONA NORTE | N51: 1002 - CICL FACT DIRECTA CUCUTA NORTE | O51: ASEO INTEGRAL | P51: NO RESIDENCIAL - ASEO GP | Q51: OFICIAL | R51: AFORO ORDINARIO-EXTRAORDINARIO | S51: Ocupado | T51: 2026 | U51: 5 | V51: 1081522325 | W51: 1081540395 | X51: 08-05-2026 | Y51: 03-06-2026 | Z51: 362738.81 | AA51: 362738.81 | AB51: 0 | AC51: 1710 | AD51: 0 | AE51: 0 | AF51: 0 | AG51: 0 | AH51: 0 | AI51: 362738.81 | AJ51: 880067.14 | AK51: 3 | AL51: 250.8 | AM51: 0 | AR51: 0 | AS51: AREAFINANCIERA@SEMCUCUTA.GOV.CO | AT51: CARTERA | AU51: yelitza | AV51: 46164
A52: 455370 | B52: 3192 | C52: 3192 | D52: 80123518 | E52: 80123518 | F52: 890501434- 2 | G52: MUNICIPIO DE SAN JOSE DE CUCUTA - SEDE TONCHALA | H52: CALLE 10 NO 0E-16 EDF CENTRO EMPRESARIAL BLOQUE B HOTEL TONCHALA | I52: ATALAYA I ETAPA | J52: NO | K52: COLEGIOS ZONA NORTE | L52: CÚCUTA MPO | M52: CUCUTA ZONA NORTE | N52: 1002 - CICL FACT DIRECTA CUCUTA NORTE | O52: ASEO INTEGRAL | P52: NO RESIDENCIAL - ASEO GP | Q52: OFICIAL | R52: AFORO ORDINARIO-EXTRAORDINARIO | S52: Ocupado | T52: 2026 | U52: 5 | V52: 1081522328 | W52: 1081540398 | X52: 08-05-2026 | Y52: 03-06-2026 | Z52: 256444.65 | AA52: 256444.65 | AB52: 0 | AC52: 1150 | AD52: 0 | AE52: 0 | AF52: 0 | AG52: 0 | AH52: 0 | AI52: 256444.65 | AJ52: 670031.3 | AK52: 3 | AL52: 250.8 | AM52: 0 | AR52: 0 | AS52: AREAFINANCIERA@SEMCUCUTA.GOV.CO | AT52: CARTERA | AU52: yelitza | AV52: 46164
A53: 455370 | B53: 3196 | C53: 3196 | D53: 80123522 | E53: 80123522 | F53: 890501434- 2 | G53: MUNICIPIO DE SAN JOSE DE CUCUTA - SEDE TONCHALA | H53: CALLE 10 NO 0E-16 EDF CENTRO EMPRESARIAL BLOQUE B HOTEL TONCHALA | I53: PALMERAS | J53: NO | K53: COLEGIOS ZONA NORTE | L53: CÚCUTA MPO | M53: CUCUTA ZONA NORTE | N53: 1002 - CICL FACT DIRECTA CUCUTA NORTE | O53: ASEO INTEGRAL | P53: NO RESIDENCIAL - ASEO GP | Q53: OFICIAL | R53: AFORO ORDINARIO-EXTRAORDINARIO | S53: Ocupado | T53: 2026 | U53: 5 | V53: 1081522332 | W53: 1081540402 | X53: 08-05-2026 | Y53: 03-06-2026 | Z53: 305795.51 | AA53: 305795.51 | AB53: 0 | AC53: 1410 | AD53: 0 | AE53: 0 | AF53: 0 | AG53: 0 | AH53: 0 | AI53: 305795.51 | AJ53: 767547.94 | AK53: 3 | AL53: 250.8 | AM53: 0 | AR53: 0 | AS53: AREAFINANCIERA@SEMCUCUTA.GOV.CO | AT53: CARTERA | AU53: yelitza | AV53: 46164
A54: 455370 | B54: 3200 | C54: 3200 | D54: 80123526 | E54: 80123526 | F54: 890501434- 2 | G54: MUNICIPIO DE SAN JOSE DE CUCUTA - SEDE TONCHALA | H54: CALLE 10 NO 0E-16 EDF CENTRO EMPRESARIAL BLOQUE B HOTEL TONCHALA | I54: DO¿A NIDIA | J54: NO | K54: COLEGIOS ZONA NORTE | L54: CÚCUTA MPO | M54: CUCUTA ZONA NORTE | N54: 1002 - CICL FACT DIRECTA CUCUTA NORTE | O54: ASEO INTEGRAL | P54: NO RESIDENCIAL - ASEO GP | Q54: OFICIAL | R54: AFORO ORDINARIO-EXTRAORDINARIO | S54: Ocupado | T54: 2026 | U54: 5 | V54: 1081522336 | W54: 1081540406 | X54: 08-05-2026 | Y54: 03-06-2026 | Z54: 465236.75 | AA54: 465236.75 | AB54: 0 | AC54: 2250 | AD54: 0 | AE54: 0 | AF54: 0 | AG54: 0 | AH54: 0 | AI54: 465236.75 | AJ54: 1082601.7 | AK54: 3 | AL54: 250.8 | AM54: 0 | AR54: 0 | AS54: AREAFINANCIERA@SEMCUCUTA.GOV.CO | AT54: CARTERA | AU54: yelitza | AV54: 46164
A55: 3205 | B55: 3204 | C55: 3204 | D55: 80123530 | E55: 80123530 | F55: 807001396-3 | G55: CENABASTOS DE CUCUTA PROPIEDAD HORIZONTAL | H55: SEC T-COMERCIO CENABASTOS OF 210 211 URB TASAJERO | I55: BARRIO NO LISTADO | J55: NO | K55: NO | L55: CÚCUTA MPO | M55: CUCUTA DIRECTA | N55: 1002 - CICL FACT DIRECTA CUCUTA NORTE | O55: ASEO INTEGRAL | P55: NO RESIDENCIAL - ASEO GP | Q55: OFICIAL | R55: AFORO ORDINARIO-EXTRAORDINARIO | S55: Ocupado | T55: 2026 | U55: 5 | V55: 1081522340 | W55: 1081540410 | X55: 08-05-2026 | Y55: 03-06-2026 | Z55: 8010224 | AA55: 8010224 | AB55: 0 | AC55: 42000 | AD55: 0 | AE55: 0 | AF55: 0 | AG55: 0 | AH55: 0 | AI55: 8010224 | AJ55: 8010224 | AK55: 0 | AL55: 250.8 | AM55: 0 | AR55: 0 | AS55: CENABASTOSPH@HOTMAIL.COM | AT55: CORREO ELECTRONICO CERTIFICADO 472 | AU55: Liliana | AV55: 46167
A56: 3209 | B56: 3208 | C56: 3208 | D56: 80127938 | E56: 80127938 | F56: 901375954 | G56: POLIMEROS ANDECOL DC S.A.S | H56: AV 7 1 136 BRR LA INSULA | I56: LA INSULA | J56: NO | K56: NO | L56: CÚCUTA MPO | M56: CUCUTA DIRECTA | N56: 1002 - CICL FACT DIRECTA CUCUTA NORTE | O56: ASEO INTEGRAL | P56: NO RESIDENCIAL - ASEO GP | Q56: COMERCIAL | R56: AFORO ORDINARIO-EXTRAORDINARIO | S56: Ocupado | T56: 2026 | U56: 5 | V56: 1081522344 | W56: 1081540414 | X56: 08-05-2026 | Y56: 03-06-2026 | Z56: 133235.34 | AA56: 133235.34 | AB56: 43092.1 | AC56: 253 | AD56: 3959.06 | AE56: 0 | AF56: 0 | AG56: 0 | AH56: 0 | AI56: 133235.34 | AJ56: 512100.9 | AK56: 3 | AL56: 376.2 | AM56: 0 | AR56: 0 | AS56: FACTURACION.ANDECOL@GMAIL.COM | AT56: CORREO ELECTRONICO CERTIFICADO 472 | AU56: Liliana | AV56: 46167
A57: 3213 | B57: 3212 | C57: 3212 | D57: 80202730 | E57: 80202730 | F57: 900155107- | G57: CENCOSUD COLOMBIA SA | H57: AVENIDA LIBERTADORES/CANAL BOGOTA | I57: PRADOS NORTE | J57: NO | K57: METRO | L57: CÚCUTA MPO | M57: CUCUTA ZONA NORTE | N57: 1002 - CICL FACT DIRECTA CUCUTA NORTE | O57: ASEO INTEGRAL | P57: NO RESIDENCIAL - ASEO GP | Q57: COMERCIAL | R57: AFORO ORDINARIO-EXTRAORDINARIO | S57: Ocupado | T57: 2026 | U57: 5 | V57: 1081522348 | W57: 1081540418 | X57: 08-05-2026 | Y57: 03-06-2026 | Z57: 840213.38 | AA57: 840213.38 | AB57: 280071.13 | AC57: 2750 | AD57: 0 | AE57: 0 | AF57: 0 | AG57: 0 | AH57: 0 | AI57: 840213.38 | AJ57: 840213.38 | AK57: 0 | AL57: 376.2 | AM57: 0 | AR57: 0 | AS57: SERVICIOS_PUBLICOS_COLOMBIA@CENCOSUD.COM.CO; MariaAngela.SanchezRincon@cencosud.com.co | AT57: CORREO ELECTRONICO CERTIFICADO 472 | AU57: ANGEL | AV57: 46169
A58: 350 | B58: 3216 | C58: 3216 | D58: 80205194 | E58: 80205194 | F58: 900603041 | G58: COMERCIALIZADORA MONTES DE COLOMBIA S.A.S | H58: AVE 6 7-35 SUPERMERCADO | I58: URB TASAJERO | J58: NO | K58: LOS MONTES | L58: CÚCUTA MPO | M58: CUCUTA DIRECTA | N58: 1002 - CICL FACT DIRECTA CUCUTA NORTE | O58: ASEO INTEGRAL | P58: NO RESIDENCIAL - ASEO GP | Q58: COMERCIAL | R58: AFORO ORDINARIO-EXTRAORDINARIO | S58: Ocupado | T58: 2026 | U58: 5 | V58: 1081522352 | W58: 1081540422 | X58: 08-05-2026 | Y58: 03-06-2026 | Z58: 492025.62 | AA58: 492025.62 | AB58: 161439.25 | AC58: 1500 | AD58: 7707.87 | AE58: 0 | AF58: 0 | AG58: 0 | AH58: 0 | AI58: 492025.62 | AJ58: 1442311.1 | AK58: 3 | AL58: 376.2 | AM58: 0 | AR58: 0 | AS58: GASTOS@SUPERLOSMONTES.CO;FACTURAELECTRONICA@SUPERLOSMONTES.CO | AT58: CORREO ELECTRONICO CERTIFICADO 472 | AU58: ANGEL | AV58: 46164
A59: 455370 | B59: 3228 | C59: 3228 | D59: 80206522 | E59: 80206522 | F59: 890501434- 2 | G59: MUNICIPIO DE SAN JOSE DE CUCUTA - SEDE TONCHALA | H59: CALLE 10 NO 0E-16 EDF CENTRO EMPRESARIAL BLOQUE B HOTEL TONCHALA | I59: ATALAYA | J59: NO | K59: COLEGIOS ZONA NORTE | L59: CÚCUTA MPO | M59: CUCUTA ZONA NORTE | N59: 1002 - CICL FACT DIRECTA CUCUTA NORTE | O59: ASEO INTEGRAL | P59: NO RESIDENCIAL - ASEO GP | Q59: OFICIAL | R59: AFORO ORDINARIO-EXTRAORDINARIO | S59: Ocupado | T59: 2026 | U59: 5 | V59: 1081522356 | W59: 1081540426 | X59: 08-05-2026 | Y59: 03-06-2026 | Z59: 786586.77 | AA59: 786586.77 | AB59: 0 | AC59: 3943 | AD59: 0 | AE59: 0 | AF59: 0 | AG59: 0 | AH59: 0 | AI59: 786586.77 | AJ59: 1717585.1 | AK59: 3 | AL59: 250.8 | AM59: 0 | AR59: 0 | AS59: AREAFINANCIERA@SEMCUCUTA.GOV.CO | AT59: CARTERA | AU59: yelitza | AV59: 46164
A60: 323057 | B60: 323056 | C60: 323056 | D60: 536628 | E60: 536628 | F60: 890900050 | G60: NUTRESA/C.I. BRAYTEX S.A. | H60: CL 17 N 5-101 | I60: ZONA INDUSTRIAL | J60: ZONA NORTE | K60: NO | L60: CÚCUTA MPO | M60: CUCUTA DIRECTA | N60: 1002 - CICL FACT DIRECTA CUCUTA NORTE | O60: ASEO INTEGRAL | P60: NO RESIDENCIAL - ASEO GP | Q60: COMERCIAL | R60: AFORO PERMANENTE | S60: Ocupado | T60: 2026 | U60: 5 | V60: 1081522525 | W60: 1081540595 | X60: 08-05-2026 | Y60: 03-06-2026 | Z60: 377562.41 | AA60: 377562.41 | AB60: 125849.7 | AC60: 1125 | AD60: 13.33 | AE60: 0 | AF60: 0 | AG60: 0 | AH60: 0 | AI60: 377562.41 | AJ60: 387277.62 | AK60: 1 | AL60: 376.2 | AM60: 0 | AR60: 0 | AS60: LYCALDERON@COMERCIALNUTRESA.COM.CO | AT60: VERIFICADOR | AU60: MARTIN | AV60: 46163
A61: 455370 | B61: 3232 | C61: 3232 | D61: 80206526 | E61: 80206526 | F61: 890501434- 2 | G61: MUNICIPIO DE SAN JOSE DE CUCUTA - SEDE TONCHALA | H61: CALLE 10 NO 0E-16 EDF CENTRO EMPRESARIAL BLOQUE B HOTEL TONCHALA | I61: ANTONIA SANTOS | J61: NO | K61: COLEGIOS ZONA NORTE | L61: CÚCUTA MPO | M61: CUCUTA ZONA NORTE | N61: 1002 - CICL FACT DIRECTA CUCUTA NORTE | O61: ASEO INTEGRAL | P61: NO RESIDENCIAL - ASEO GP | Q61: OFICIAL | R61: AFORO ORDINARIO-EXTRAORDINARIO | S61: Ocupado | T61: 2026 | U61: 5 | V61: 1081522361 | W61: 1081540431 | X61: 08-05-2026 | Y61: 03-06-2026 | Z61: 549702.65 | AA61: 549702.65 | AB61: 0 | AC61: 2695 | AD61: 0 | AE61: 0 | AF61: 0 | AG61: 0 | AH61: 0 | AI61: 549702.65 | AJ61: 1249505.2 | AK61: 3 | AL61: 250.8 | AM61: 0 | AR61: 0 | AS61: AREAFINANCIERA@SEMCUCUTA.GOV.CO | AT61: CARTERA | AU61: yelitza | AV61: 46164
A62: 573 | B62: 3236 | C62: 3236 | D62: 80212407 | E62: 80212407 | F62: 900144842 | G62: DEL - BEN SAS | H62: BODEGA D1 -1 ZONA FRANCA | I62: ZONA FRANCA | J62: NO | K62: DEL BEN | L62: CÚCUTA MPO | M62: CUCUTA DIRECTA | N62: 1002 - CICL FACT DIRECTA CUCUTA NORTE | O62: ASEO INTEGRAL | P62: NO RESIDENCIAL - ASEO GP | Q62: INDUSTRIAL | R62: AFORO ORDINARIO-EXTRAORDINARIO | S62: Ocupado | T62: 2026 | U62: 5 | V62: 1081522364 | W62: 1081540434 | X62: 08-05-2026 | Y62: 03-06-2026 | Z62: 113680.93 | AA62: 113680.93 | AB62: 25826.79 | AC62: 252.5 | AD62: 1764.85 | AE62: 0 | AF62: 0 | AG62: 0 | AH62: 0 | AI62: 113680.93 | AJ62: 223992.95 | AK62: 1 | AL62: 326.04 | AM62: 0 | AR62: 0 | AS62: CONTABILIDAD1@DELBEN.CO | AT62: CORREO ELECTRONICO CERTIFICADO 472 | AU62: ANGEL | AV62: 46169
A63: 455370 | B63: 3240 | C63: 3240 | D63: 80212698 | E63: 80212698 | F63: 890501434- 2 | G63: MUNICIPIO DE SAN JOSE DE CUCUTA - SEDE TONCHALA | H63: CALLE 10 NO 0E-16 EDF CENTRO EMPRESARIAL BLOQUE B HOTEL TONCHALA | I63: PUEBLO NUEVO | J63: NO | K63: COLEGIOS ZONA NORTE | L63: CÚCUTA MPO | M63: CUCUTA ZONA NORTE | N63: 1002 - CICL FACT DIRECTA CUCUTA NORTE | O63: ASEO INTEGRAL | P63: NO RESIDENCIAL - ASEO GP | Q63: OFICIAL | R63: AFORO ORDINARIO-EXTRAORDINARIO | S63: Ocupado | T63: 2026 | U63: 5 | V63: 1081522369 | W63: 1081540439 | X63: 08-05-2026 | Y63: 03-06-2026 | Z63: 133067.5 | AA63: 133067.5 | AB63: 0 | AC63: 500 | AD63: 0 | AE63: 0 | AF63: 0 | AG63: 0 | AH63: 0 | AI63: 133067.5 | AJ63: 426239.7 | AK63: 3 | AL63: 250.8 | AM63: 0 | AR63: 0 | AS63: AREAFINANCIERA@SEMCUCUTA.GOV.CO | AT63: CARTERA | AU63: yelitza | AV63: 46164
A64: 455370 | B64: 3248 | C64: 3248 | D64: 80212706 | E64: 80212706 | F64: 890501434- 2 | G64: MUNICIPIO DE SAN JOSE DE CUCUTA - SEDE TONCHALA | H64: CALLE 10 NO 0E-16 EDF CENTRO EMPRESARIAL BLOQUE B HOTEL TONCHALA | I64: BRISAS DEL AEROPUERTO | J64: NO | K64: COLEGIOS ZONA NORTE | L64: CÚCUTA MPO | M64: CUCUTA ZONA NORTE | N64: 1002 - CICL FACT DIRECTA CUCUTA NORTE | O64: ASEO INTEGRAL | P64: NO RESIDENCIAL - ASEO GP | Q64: OFICIAL | R64: AFORO ORDINARIO-EXTRAORDINARIO | S64: Ocupado | T64: 2026 | U64: 5 | V64: 1081522373 | W64: 1081540443 | X64: 08-05-2026 | Y64: 03-06-2026 | Z64: 133067.5 | AA64: 133067.5 | AB64: 0 | AC64: 500 | AD64: 0 | AE64: 0 | AF64: 0 | AG64: 0 | AH64: 0 | AI64: 133067.5 | AJ64: 426239.7 | AK64: 3 | AL64: 250.8 | AM64: 0 | AR64: 0 | AS64: AREAFINANCIERA@SEMCUCUTA.GOV.CO | AT64: CARTERA | AU64: yelitza | AV64: 46164
A65: 455370 | B65: 3252 | C65: 3252 | D65: 80212710 | E65: 80212710 | F65: 890501434- 2 | G65: MUNICIPIO DE SAN JOSE DE CUCUTA - SEDE TONCHALA | H65: CALLE 10 NO 0E-16 EDF CENTRO EMPRESARIAL BLOQUE B HOTEL TONCHALA | I65: SAN MIGUEL | J65: NO | K65: COLEGIOS ZONA NORTE | L65: CÚCUTA MPO | M65: CUCUTA ZONA NORTE | N65: 1002 - CICL FACT DIRECTA CUCUTA NORTE | O65: ASEO INTEGRAL | P65: NO RESIDENCIAL - ASEO GP | Q65: OFICIAL | R65: AFORO ORDINARIO-EXTRAORDINARIO | S65: Ocupado | T65: 2026 | U65: 5 | V65: 1081522378 | W65: 1081540448 | X65: 08-05-2026 | Y65: 03-06-2026 | Z65: 164955.75 | AA65: 164955.75 | AB65: 0 | AC65: 668 | AD65: 0 | AE65: 0 | AF65: 0 | AG65: 0 | AH65: 0 | AI65: 164955.75 | AJ65: 489250.46 | AK65: 3 | AL65: 250.8 | AM65: 0 | AR65: 0 | AS65: AREAFINANCIERA@SEMCUCUTA.GOV.CO | AT65: CARTERA | AU65: yelitza | AV65: 46164
A66: 455370 | B66: 3256 | C66: 3256 | D66: 80212714 | E66: 80212714 | F66: 890501434- 2 | G66: MUNICIPIO DE SAN JOSE DE CUCUTA - SEDE TONCHALA | H66: CALLE 10 NO 0E-16 EDF CENTRO EMPRESARIAL BLOQUE B HOTEL TONCHALA | I66: COMUNEROS | J66: NO | K66: COLEGIOS ZONA NORTE | L66: CÚCUTA MPO | M66: CUCUTA ZONA NORTE | N66: 1002 - CICL FACT DIRECTA CUCUTA NORTE | O66: ASEO INTEGRAL | P66: NO RESIDENCIAL - ASEO GP | Q66: OFICIAL | R66: AFORO ORDINARIO-EXTRAORDINARIO | S66: Ocupado | T66: 2026 | U66: 5 | V66: 1081522382 | W66: 1081540452 | X66: 08-05-2026 | Y66: 03-06-2026 | Z66: 464287.7 | AA66: 464287.7 | AB66: 0 | AC66: 2245 | AD66: 0 | AE66: 0 | AF66: 0 | AG66: 0 | AH66: 0 | AI66: 464287.7 | AJ66: 1080726.4 | AK66: 3 | AL66: 250.8 | AM66: 0 | AR66: 0 | AS66: AREAFINANCIERA@SEMCUCUTA.GOV.CO | AT66: CARTERA | AU66: yelitza | AV66: 46164
A67: 455370 | B67: 3260 | C67: 3260 | D67: 80212718 | E67: 80212718 | F67: 890501434- 2 | G67: MUNICIPIO DE SAN JOSE DE CUCUTA - SEDE TONCHALA | H67: CALLE 10 NO 0E-16 EDF CENTRO EMPRESARIAL BLOQUE B HOTEL TONCHALA | I67: EL PARAISO | J67: NO | K67: COLEGIOS ZONA NORTE | L67: CÚCUTA MPO | M67: CUCUTA ZONA NORTE | N67: 1002 - CICL FACT DIRECTA CUCUTA NORTE | O67: ASEO INTEGRAL | P67: NO RESIDENCIAL - ASEO GP | Q67: OFICIAL | R67: AFORO ORDINARIO-EXTRAORDINARIO | S67: Ocupado | T67: 2026 | U67: 5 | V67: 1081522386 | W67: 1081540456 | X67: 08-05-2026 | Y67: 03-06-2026 | Z67: 86184.18 | AA67: 86184.18 | AB67: 0 | AC67: 253 | AD67: 0 | AE67: 0 | AF67: 0 | AG67: 0 | AH67: 0 | AI67: 86184.18 | AJ67: 333598.89 | AK67: 3 | AL67: 250.8 | AM67: 0 | AR67: 0 | AS67: AREAFINANCIERA@SEMCUCUTA.GOV.CO | AT67: CARTERA | AU67: yelitza | AV67: 46164
A68: 455370 | B68: 3264 | C68: 3264 | D68: 80212722 | E68: 80212722 | F68: 890501434- 2 | G68: MUNICIPIO DE SAN JOSE DE CUCUTA - SEDE TONCHALA | H68: CALLE 10 NO 0E-16 EDF CENTRO EMPRESARIAL BLOQUE B HOTEL TONCHALA | I68: LA VICTORIA | J68: NO | K68: COLEGIOS ZONA NORTE | L68: CÚCUTA MPO | M68: CUCUTA ZONA NORTE | N68: 1002 - CICL FACT DIRECTA CUCUTA NORTE | O68: ASEO INTEGRAL | P68: NO RESIDENCIAL - ASEO GP | Q68: OFICIAL | R68: AFORO ORDINARIO-EXTRAORDINARIO | S68: Ocupado | T68: 2026 | U68: 5 | V68: 1081522390 | W68: 1081540460 | X68: 08-05-2026 | Y68: 03-06-2026 | Z68: 319651.71 | AA68: 319651.71 | AB68: 0 | AC68: 1483 | AD68: 0 | AE68: 0 | AF68: 0 | AG68: 0 | AH68: 0 | AI68: 319651.71 | AJ68: 1247056.6 | AK68: 3 | AL68: 250.8 | AM68: 0 | AR68: 0 | AS68: AREAFINANCIERA@SEMCUCUTA.GOV.CO | AT68: CARTERA | AU68: yelitza | AV68: 46164
A69: 326717 | B69: 326716 | C69: 326716 | D69: 590028 | E69: 590028 | F69: 901959258-8 | G69: PRINT PACK CARIBE S.A.S | H69: AVE 4 7N - 94 1219 | I69: ZONA INDUSTRIAL | J69: NO | K69: CARIBE | L69: CÚCUTA MPO | M69: CUCUTA DIRECTA | N69: 1002 - CICL FACT DIRECTA CUCUTA NORTE | O69: ASEO INTEGRAL | P69: NO RESIDENCIAL - ASEO GP | Q69: INDUSTRIAL | R69: AFORO ORDINARIO-EXTRAORDINARIO | S69: Ocupado | T69: 2026 | U69: 5 | V69: 1081522529 | W69: 1081540599 | X69: 08-05-2026 | Y69: 03-06-2026 | Z69: 205065.8 | AA69: 205065.8 | AB69: 47322.87 | AC69: 630 | AD69: 0 | AE69: 0 | AF69: 0 | AG69: 0 | AH69: 0 | AI69: 205065.8 | AJ69: 205065.8 | AK69: 0 | AL69: 326.04 | AM69: 0 | AR69: 0 | AS69: PRINTPACKCARIBE@HOTMAIL.COM | AT69: CORREO ELECTRONICO CERTIFICADO 472 | AU69: ANGEL | AV69: 46163
A70: 326729 | B70: 326728 | C70: 326728 | D70: 590149 | E70: 590149 | F70: 800092777 | G70: GRUPO NOVA SA | H70: CL 18 N 5 62 ZN INDUSTRIAL | I70: NO REGISTRA | J70: NO | K70: GRUPO NOVA | L70: CÚCUTA MPO | M70: CUCUTA DIRECTA | N70: 1002 - CICL FACT DIRECTA CUCUTA NORTE | O70: ASEO INTEGRAL | P70: NO RESIDENCIAL - ASEO GP | Q70: INDUSTRIAL | R70: AFORO PERMANENTE | S70: Ocupado | T70: 2026 | U70: 5 | V70: 1081522532 | W70: 1081540602 | X70: 08-05-2026 | Y70: 03-06-2026 | Z70: 2635842.4 | AA70: 2635842.4 | AB70: 608271.33 | AC70: 10481 | AD70: 0 | AE70: 0 | AF70: 0 | AG70: 0 | AH70: 0 | AI70: 2622603.4 | AJ70: 2622603.4 | AK70: 0 | AL70: 326.04 | AM70: 0 | AP70: 13239 | AR70: 0 | AS70: 800092777@FACTUREINBOX.CO | AT70: CORREO ELECTRONICO CERTIFICADO 472 | AU70: ANGEL | AV70: 46169
A71: 326737 | B71: 326736 | C71: 326736 | D71: 590265 | E71: 590265 | F71: 901260249-1 | G71: TEMGLASS CUCUTA | H71: AVE 4 7N - 160 519658 | I71: ZONA INDUSTRIAL | J71: NO | K71: NO | L71: CÚCUTA MPO | M71: CUCUTA DIRECTA | N71: 1002 - CICL FACT DIRECTA CUCUTA NORTE | O71: ASEO INTEGRAL | P71: NO RESIDENCIAL - ASEO GP | Q71: INDUSTRIAL | R71: AFORO ORDINARIO-EXTRAORDINARIO | S71: Ocupado | T71: 2026 | U71: 5 | V71: 1081522536 | W71: 1081540606 | X71: 08-05-2026 | Y71: 03-06-2026 | Z71: 187054.23 | AA71: 187054.23 | AB71: 39920.25 | AC71: 500 | AD71: 14066.48 | AE71: 0 | AF71: 0 | AG71: 0 | AH71: 0 | AI71: 187054.23 | AJ71: 1181118.4 | AK71: 3 | AL71: 326.04 | AM71: 0 | AR71: 0 | AS71: CONTA.TEMGLASSCUCUTA@GMAIL.COM | AT71: CORREO ELECTRONICO CERTIFICADO 472 | AU71: Liliana | AV71: 46167
A72: 455370 | B72: 3268 | C72: 3268 | D72: 80212726 | E72: 80212726 | F72: 890501434- 2 | G72: MUNICIPIO DE SAN JOSE DE CUCUTA - SEDE TONCHALA | H72: CALLE 10 NO 0E-16 EDF CENTRO EMPRESARIAL BLOQUE B HOTEL TONCHALA | I72: CUNDINAMARCA | J72: NO | K72: COLEGIOS ZONA NORTE | L72: CÚCUTA MPO | M72: CUCUTA ZONA NORTE | N72: 1002 - CICL FACT DIRECTA CUCUTA NORTE | O72: ASEO INTEGRAL | P72: NO RESIDENCIAL - ASEO GP | Q72: OFICIAL | R72: AFORO ORDINARIO-EXTRAORDINARIO | S72: Ocupado | T72: 2026 | U72: 5 | V72: 1081522394 | W72: 1081540464 | X72: 08-05-2026 | Y72: 03-06-2026 | Z72: 133067.5 | AA72: 133067.5 | AB72: 0 | AC72: 500 | AD72: 0 | AE72: 0 | AF72: 0 | AG72: 0 | AH72: 0 | AI72: 133067.5 | AJ72: 426239.7 | AK72: 3 | AL72: 250.8 | AM72: 0 | AR72: 0 | AS72: AREAFINANCIERA@SEMCUCUTA.GOV.CO | AT72: CARTERA | AU72: yelitza | AV72: 46164
A73: 455370 | B73: 3272 | C73: 3272 | D73: 80212730 | E73: 80212730 | F73: 890501434- 2 | G73: MUNICIPIO DE SAN JOSE DE CUCUTA - SEDE TONCHALA | H73: CALLE 10 NO 0E-16 EDF CENTRO EMPRESARIAL BLOQUE B HOTEL TONCHALA | I73: SEVILLA | J73: NO | K73: COLEGIOS ZONA NORTE | L73: CÚCUTA MPO | M73: CUCUTA ZONA NORTE | N73: 1002 - CICL FACT DIRECTA CUCUTA NORTE | O73: ASEO INTEGRAL | P73: NO RESIDENCIAL - ASEO GP | Q73: OFICIAL | R73: AFORO ORDINARIO-EXTRAORDINARIO | S73: Ocupado | T73: 2026 | U73: 5 | V73: 1081522397 | W73: 1081540467 | X73: 08-05-2026 | Y73: 03-06-2026 | Z73: 322878.5 | AA73: 322878.5 | AB73: 0 | AC73: 1500 | AD73: 0 | AE73: 0 | AF73: 0 | AG73: 0 | AH73: 0 | AI73: 322878.5 | AJ73: 801303.7 | AK73: 3 | AL73: 250.8 | AM73: 0 | AR73: 0 | AS73: AREAFINANCIERA@SEMCUCUTA.GOV.CO | AT73: CARTERA | AU73: yelitza | AV73: 46164
A74: 455370 | B74: 3276 | C74: 3276 | D74: 80212734 | E74: 80212734 | F74: 890501434- 2 | G74: MUNICIPIO DE SAN JOSE DE CUCUTA - SEDE TONCHALA | H74: CALLE 10 NO 0E-16 EDF CENTRO EMPRESARIAL BLOQUE B HOTEL TONCHALA | I74: BELISARIO BETANCOURT | J74: NO | K74: COLEGIOS ZONA NORTE | L74: CÚCUTA MPO | M74: CUCUTA ZONA NORTE | N74: 1002 - CICL FACT DIRECTA CUCUTA NORTE | O74: ASEO INTEGRAL | P74: NO RESIDENCIAL - ASEO GP | Q74: OFICIAL | R74: AFORO ORDINARIO-EXTRAORDINARIO | S74: Ocupado | T74: 2026 | U74: 5 | V74: 1081522401 | W74: 1081540471 | X74: 08-05-2026 | Y74: 03-06-2026 | Z74: 133067.5 | AA74: 133067.5 | AB74: 0 | AC74: 500 | AD74: 0 | AE74: 0 | AF74: 0 | AG74: 0 | AH74: 0 | AI74: 133067.5 | AJ74: 426239.7 | AK74: 3 | AL74: 250.8 | AM74: 0 | AR74: 0 | AS74: AREAFINANCIERA@SEMCUCUTA.GOV.CO | AT74: CARTERA | AU74: yelitza | AV74: 46164
A75: 455370 | B75: 3280 | C75: 3280 | D75: 80212738 | E75: 80212738 | F75: 890501434- 2 | G75: MUNICIPIO DE SAN JOSE DE CUCUTA - SEDE TONCHALA | H75: CALLE 10 NO 0E-16 EDF CENTRO EMPRESARIAL BLOQUE B HOTEL TONCHALA | I75: SAN GERARDO | J75: NO | K75: COLEGIOS ZONA NORTE | L75: CÚCUTA MPO | M75: CUCUTA ZONA NORTE | N75: 1002 - CICL FACT DIRECTA CUCUTA NORTE | O75: ASEO INTEGRAL | P75: NO RESIDENCIAL - ASEO GP | Q75: OFICIAL | R75: AFORO ORDINARIO-EXTRAORDINARIO | S75: Ocupado | T75: 2026 | U75: 5 | V75: 1081522405 | W75: 1081540475 | X75: 08-05-2026 | Y75: 03-06-2026 | Z75: 105544.91 | AA75: 105544.91 | AB75: 0 | AC75: 355 | AD75: 0 | AE75: 0 | AF75: 0 | AG75: 0 | AH75: 0 | AI75: 105544.91 | AJ75: 371855.43 | AK75: 3 | AL75: 250.8 | AM75: 0 | AR75: 0 | AS75: AREAFINANCIERA@SEMCUCUTA.GOV.CO | AT75: CARTERA | AU75: yelitza | AV75: 46164
A76: 147 | B76: 3284 | C76: 3284 | D76: 80217309 | E76: 80217309 | F76: 800141397-5 | G76: POLICIA NACIONAL-DIRECCION LOGISTICA Y FINANCIERA | H76: AVE 3 CLL 24 GARITA # 1 | I76: EL SALADO | J76: NO | K76: POLICIA | L76: CÚCUTA MPO | M76: CUCUTA DIRECTA | N76: 1002 - CICL FACT DIRECTA CUCUTA NORTE | O76: ASEO INTEGRAL | P76: NO RESIDENCIAL - ASEO GP | Q76: OFICIAL | R76: AFORO ORDINARIO-EXTRAORDINARIO | S76: Ocupado | T76: 2026 | U76: 5 | V76: 1081522409 | W76: 1081540479 | X76: 08-05-2026 | Y76: 03-06-2026 | Z76: 86089.29 | AA76: 86089.29 | AB76: 0 | AC76: 252.5 | AD76: 0 | AE76: 0 | AF76: 0 | AG76: 0 | AH76: 0 | AI76: 86089.29 | AJ76: 170944.69 | AK76: 1 | AL76: 250.8 | AM76: 0 | AR76: 0 | AS76: MECUC.GUBIR@POLICIA.GOV.CO | AT76: CORREO ELECTRONICO CERTIFICADO 472 | AU76: ANGEL | AV76: 46163
A77: 147 | B77: 3288 | C77: 3288 | D77: 80217313 | E77: 80217313 | F77: 800141397-5 | G77: POLICIA NACIONAL-DIRECCION LOGISTICA Y FINANCIERA | H77: AVE 3 CLL 24 GARITA # 1 | I77: NI¿A CECI | J77: NO | K77: POLICIA | L77: CÚCUTA MPO | M77: CUCUTA DIRECTA | N77: 1002 - CICL FACT DIRECTA CUCUTA NORTE | O77: ASEO INTEGRAL | P77: NO RESIDENCIAL - ASEO GP | Q77: OFICIAL | R77: AFORO ORDINARIO-EXTRAORDINARIO | S77: Ocupado | T77: 2026 | U77: 5 | V77: 1081522412 | W77: 1081540482 | X77: 08-05-2026 | Y77: 03-06-2026 | Z77: 86089.29 | AA77: 86089.29 | AB77: 0 | AC77: 252.5 | AD77: 0 | AE77: 0 | AF77: 0 | AG77: 0 | AH77: 0 | AI77: 86089.29 | AJ77: 170944.69 | AK77: 1 | AL77: 250.8 | AM77: 0 | AR77: 0 | AS77: MECUC.GUBIR@POLICIA.GOV.CO | AT77: CORREO ELECTRONICO CERTIFICADO 472 | AU77: ANGEL | AV77: 46163
A78: 455370 | B78: 3292 | C78: 3292 | D78: 80218484 | E78: 80218484 | F78: 890501434- 2 | G78: MUNICIPIO DE SAN JOSE DE CUCUTA - SEDE TONCHALA | H78: CALLE 10 NO 0E-16 EDF CENTRO EMPRESARIAL BLOQUE B HOTEL TONCHALA | I78: NUEVO HORIZONTE | J78: NO | K78: COLEGIOS ZONA NORTE | L78: CÚCUTA MPO | M78: CUCUTA ZONA NORTE | N78: 1002 - CICL FACT DIRECTA CUCUTA NORTE | O78: ASEO INTEGRAL | P78: NO RESIDENCIAL - ASEO GP | Q78: OFICIAL | R78: AFORO ORDINARIO-EXTRAORDINARIO | S78: Ocupado | T78: 2026 | U78: 5 | V78: 1081522416 | W78: 1081540486 | X78: 08-05-2026 | Y78: 03-06-2026 | Z78: 397474.22 | AA78: 397474.22 | AB78: 0 | AC78: 1893 | AD78: 0 | AE78: 0 | AF78: 0 | AG78: 0 | AH78: 0 | AI78: 397474.22 | AJ78: 948703.85 | AK78: 3 | AL78: 250.8 | AM78: 0 | AR78: 0 | AS78: AREAFINANCIERA@SEMCUCUTA.GOV.CO | AT78: CARTERA | AU78: yelitza | AV78: 46164
A79: 455370 | B79: 3296 | C79: 3296 | D79: 80218697 | E79: 80218697 | F79: 890501434- 2 | G79: MUNICIPIO DE SAN JOSE DE CUCUTA - SEDE TONCHALA | H79: CALLE 10 NO 0E-16 EDF CENTRO EMPRESARIAL BLOQUE B HOTEL TONCHALA | I79: CARLOS RAMIREZ PARIS | J79: NO | K79: COLEGIOS ZONA NORTE | L79: CÚCUTA MPO | M79: CUCUTA ZONA NORTE | N79: 1002 - CICL FACT DIRECTA CUCUTA NORTE | O79: ASEO INTEGRAL | P79: NO RESIDENCIAL - ASEO GP | Q79: OFICIAL | R79: AFORO ORDINARIO-EXTRAORDINARIO | S79: Ocupado | T79: 2026 | U79: 5 | V79: 1081522420 | W79: 1081540490 | X79: 08-05-2026 | Y79: 03-06-2026 | Z79: 86184.18 | AA79: 86184.18 | AB79: 0 | AC79: 253 | AD79: 0 | AE79: 0 | AF79: 0 | AG79: 0 | AH79: 0 | AI79: 86184.18 | AJ79: 333598.89 | AK79: 3 | AL79: 250.8 | AM79: 0 | AR79: 0 | AS79: AREAFINANCIERA@SEMCUCUTA.GOV.CO | AT79: CARTERA | AU79: yelitza | AV79: 46164
A80: 455370 | B80: 3300 | C80: 3300 | D80: 80222597 | E80: 80222597 | F80: 890501434- 2 | G80: MUNICIPIO DE SAN JOSE DE CUCUTA - SEDE TONCHALA | H80: CALLE 10 NO 0E-16 EDF CENTRO EMPRESARIAL BLOQUE B HOTEL TONCHALA | I80: BARRIO NO LISTADO | J80: NO | K80: COLEGIOS ZONA NORTE | L80: CÚCUTA MPO | M80: CUCUTA ZONA NORTE | N80: 1002 - CICL FACT DIRECTA CUCUTA NORTE | O80: ASEO INTEGRAL | P80: NO RESIDENCIAL - ASEO GP | Q80: OFICIAL | R80: AFORO ORDINARIO-EXTRAORDINARIO | S80: Ocupado | T80: 2026 | U80: 5 | V80: 1081522424 | W80: 1081540494 | X80: 08-05-2026 | Y80: 03-06-2026 | Z80: 86184.18 | AA80: 86184.18 | AB80: 0 | AC80: 253 | AD80: 0 | AE80: 0 | AF80: 0 | AG80: 0 | AH80: 0 | AI80: 86184.18 | AJ80: 333598.89 | AK80: 3 | AL80: 250.8 | AM80: 0 | AR80: 0 | AS80: AREAFINANCIERA@SEMCUCUTA.GOV.CO | AT80: CARTERA | AU80: yelitza | AV80: 46164
A81: 3309 | B81: 3308 | C81: 3308 | D81: 80228953 | E81: 80228953 | F81: 8507015 | G81: RODSAN Y ASOCIADOS LTDA | H81: AV LIBERT CC UNICENTRO LOC 88 | I81: PRADOS NORTE | J81: NO | K81: NO | L81: CÚCUTA MPO | M81: CUCUTA DIRECTA | N81: 1002 - CICL FACT DIRECTA CUCUTA NORTE | O81: ASEO INTEGRAL | P81: NO RESIDENCIAL - ASEO GP | Q81: COMERCIAL | R81: AFORO ORDINARIO-EXTRAORDINARIO | S81: Ocupado | T81: 2026 | U81: 5 | V81: 1081522428 | W81: 1081540498 | X81: 08-05-2026 | Y81: 03-06-2026 | Z81: 419873.22 | AA81: 419873.22 | AB81: 87887.5 | AC81: 725 | AD81: 156210.74 | AE81: 0 | AF81: 0 | AG81: 0 | AH81: 0 | AI81: 419873.22 | AJ81: 11157766 | AK81: 36 | AL81: 376.2 | AM81: 0 | AR81: 0 | AS81: loysa88@yahoo.es | AT81: CORREO ELECTRONICO CERTIFICADO 472 | AU81: Liliana | AV81: 46167
A82: 147 | B82: 3312 | C82: 3312 | D82: 80230161 | E82: 80230161 | F82: 800141397-5 | G82: POLICIA NACIONAL-DIRECCION LOGISTICA Y FINANCIERA | H82: AVE 3 CLL 24 GARITA # 1 | I82: URB TASAJERO | J82: NO | K82: POLICIA | L82: CÚCUTA MPO | M82: CUCUTA DIRECTA | N82: 1002 - CICL FACT DIRECTA CUCUTA NORTE | O82: ASEO INTEGRAL | P82: NO RESIDENCIAL - ASEO GP | Q82: OFICIAL | R82: AFORO PERMANENTE | S82: Ocupado | T82: 2026 | U82: 5 | V82: 1081522433 | W82: 1081540503 | X82: 08-05-2026 | Y82: 03-06-2026 | Z82: 1587494.3 | AA82: 1587494.3 | AB82: 0 | AC82: 8162.5 | AD82: 0 | AE82: 0 | AF82: 0 | AG82: 0 | AH82: 0 | AI82: 1587494.3 | AJ82: 10166243 | AK82: 5 | AL82: 250.8 | AM82: 0 | AR82: 0 | AS82: MECUC.GUBIR@POLICIA.GOV.CO | AT82: CORREO ELECTRONICO CERTIFICADO 472 | AU82: ANGEL | AV82: 46163
A83: 3317 | B83: 3316 | C83: 3316 | D83: 80231078 | E83: 80231078 | F83: 901338746 | G83: PROM DE INVERSIONES H Y A QUEMBA & BARON SAS - HIELOS LA SABANA CUCUTA | H83: AVE 5 2 - 78 1007 | I83: LATINO | J83: CENTRO | K83: CENTRO | L83: CÚCUTA MPO | M83: CUCUTA DIRECTA | N83: 1002 - CICL FACT DIRECTA CUCUTA NORTE | O83: ASEO INTEGRAL | P83: NO RESIDENCIAL - ASEO GP | Q83: INDUSTRIAL | R83: AFORO ORDINARIO-EXTRAORDINARIO | S83: Ocupado | T83: 2026 | U83: 5 | V83: 1081522437 | W83: 1081540507 | X83: 08-05-2026 | Y83: 03-06-2026 | Z83: 803388.89 | AA83: 803388.89 | AB83: 68391.9 | AC83: 1000 | AD83: 507023.99 | AE83: 0 | AF83: 0 | AG83: 0 | AH83: 0 | AI83: 803388.89 | AJ83: 50331968 | AK83: 125 | AL83: 326.04 | AM83: 0 | AR83: 0 | AS83: HIELOLASABANACUCUTALTDA@HOTMAIL.COM | AT83: VERIFICADOR | AU83: ARIDE | AV83: 46163
A84: 3321 | B84: 3320 | C84: 3320 | D84: 80231096 | E84: 80231096 | F84: 590029 | G84: DIVERSIONES DEL ORIENTE S.A. | H84: AVE LIBERTADORES C.C UNICENTRO - LOCAL 1 1 | I84: PRADOS NORTE | J84: NO | K84: NO | L84: CÚCUTA MPO | M84: CUCUTA DIRECTA | N84: 1002 - CICL FACT DIRECTA CUCUTA NORTE | O84: ASEO INTEGRAL | P84: NO RESIDENCIAL - ASEO GP | Q84: COMERCIAL | R84: AFORO ORDINARIO-EXTRAORDINARIO | S84: Ocupado | T84: 2026 | U84: 5 | V84: 1081522446 | W84: 1081540516 | X84: 08-05-2026 | Y84: 03-06-2026 | Z84: 263662.48 | AA84: 263662.48 | AB84: 87887.5 | AC84: 725 | AD84: 0 | AE84: 0 | AF84: 0 | AG84: 0 | AH84: 0 | AI84: 204474.4 | AJ84: 204474.4 | AK84: 0 | AL84: 376.2 | AM84: 0 | AP84: 59188.08 | AR84: 0 | AS84: FACTURACION@DIVERSIONESDELORIENTE.COM | AT84: CORREO ELECTRONICO CERTIFICADO 472 | AU84: Liliana | AV84: 46167
A85: 3329 | B85: 3328 | C85: 3328 | D85: 80256518 | E85: 80256518 | F85: 900770019 | G85: C.I. INDUBOLSAS CONTRERAS J Y T S.A.S. | H85: KDX 25 6-B (CALLE 0B 7A-131) PANAMERICANO | I85: PANAMERICANO | J85: NO | K85: NO | L85: CÚCUTA MPO | M85: CUCUTA DIRECTA | N85: 1002 - CICL FACT DIRECTA CUCUTA NORTE | O85: ASEO INTEGRAL | P85: NO RESIDENCIAL - ASEO GP | Q85: COMERCIAL | R85: AFORO PERMANENTE | S85: Ocupado | T85: 2026 | U85: 5 | V85: 1081522448 | W85: 1081540518 | X85: 08-05-2026 | Y85: 03-06-2026 | Z85: 655147.65 | AA85: 655147.65 | AB85: 218382.55 | AC85: 2100 | AD85: 0 | AE85: 0 | AF85: 0 | AG85: 0 | AH85: 0 | AI85: 655147.08 | AJ85: 655147.08 | AK85: 0 | AL85: 376.2 | AM85: 0 | AP85: 0.57 | AR85: 0 | AS85: FACTURACION@BOLSAGREEN.COM | AT85: CORREO ELECTRONICO CERTIFICADO 472 | AU85: Liliana | AV85: 46167
A86: 147 | B86: 333928 | C86: 333928 | D86: 670211 | E86: 670211 | F86: 800141397-5 | G86: POLICIA NACIONAL-DIRECCION LOGISTICA Y FINANCIERA | H86: AVE 3 CLL 24 GARITA # 1 | I86: BENJAMIN HERRERA | J86: NO | K86: POLICIA | L86: CÚCUTA MPO | M86: CUCUTA DIRECTA | N86: 1002 - CICL FACT DIRECTA CUCUTA NORTE | O86: ASEO INTEGRAL | P86: NO RESIDENCIAL - ASEO GP | Q86: OFICIAL | R86: AFORO PERMANENTE | S86: Ocupado | T86: 2026 | U86: 5 | V86: 1081522540 | W86: 1081540610 | X86: 08-05-2026 | Y86: 03-06-2026 | Z86: 664538.3 | AA86: 664538.3 | AB86: 0 | AC86: 3300 | AD86: 0 | AE86: 0 | AF86: 0 | AG86: 0 | AH86: 0 | AI86: 664538.3 | AJ86: 1008284.8 | AK86: 1 | AL86: 250.8 | AM86: 0 | AR86: 0 | AS86: MECUC.GUBIR@POLICIA.GOV.CO | AT86: CORREO ELECTRONICO CERTIFICADO 472 | AU86: ANGEL | AV86: 46163
A87: 334101 | B87: 334100 | C87: 334100 | D87: 674332 | E87: 674332 | F87: 901959814-3 | G87: VBC CARIBE S.A.S | H87: AVE 4 8AN - 79 | I87: ZONA INDUSTRIAL | J87: NO | K87: CARIBE | L87: CÚCUTA MPO | M87: CUCUTA DIRECTA | N87: 1002 - CICL FACT DIRECTA CUCUTA NORTE | O87: ASEO INTEGRAL | P87: NO RESIDENCIAL - ASEO GP | Q87: COMERCIAL | R87: AFORO ORDINARIO-EXTRAORDINARIO | S87: Ocupado | T87: 2026 | U87: 5 | V87: 1081522544 | W87: 1081540614 | X87: 08-05-2026 | Y87: 03-06-2026 | Z87: 149775.88 | AA87: 149775.88 | AB87: 49925.3 | AC87: 325 | AD87: 0 | AE87: 0 | AF87: 0 | AG87: 0 | AH87: 0 | AI87: 149775.88 | AJ87: 149775.88 | AK87: 0 | AL87: 376.2 | AM87: 0 | AR87: 0 | AS87: PRINTPACKCARIBE@HOTMAIL.COM | AT87: CORREO ELECTRONICO CERTIFICADO 472 | AU87: ANGEL | AV87: 46163
A88: 365543 | B88: 360848 | C88: 362426 | D88: 1035546 | E88: 1035546 | F88: 1090525771 | G88: MARIA FERNANDA RANGEL CARVAJAL | H88: MNZ D LTE 21 A LOC 6 274 | I88: NUEVA ILUSION | J88: NO | K88: NO | L88: CÚCUTA MPO | M88: CUCUTA DIRECTA | N88: 1002 - CICL FACT DIRECTA CUCUTA NORTE | O88: 720 ASEO ESPECIAL DESOCUPADO | P88: RESIDENCIAL | Q88: ESTRATO 1 | R88: NO AFORADO | S88: Ocupado | T88: 2026 | U88: 5 | V88: 1081522547 | W88: 1081540617 | X88: 08-05-2026 | Y88: 03-06-2026 | Z88: 30080.82 | AA88: 30080.82 | AB88: -8985.18 | AC88: 0 | AD88: 0 | AE88: 0 | AF88: 0 | AG88: 0 | AH88: 0 | AI88: 0 | AJ88: 0 | AK88: 0 | AL88: 193.12 | AM88: 0 | AP88: 30080.82 | AR88: 77.18 | AS88: SUPERMERCADOELBOON@GMAIL.COM; LEIDYCONTRERAS1994@GMAIL.COM | AT88: CORREO ELECTRONICO CERTIFICADO 472 | AU88: Liliana | AV88: 46167
A89: 285191 | B89: 365836 | C89: 371462 | D89: 1043375 | E89: 1043375 | F89: 900276962 | G89: D1 S A S | H89: KDX 73-2 1116 | I89: URB TASAJERO | J89: NO | K89: D1 | L89: CÚCUTA MPO | M89: CUCUTA DIRECTA | N89: 1002 - CICL FACT DIRECTA CUCUTA NORTE | O89: ASEO INTEGRAL | P89: NO RESIDENCIAL - ASEO PP | Q89: COMERCIAL RANGO 3 | R89: NO AFORADO | S89: Ocupado | T89: 2026 | U89: 5 | V89: 1081522554 | W89: 1081540624 | X89: 08-05-2026 | Y89: 03-06-2026 | Z89: 113911.5 | AA89: 113911.5 | AB89: 37970.5 | AC89: 0 | AD89: 0 | AE89: 0 | AF89: 0 | AG89: 0 | AH89: 0 | AI89: 113911.5 | AJ89: 113911.5 | AK89: 0 | AL89: 376.2 | AM89: 0 | AR89: 0 | AS89: ALBA.CELIS@D1.COM.CO;CARMEN.DAVILA@D1.COM.CO | AT89: CORREO ELECTRONICO CERTIFICADO 472 | AU89: ANGEL | AV89: 46163
A90: 382325 | B90: 367988 | C90: 375272 | D90: 1036713 | E90: 1036713 | F90: 900495013 | G90: BACCA RODRIGUEZ SAS | H90: AVE 9 0A-72 1219 | I90: ZONA INDUSTRIAL | J90: NO | K90: NO | L90: CÚCUTA MPO | M90: CUCUTA DIRECTA | N90: 1002 - CICL FACT DIRECTA CUCUTA NORTE | O90: ASEO INTEGRAL | P90: NO RESIDENCIAL - ASEO PP | Q90: COMERCIAL RANGO 3 | R90: NO AFORADO | S90: Ocupado | T90: 2026 | U90: 5 | V90: 1081522557 | W90: 1081540627 | X90: 08-05-2026 | Y90: 03-06-2026 | Z90: 129389.55 | AA90: 129389.55 | AB90: 37970.5 | AC90: 0 | AD90: 15478.05 | AE90: 0 | AF90: 0 | AG90: 0 | AH90: 0 | AI90: 129389.55 | AJ90: 1078261.2 | AK90: 7 | AL90: 376.2 | AM90: 0 | AR90: 0 | AS90: NEBACCA@HOTMAIL.COM;TALENTOHUMANONEBACCA@GMAIL.COM | AT90: CORREO ELECTRONICO CERTIFICADO 472 | AU90: Liliana | AV90: 46167
A91: 3209 | B91: 424660 | C91: 440301 | D91: 1033314 | E91: 1033314 | F91: 901375954 | G91: POLIMEROS ANDECOL DC S.A.S | H91: AV 7 1 136 BRR LA INSULA | I91: LA INSULA | J91: ZONA NORTE | K91: NO | L91: CÚCUTA MPO | M91: CUCUTA DIRECTA | N91: 1002 - CICL FACT DIRECTA CUCUTA NORTE | O91: ASEO INTEGRAL | P91: NO RESIDENCIAL - ASEO PP | Q91: COMERCIAL RANGO 3 | R91: NO AFORADO | S91: Ocupado | T91: 2026 | U91: 5 | V91: 1081522561 | W91: 1081540631 | X91: 08-05-2026 | Y91: 03-06-2026 | Z91: 117405.93 | AA91: 117405.93 | AB91: 37970.5 | AC91: 0 | AD91: 3494.43 | AE91: 0 | AF91: 0 | AG91: 0 | AH91: 0 | AI91: 117405.93 | AJ91: 450918.18 | AK91: 3 | AL91: 376.2 | AM91: 0 | AR91: 0 | AS91: FACTURACION.ANDECOL@GMAIL.COM | AT91: VERIFICADOR | AU91: MARTIN | AV91: 46163
A92: 699 | B92: 436688 | C92: 459905 | D92: 1092716 | E92: 1092716 | F92: 900480569 | G92: JERONIMO MARTINS COLOMBIA SAS | H92: CLL 12 4-52 CENTRO | I92: CHAPINERO | J92: NO | K92: ARA CUCUTA | L92: CÚCUTA MPO | M92: CUCUTA ZONA NORTE | N92: 1002 - CICL FACT DIRECTA CUCUTA NORTE | O92: ASEO INTEGRAL | P92: NO RESIDENCIAL - ASEO PP | Q92: COMERCIAL RANGO 1 | R92: NO AFORADO | S92: Ocupado | T92: 2026 | U92: 5 | V92: 1081522565 | W92: 1081540635 | X92: 08-05-2026 | Y92: 03-06-2026 | Z92: 76141.5 | AA92: 76141.5 | AB92: 25380.5 | AC92: 0 | AD92: 0 | AE92: 0 | AF92: 0 | AG92: 0 | AH92: 0 | AI92: 76141.5 | AJ92: 151704 | AK92: 1 | AL92: 376.2 | AM92: 0 | AR92: 0 | AS92: COORDINADOR.OPERACIONES.R11@JERONIMO-MARTINS.COM | AT92: CORREO ELECTRONICO CERTIFICADO 472 | AU92: ANGEL | AV92: 46163
A93: 595127 | B93: 498508 | C93: 551613 | F93: 1254985 | G93: ESPERANZA CASTRO MUNEVAR | H93: CLL 14AN 4A-81 TORRE 1 APTO 101 | I93: PORTACHUELO | J93: CR PORTACHUELO | K93: CR PORTACHUELO | L93: CÚCUTA MPO | M93: CUCUTA DIRECTA | N93: 1002 - CICL FACT DIRECTA CUCUTA NORTE | O93: ASEO INTEGRAL | P93: RESIDENCIAL | Q93: ESTRATO 3 | R93: NO AFORADO | S93: Ocupado | T93: 2026 | U93: 5 | V93: 1081522569 | W93: 1081540639 | X93: 08-05-2026 | Y93: 03-06-2026 | Z93: 50434.76 | AA93: 50434.76 | AB93: -1667.24 | AC93: 0 | AD93: 0 | AE93: 0 | AF93: 0 | AG93: 0 | AH93: 0 | AI93: 50434.76 | AJ93: 50434.76 | AK93: 0 | AL93: 242.77 | AM93: 0 | AR93: 0 | AT93: VERIFICADOR | AU93: MARTIN | AV93: 46164
A94: 595131 | B94: 498512 | C94: 551617 | F94: 1254989 | G94: ESPERANZA CASTRO MUNEVAR | H94: CLL 14AN 4A-81 TORRE 1 APTO 201 | I94: PORTACHUELO | J94: CR PORTACHUELO | K94: CR PORTACHUELO | L94: CÚCUTA MPO | M94: CUCUTA DIRECTA | N94: 1002 - CICL FACT DIRECTA CUCUTA NORTE | O94: ASEO INTEGRAL | P94: RESIDENCIAL | Q94: ESTRATO 3 | R94: NO AFORADO | S94: Ocupado | T94: 2026 | U94: 5 | V94: 1081522575 | W94: 1081540645 | X94: 08-05-2026 | Y94: 03-06-2026 | Z94: 50434.76 | AA94: 50434.76 | AB94: -1667.24 | AC94: 0 | AD94: 0 | AE94: 0 | AF94: 0 | AG94: 0 | AH94: 0 | AI94: 50434.76 | AJ94: 50434.76 | AK94: 0 | AL94: 242.77 | AM94: 0 | AR94: 0 | AT94: VERIFICADOR | AU94: MARTIN | AV94: 46164
A95: 595135 | B95: 498516 | C95: 551621 | F95: 1254993 | G95: JORGE IVAN SOTO ZULUAGA | H95: CLL 14AN 4A-81 TORRE 1 APTO 301 | I95: PORTACHUELO | J95: CR PORTACHUELO | K95: CR PORTACHUELO | L95: CÚCUTA MPO | M95: CUCUTA DIRECTA | N95: 1002 - CICL FACT DIRECTA CUCUTA NORTE | O95: ASEO INTEGRAL | P95: RESIDENCIAL | Q95: ESTRATO 3 | R95: NO AFORADO | S95: Ocupado | T95: 2026 | U95: 5 | V95: 1081522577 | W95: 1081540647 | X95: 08-05-2026 | Y95: 03-06-2026 | Z95: 50434.76 | AA95: 50434.76 | AB95: -1667.24 | AC95: 0 | AD95: 0 | AE95: 0 | AF95: 0 | AG95: 0 | AH95: 0 | AI95: 50434.76 | AJ95: 50434.76 | AK95: 0 | AL95: 242.77 | AM95: 0 | AR95: 0 | AT95: VERIFICADOR | AU95: MARTIN | AV95: 46164
A96: 595139 | B96: 498520 | C96: 551625 | F96: 1254997 | G96: ANGELA PERUTTI ARAQUE | H96: CLL 14AN 4A-81 TORRE 1 APTO 401 | I96: PORTACHUELO | J96: CR PORTACHUELO | K96: CR PORTACHUELO | L96: CÚCUTA MPO | M96: CUCUTA DIRECTA | N96: 1002 - CICL FACT DIRECTA CUCUTA NORTE | O96: ASEO INTEGRAL | P96: RESIDENCIAL | Q96: ESTRATO 3 | R96: NO AFORADO | S96: Ocupado | T96: 2026 | U96: 5 | V96: 1081522580 | W96: 1081540650 | X96: 08-05-2026 | Y96: 03-06-2026 | Z96: 50598.63 | AA96: 50598.63 | AB96: -1667.24 | AC96: 0 | AD96: 163.87 | AE96: 0 | AF96: 0 | AG96: 0 | AH96: 0 | AI96: 50598.63 | AJ96: 100942.83 | AK96: 1 | AL96: 242.77 | AM96: 0 | AR96: 0 | AT96: VERIFICADOR | AU96: MARTIN | AV96: 46164
A97: 595143 | B97: 498524 | C97: 551629 | F97: 1255001 | G97: FEDERICO GARCIA QUIÑONES | H97: CLL 14AN 4A-81 TORRE 2 APTO 101 | I97: PORTACHUELO | J97: CR PORTACHUELO | K97: CR PORTACHUELO | L97: CÚCUTA MPO | M97: CUCUTA DIRECTA | N97: 1002 - CICL FACT DIRECTA CUCUTA NORTE | O97: ASEO INTEGRAL | P97: RESIDENCIAL | Q97: ESTRATO 3 | R97: NO AFORADO | S97: Ocupado | T97: 2026 | U97: 5 | V97: 1081522584 | W97: 1081540654 | X97: 08-05-2026 | Y97: 03-06-2026 | Z97: 50434.76 | AA97: 50434.76 | AB97: -1667.24 | AC97: 0 | AD97: 0 | AE97: 0 | AF97: 0 | AG97: 0 | AH97: 0 | AI97: 50434.76 | AJ97: 50434.76 | AK97: 0 | AL97: 242.77 | AM97: 0 | AR97: 0 | AT97: VERIFICADOR | AU97: MARTIN | AV97: 46164
A98: 595147 | B98: 498528 | C98: 551633 | F98: 1255005 | G98: JAMES ENRIQUE CASAS | H98: CLL 14AN 4A-81 TORRE 2 APTO 201 | I98: PORTACHUELO | J98: CR PORTACHUELO | K98: CR PORTACHUELO | L98: CÚCUTA MPO | M98: CUCUTA DIRECTA | N98: 1002 - CICL FACT DIRECTA CUCUTA NORTE | O98: ASEO INTEGRAL | P98: RESIDENCIAL | Q98: ESTRATO 3 | R98: NO AFORADO | S98: Ocupado | T98: 2026 | U98: 5 | V98: 1081522588 | W98: 1081540658 | X98: 08-05-2026 | Y98: 03-06-2026 | Z98: 53638.77 | AA98: 53638.77 | AB98: -1667.24 | AC98: 0 | AD98: 3204.01 | AE98: 0 | AF98: 0 | AG98: 0 | AH98: 0 | AI98: 53638.77 | AJ98: 283504.12 | AK98: 5 | AL98: 242.77 | AM98: 0 | AR98: 0 | AT98: VERIFICADOR | AU98: MARTIN | AV98: 46164
A99: 595151 | B99: 498532 | C99: 551637 | F99: 1255009 | G99: MARIA BELEN RINCON VARGAS | H99: CLL 14AN 4A-81 TORRE 2 APTO 301 | I99: PORTACHUELO | J99: CR PORTACHUELO | K99: CR PORTACHUELO | L99: CÚCUTA MPO | M99: CUCUTA DIRECTA | N99: 1002 - CICL FACT DIRECTA CUCUTA NORTE | O99: ASEO INTEGRAL | P99: RESIDENCIAL | Q99: ESTRATO 3 | R99: NO AFORADO | S99: Ocupado | T99: 2026 | U99: 5 | V99: 1081522592 | W99: 1081540662 | X99: 08-05-2026 | Y99: 03-06-2026 | Z99: 50434.76 | AA99: 50434.76 | AB99: -1667.24 | AC99: 0 | AD99: 0 | AE99: 0 | AF99: 0 | AG99: 0 | AH99: 0 | AI99: 50434.76 | AJ99: 50434.76 | AK99: 0 | AL99: 242.77 | AM99: 0 | AR99: 0 | AT99: VERIFICADOR | AU99: MARTIN | AV99: 46164
A100: 595155 | B100: 498536 | C100: 551641 | F100: 1255013 | G100: NEREIDA GRANADOS - JOSE ALFONSO PEÑARANDA LOZANO | H100: CLL 14AN 4A-81 TORRE 2 APTO 401 | I100: PORTACHUELO | J100: CR PORTACHUELO | K100: CR PORTACHUELO | L100: CÚCUTA MPO | M100: CUCUTA DIRECTA | N100: 1002 - CICL FACT DIRECTA CUCUTA NORTE | O100: ASEO INTEGRAL | P100: RESIDENCIAL | Q100: ESTRATO 3 | R100: NO AFORADO | S100: Ocupado | T100: 2026 | U100: 5 | V100: 1081522595 | W100: 1081540665 | X100: 08-05-2026 | Y100: 03-06-2026 | Z100: 50434.76 | AA100: 50434.76 | AB100: -1667.24 | AC100: 0 | AD100: 0 | AE100: 0 | AF100: 0 | AG100: 0 | AH100: 0 | AI100: 50434.76 | AJ100: 50434.76 | AK100: 0 | AL100: 242.77 | AM100: 0 | AR100: 0 | AT100: VERIFICADOR | AU100: MARTIN | AV100: 46164
...
